Workbook

Sheet 安装及设备购置费四厂对比表
A1: 安装及设备购置费四厂对比表
A2: 序号 | B2: 工程或费用名称 | C2: 南站水厂 | I2: 环城北金额 | K2: 洛溪厂（首期） | M2: 中部大龙水厂金额 | O2: 偏差原因分析
C3: 首期 | E3: 二期预估 | G3: 总厂
C4: 安装费 （万元） | D4: 设备购置费 （万元） | E4: 安装费 （万元） | F4: 设备购置费 （万元） | G4: 安装费 （万元） | H4: 设备购置费 （万元） | I4: 安装费 （万元） | J4: 设备购置费 （万元） | K4: 安装费 （万元） | L4: 设备购置费 （万元） | M4: 安装费 （万元） | N4: 设备购置费 （万元）
B5: 污水处理规模（万吨/日） | C5: 5 | E5: 5 | G5: 10 | I5: 10 | K5: 5 | M5: 10
B6: 工艺 | C6: AAO+MBR | I6: AAO+MBR | K6: AAO+MBR | M6: A/A/O-AO
B7: K设计 | C7: 1.5 | I7: 1.5 | K7: 1.3 | M7: 1.5
B8: 安装专业工程费用 | C8: ==C9+C20+C42 -> 4363.3216 | D8: ==D9+D20+D42 -> 13067.646 | E8: ==E9+E20+E42 -> 525.07221 | F8: ==F9+F20+F42 -> 7780.2228 | G8: ==G9+G20+G42 -> 4888.3938 | H8: ==H9+H20+H42 -> 20847.869 | I8: ==I9+I20+I42 -> 7656.68 | J8: ==J9+J20+J42 -> 20780.036 | ... N8: ==N9+N20+N42 -> 15425.084
A9: (一) | B9: 南站水厂的甲供设备部分 | C9: ==SUM(C10:C19) -> 0 | D9: ==SUM(D10:D19) -> 8933.8691 | E9: ==SUM(E10:E19) -> 0 | F9: ==SUM(F10:F19) -> 6308.7907 | G9: ==SUM(G10:G19) -> 0 | H9: ==SUM(H10:H19) -> 15242.66 | I9: ==SUM(I10:I19) -> 985.62 | J9: ==SUM(J10:J19) -> 12014.446 | ... L9: ==SUM(L10:L19) -> 7934.4139 | N9: ==SUM(N10:N19) -> 5879.6848
A10: 1 | B10: 提升泵及配套设备 （首期66%、远期34%） | C10: 0 | D10: ==甲供设备!L6/10000 -> 170.33371 | E10: 0 | F10: ==甲供设备!L7/10000 -> 99.954838 | G10: 0 | H10: ==D10+F10 -> 270.28855 | I10: 0 | J10: ==甲供设备!N6/10000 -> 114.9012 | K10: 0 | L10: ==甲供设备!R6/10000 -> 136.5891 | M10: / | N10: ==甲供设备!P6/10000 -> 220 | O10: 环城北：3台（Q=1300m3/h,H=25m）； 南站水厂：6台（4台Q=2083m3/h，H=9.5m、2台Q=1041m3/h，H=9.5m）； 中部净水厂：5台（Q=1565m3/h，H=9.0m） 洛溪首期：5台（3台Q=1460m3/h，H=6.0m、2台Q=1880m3/h，H=6.0m）； 结论：1、经对比分析，“南站”、“洛溪”和“中部”设备配置及价值水平基本一致； 2、“环城北”水泵设置在放空泵房，水泵投入数量、过水量偏差太大，不具备可比性。 | Q10: 近期4台，远期安装2台
A11: 2 | B11: 内进流格栅除污机及其配套设备 （首期66%、远期34%） | C11: 0 | D11: ==甲供设备!L9/10000 -> 400.72796 | E11: 0 | F11: ==甲供设备!K10/10000+甲供设备!K15*2/10000 -> 207.02453 | G11: 0 | H11: ==D11+F11 -> 607.75249 | I11: 0 | J11: ==甲供设备!N9/10000 -> 569.66 | K11: 0 | L11: ==甲供设备!R9/10000 -> 718.4068 | M11: / | N11: ==甲供设备!P9/10000 -> 510 | O11: 环城北：5套细格栅（Q=1565m3/h，b=5mm）+5套膜格栅（Q=1565m3/h，b=1mm）； 南站水厂：4套细格栅（Q≥2100m3/h，b=5mm）+5膜格栅（Q≥1580m3/h，b=1mm）； 中部净水厂：3套细格栅（Q=3125m3/h，b=6mm）+4膜格栅（Q=2100m3/h，b=2mm） 洛溪首期：3套细格栅（Q=2917m3/h，b=3mm）+3套膜格栅（Q=1436m3/h，b=1mm）； 结论：1、膜格栅：“南站水厂”与“环城北”选用品牌档次不一致，价格水平不具备可比性。 2、经对比分析，“南站水厂”与“中部水厂”设备配置及价值水平基本一致。 | P11: 膜格栅：洛溪用的品牌都是进口的 | Q11: 细格栅近期3台，远期安装1台；膜格栅近期3台，远期安装2台
A12: 3 | B12: 立式搅拌器及配套设备 （首期50%、远期50%） | C12: 0 | D12: ==甲供设备!L20/10000 -> 100.77875 | E12: 0 | F12: ==甲供设备!L20/5*4/10000 -> 80.623 | G12: 0 | H12: ==D12+F12 -> 181.40175 | I12: 0 | J12: ==甲供设备!N20/10000 -> 165 | K12: 0 | L12: ==甲供设备!R20/10000 -> 124.839 | M12: / | N12: ==甲供设备!P20/10000 -> 69 | O12: 环城北：30台潜水搅拌器（D=580mm）+26台潜水推进器（D=2500mm）； 南站水厂：9台潜水搅拌器（D=4000mm）+9台潜水推流器； 中部净水厂：6台潜水搅拌器（D=650mm）+16台潜水推流器； 洛溪首期：15台潜水搅拌器+3台潜水推进器； 结论：经过对比分析，“南站水厂”、“中部水厂”及“环城北”在设备投入数量、规格参数上都不具备可比性。 | Q12: 近期5台（4用1库备），远期4台
A13: 4 | B13: 潜水推流器及配套设备 （首期50%、远期50%） | C13: 0 | D13: ==甲供设备!L23/10000 -> 60.0838 | E13: 0 | F13: ==甲供设备!L23/5*4/10000 -> 48.06704 | G13: 0 | H13: ==D13+F13 -> 108.15084 | I13: 0 | J13: ==甲供设备!N23/10000 -> 221 | K13: 0 | L13: ==甲供设备!R23/10000 -> 33.465 | M13: / | N13: ==甲供设备!P23/10000 -> 216 | Q13: 近期5台（4用1库备），远期4台
A14: 5 | B14: MBR膜池工艺系统及配套设备 （首期50%、远期50%） | D14: ==甲供设备!L25/10000 -> 3305.5671 | F14: ==甲供设备!L25/10000 -> 3305.5671 | H14: ==D14+F14 -> 6611.1341 | I14: 850.44 | J14: 5468.37 | K14: 226.96 | L14: 2371.45 | M14: / | N14: ==甲供设备!P25 -> / | Q14: 近期1座，远期1座
A15: 6 | B15: 精确曝气系统及配套设备 （首期85%、远期15%） | C15: 0 | D15: ==甲供设备!L147/10000 -> 350.33526 | E15: 0 | F15: 50 | G15: 0 | H15: ==D15+F15 -> 400.33526 | I15: 0 | J15: ==甲供设备!N147/10000 -> 554.2 | K15: / | L15: ==甲供设备!R147 -> / | M15: / | N15: ==甲供设备!P147/10000 -> 314.68476 | Q15: 近期4台，远期4台
A16: 7 | B16: 鼓风机及配套设备 （首期50%、远期50%） | C16: 0 | D16: ==甲供设备!L159/10000 -> 909.9395 | E16: 0 | F16: ==甲供设备!L159/10000 -> 909.9395 | G16: 0 | H16: ==D16+F16 -> 1819.879 | I16: 0 | J16: ==甲供设备!N159/10000 -> 1143.22 | K16: 0 | L16: ==甲供设备!R159/10000 -> 1211.8 | M16: / | N16: ==甲供设备!P159/10000 -> 720 | O16: 环城北：2台（Q=4800m3/h）+3台（Q=6600m3/h）+3台（Q=15600m3/h）； 南站水厂：6台（Q=5040m3/h）+6台（Q=7500m3/h）； 中部净水厂：4台（Q=7200m3/h） 洛溪首期：2台（Q=4500m3/h）+1台（Q=9000m3/h）+3台（Q=8940-11880m3/h）； 结论：经过对比分析，“南站水厂”、“中部水厂”及“环城北”在设备投入数量、规格参数上都不具备可比性。 | Q16: 近期3台（2用1备），远期3台
A17: 8 | B17: 污泥装置设备 （首期66%、远期34%） | D17: ==甲供设备!L163/10000 -> 3215.2295 | F17: ==甲供设备!L163/2/10000 -> 1607.6147 | H17: ==D17+F17 -> 4822.8443 | I17: 135.18 | J17: 3349.07 | K17: 432.59 | L17: 3217.44 | M17: / | N17: ==甲供设备!P163/10000 -> 3720 | O17: 环城北：2套干化主机（土建预留1套设备不安装）； 南站水厂：3套干化主机； 中部水厂：3套干化主机； 洛溪首期：2套干化主机； 结论：设备数量不一致，设备价值水平基本一致。 | Q17: 近期2台，远期1台
A18: 9 | B18: 在线仪表设备 （首期100%） | D18: ==甲供设备!L263/10000 -> 120.8736 | F18: 0 | H18: ==D18+F18 -> 120.8736 | I18: 0 | J18: ==甲供设备!N263/10000 -> 104.8 | L18: ==甲供设备!R263/10000 -> 120.424 | M18: / | N18: ==甲供设备!P263/10000 -> 110
A19: 10 | B19: 智慧水厂及配套设备 （首期100%） | D19: ==甲供设备!L270/10000 -> 300 | F19: 0 | H19: ==D19+F19 -> 300 | I19: 0 | J19: ==甲供设备!N270/10000 -> 324.2251 | L19: ==甲供设备!R270 -> / | M19: / | N19: ==甲供设备!P270 -> / | O19: 环城北该项金额是为对应南站水厂的范围剥离出来的金额
A20: （二） | B20: 南站水厂的乙供设备部分 | C20: ==SUM(C21,C34,C35,C36,C39,C40,C41) -> 4363.3216 | D20: ==SUM(D21,D34,D35,D36,D39,D40,D41) -> 4133.7766 | E20: ==SUM(E21,E34,E35,E36,E39,E40,E41) -> 525.07221 | F20: ==SUM(F21,F34,F35,F36,F39,F40,F41) -> 1471.4321 | G20: ==SUM(G21,G34,G35,G36,G39,G40,G41) -> 4888.3938 | H20: ==SUM(H21,H34,H35,H36,H39,H40,H41) -> 5605.2087 | I20: ==SUM(I21,I34,I35,I36,I39,I40,I41) -> 6671.06 | J20: ==SUM(J21,J34,J35,J36,J39,J40,J41) -> 8557.79 | ... N20: ==SUM(N21,N34,N35,N36,N39,N40,N41) -> 9545.3993
A21: 1 | B21: 工艺专业 （首期60%、远期40%） | C21: ==SUM(C22:C33) -> 800.17 | D21: ==SUM(D22:D33) -> 1603.58 | E21: ==SUM(E22:E33) -> 86.462206 | F21: ==SUM(F22:F33) -> 864.62206 | G21: ==SUM(G22:G33) -> 886.63221 | H21: ==SUM(H22:H33) -> 2468.2021 | I21: ==SUM(I22:I33) -> 1412.15 | J21: ==SUM(J22:J33) -> 3078.16 | ... N21: ==SUM(N22:N33) -> 5866.5337 | O21: 偏差原因： 一、设备购置费 1、中部水厂： （1）工艺不同：中部水厂是含高效沉淀池和二沉池系统，南部水厂是膜系统； （2）中部水厂含精细格栅系统，而南部水厂无此系统； （3）中部水厂加药间甲供设备； （4）中部水厂出水及消毒区含精密过滤系统。 2、环城北： （1）南站水厂预处理区格栅系统甲供设备。 （2）南站水厂加药间系统乙供设备。 3、洛溪水厂： （1）南站水厂预处理区格栅系统甲供，生物反应池和出水及消毒区设备乙供。 二、安装费 1、中部水厂：工艺不同，南站水厂无高效沉淀池和二沉池系统。 2、环城北：结构形式不同，环城北是半地下式，南站水厂是全埋式，涉及地下暗室增加费。 3、洛溪水厂：污水处理规模不同。
A22: 1.1 | B22: 预处理区 | C22: ==197.4 -> 197.4 | D22: ==370.67 -> 370.67 | E22: ==F22*0.1 -> 5.672 | F22: ==56.72 -> 56.72 | G22: ==C22+E22 -> 203.072 | H22: ==D22+F22 -> 427.39 | I22: ==22.38+84.52 -> 106.9 | J22: ==223.33+1214.46-J11 -> 868.13 | K22: ==6699477.07/10000-226.96 -> 442.98771 | L22: ==484.76 -> 484.76 | M22: ==(13066219.29+35471.24-10136098.81*1.09)/10000 -> 205.33428 | N22: ==10136098.81*1.13/10000 -> 1145.3792
A23: 1.2 | B23: 生物反应池 | C23: ==25.84 -> 25.84 | D23: ==620.68 -> 620.68 | E23: ==F23*0.1 -> 2.3482056 | F23: ==234820.56/10000 -> 23.482056 | G23: ==C23+E23 -> 28.188206 | H23: ==D23+F23 -> 644.16206 | I23: 332.21 | J23: ==1104.15-386 -> 718.15 | L23: 284.46 | M23: ==(13732603.83-7372886.14*1.09)/10000 -> 569.61579 | N23: ==7372886.14*1.13/10000 -> 833.13613
A24: 1.3 | B24: MBR膜池 | C24: ==4.49 -> 4.49 | D24: ==141.61 -> 141.61 | E24: ==F24*0.1 -> 0 | F24: ==0 -> 0 | G24: ==C24+E24 -> 4.49 | H24: ==D24+F24 -> 141.61 | I24: 0 | J24: 188.5 | L24: 59.87 | M24: / | N24: /
A25: 1.4 | B25: 出水及消毒区 | C25: ==87.67 -> 87.67 | D25: ==217.5 -> 217.5 | E25: ==F25*0.1 -> 50.84 | F25: ==508.4 -> 508.4 | G25: ==C25+E25 -> 138.51 | H25: ==D25+F25 -> 725.9 | I25: 42.99 | J25: 532.46 | L25: 172.27 | M25: ==(17595506.9+2264997.25-(15500198.22+747758.14)*1.09)/10000 -> 215.02317 | N25: ==(15500198.22+747758.14)*1.13/10000 -> 1836.0191
A26: 1.5 | B26: 浓缩池 | C26: ==19.06 -> 19.06 | D26: ==37.29 -> 37.29 | E26: ==F26*0.1 -> 4.326 | F26: ==43.26 -> 43.26 | G26: ==C26+E26 -> 23.386 | H26: ==D26+F26 -> 80.55 | I26: 58.46 | J26: 119.57 | L26: / | M26: ==(91.74-39.74/1.13)+19.97 -> 76.541858 | N26: ==(11032.74+15421.68+8451.33+316814.16)*1.13/10000 -> 39.74435
A27: 1.6 | B27: 放空泵房 | C27: ==56.58 -> 56.58 | D27: ==26.61 -> 26.61 | E27: ==F27*0.1 -> 0 | F27: 0 | G27: ==C27+E27 -> 56.58 | H27: ==D27+F27 -> 26.61 | I27: 19.26 | J27: ==164.61-114.9 -> 49.71 | L27: 133.75 | M27: ==(1093431.08-531539.82*1.09)/10000 -> 51.405268 | N27: ==531539.82*1.13/10000 -> 60.064
A28: 1.7 | B28: 鼓风机房 | C28: ==88.24 -> 88.24 | D28: ==37.04 -> 37.04 | E28: ==F28*0.1 -> 0 | F28: 0 | G28: ==C28+E28 -> 88.24 | H28: ==D28+F28 -> 37.04 | I28: 85.72 | J28: ==1197.63-1143.22 -> 54.41 | L28: ==21.33 -> 21.33 | M28: ==(908383.68-104558.59*1.09)/10000 -> 79.441482 | N28: ==104558.59*1.13/10000 -> 11.815121
A29: 1.8 | B29: 加药间 | C29: ==47.09 -> 47.09 | D29: ==140.12 -> 140.12 | E29: ==F29*0.1 -> 23.276 | F29: 232.76 | G29: ==C29+E29 -> 70.366 | H29: ==D29+F29 -> 372.88 | I29: 79.48 | J29: 188.87 | L29: 34.85 | M29: ==(66.02-38.4/1.13)+9.98 -> 42.017699 | N29: ==78.14-39.74 -> 38.4
A30: 1.9 | B30: 高效沉淀池 | C30: / | D30: / | E30: / | F30: / | G30: / | H30: / | I30: / | J30: / | L30: 520.03 | M30: ==(1518526.32-248027.5*1.09)/10000 -> 124.81763 | N30: ==248027.5*1.13/10000+1300 -> 1328.0271
A31: 1.1 | B31: 二沉池 | C31: / | D31: / | E31: / | F31: / | G31: / | H31: / | I31: / | J31: / | M31: ==(4688890.04-697272.42*1.09)/10000 -> 392.88631 | N31: ==697272.42*1.13/10000+480 -> 558.79178
A32: 1.11 | B32: 维修车间 | C32: ==1.08 -> 1.08 | D32: ==2.83 -> 2.83 | E32: ==F32*0.1 -> 0 | F32: 0 | G32: ==C32+E32 -> 1.08 | H32: ==D32+F32 -> 2.83 | I32: 0 | J32: ==21.17+92.15 -> 113.32 | L32: 9.86 | M32: ==(104277.5-81035.4*1.09)/10000 -> 1.5948914 | N32: ==81035.4*1.13/10000 -> 9.1570002
A33: 1.12 | B33: 工艺综合管线 | C33: ==272.72 -> 272.72 | D33: ==9.23 -> 9.23 | E33: ==F33*0.1 -> 0 | F33: 0 | G33: ==C33+E33 -> 272.72 | H33: ==D33+F33 -> 9.23 | I33: 687.13 | J33: ==235.04+10 -> 245.04 | K33: 220.36 | L33: 9.41 | M33: ==(1664261.73-53097.35*1.09)/10000 -> 160.63856 | N33: ==53097.35*1.13/10000 -> 6.0000006
A34: 2 | B34: 仪表自控专业 （首期90%、远期10%） | C34: 347.46 | D34: 1105.25 | E34: 38.61 | F34: 122.81 | G34: ==C34+E34 -> 386.07 | H34: ==D34+F34 -> 1228.06 | I34: 1096.83 | J34: ==1226.45-104.8 -> 1121.65 | K34: ==(1392951.6+246173.88)/10000 -> 163.91255 | L34: ==(3506260+2861504)/10000-L18 -> 516.3524 | M34: ==(23696286.07-15301218.04*1.09)/10000 -> 701.79584 | N34: ==15301218.04*1.13/10000-314.68 -> 1414.3576 | O34: 偏差原因： 一、经对比分析，“南站”、“环城北”和“中部”设备配置及价值水平基本一致； 二、基于安装与设备费占比通常为30%~50%： 1.“环城北”安装费异常偏高； 2.“中部”因建面较大，线缆配置需求较“南站”大，故安装费稍高于“南站”，但属合理范围内。
A35: 3 | B35: 电气专业 （首期80%、远期20%） | C35: ==(32700857.94-762028.01-185537.84-(6547631.99-94646.94-79979.29)*1.09)/10000 -> 2480.6716 | D35: ==(6547631.99-17130.97)*1.13/10000 -> 737.94662 | E35: 400 | F35: 184 | G35: ==C35+E35 -> 2880.6716 | H35: ==D35+F35 -> 921.94662 | I35: ==2120.46+903.7+17.5+85.64 -> 3127.3 | J35: ==1444.97+122.76+70 -> 1637.73 | K35: ==(8735870.42+264248.07+379091.27+47274.27+129858.67+2292379.56+114682.16)/10000 -> 1196.3404 | L35: ==8744319/10000 -> 874.4319 | M35: ==(8505692.48+10405978.9+1895043.72+1090440.24-(3945265.32+2060121.53+181867.96+372159.09)*1.09)/10000 -> 1474.7394 | N35: ==(3945265.32+2060121.53+181867.96+372159.09)*1.13/10000 -> 741.21377 | O35: 偏差原因：安装费因工程量差异；设备费偏差主要是数量和单价的差异。 一、环城北：1.安装费:因工程量差异；2.设备费：2.1南站水厂高压柜（含直流屏）14台，平均单价7.2万/台，低压柜69台，平均单价5.8万/台；环城北高压柜（含直流屏）14台，平均单价10.1万/台，低压柜150台，平均单价6.1万/台，相比少600万；2.2南站水厂配电箱140台，平均单价6600元/台；环城北配电箱457台，平均单价3500元/台，相比少70万，总共少670万。 二、中部净水厂：1.安装费:1.1中部水厂有763万外电未在招标预算范围；1.2.南站水厂母线760米，平均单价5500元/米，中部水厂母线130米，平均单价5500元/米，相比多415万。 三、洛溪首期：1.安装费:因工程量差异；2.设备费：2.1南站水厂高压柜（含直流屏）14台，平均单价7.2万/台，低压柜69台，平均单价5.8万/台；洛溪首期高压柜（含直流屏）10台，平均单价10万/台，低压柜73台，平均单价8万/台，相比少170万；2.2南站水厂电梯3部，平均单价28.2万/部，洛溪首期电梯3部，平均单价13.1万/部，相比多40万，总共少130万。
A36: 4 | B36: 暖通、除臭专业 （首期100%） | C36: ==C37+C38 -> 735.02 | D36: ==D37+D38 -> 687 | E36: ==E37+E38 -> 0 | F36: ==F37+F38 -> 300 | G36: ==G37+G38 -> 735.02 | H36: ==H37+H38 -> 987 | I36: ==I37+I38 -> 618.21 | J36: ==J37+J38 -> 770.49 | ... L36: ==L37+L38 -> 395.934 | M36: ==M37 -> 1684.1155 | N36: ==N37 -> 1483.9777 | O36: 一、经对比分析，“南站”和“中部”设备配置不一致。“中部”设备为“碱洗涤+生物除臭复合滤池”、“化学碱洗涤塔”、“土壤除臭滤池”、“全过程除臭生物填料释放罐”等设备，费用约737万； 二、“南站””和“环城北”相比，设备配置基本一致，“环城北”设备费偏低。
A37: 4.1 | B37: 暖通 | C37: 506.48 | D37: 190.31 | E37: 0 | F37: 0 | G37: ==C37+E37 -> 506.48 | H37: ==D37+F37 -> 190.31 | I37: ==372.78+6.56 -> 379.34 | J37: ==212.86+47.61 -> 260.47 | K37: ==(4892831.43+135713.34)/10000 -> 502.85448 | L37: ==906700/10000 -> 90.67 | M37: ==(29785405.02+1370224.79-(12562539.41+570006.55)*1.09)/10000 -> 1684.1155 | N37: ==(12562539.41+570006.55)*1.13/10000 -> 1483.9777
A38: 4.2 | B38: 除臭 | C38: 228.54 | D38: 496.69 | E38: 0 | F38: 300 | G38: ==C38+E38 -> 228.54 | H38: ==D38+F38 -> 796.69 | I38: ==238.87 -> 238.87 | J38: ==510.02 -> 510.02 | L38: ==3052640/10000 -> 305.264
A39: 5 | B39: 给排水 （首期100%） | I39: ==19.55+397.02 -> 416.57 | J39: ==60.41 -> 60.41 | K39: ==(2470845.58+299898.25)/10000 -> 277.07438 | L39: 0 | M39: ==(496306.72+989426.11+2368731.64-(136689.31+130205.18+81038.49)*1.09)/10000 -> 347.52175 | N39: ==(136689.31+130205.18+81038.49)*1.13/10000 -> 39.316427
A40: 6 | B40: 化验室、维修间设备 | I40: 0 | J40: 166.48 | K40: / | L40: ==361700/10000 -> 36.17 | M40: / | N40: 0
A41: 7 | B41: 智慧水厂 | I41: 0 | J41: ==2601.3-324.23-554.2 -> 1722.87 | K41: 0 | L41: 0 | M41: / | N41: /
A42: （三） | B42: 工器具及生产工具购置费 | I42: 0 | J42: 207.8 | K42: 0 | L42: 0 | M42: 205.27

Sheet 甲供设备
A1: 设备价格表（含税）
A2: 单位工程：甲供设备
A3: 序号 | B3: 设备名称 | C3: 概算规格、型号 | D3: 施工图预算规格、型号 | E3: 单位 | F3: 数量 | G3: 概算 | I3: 南站水厂（5万m³/d） | M3: 环城北（100000m3/d） | O3: 中部水厂（100000m3/d） | Q3: 洛溪水厂(首期) （5万m³/d） | S3: 南站水厂 | U3: 品牌1 | Y3: 品牌2 | AC3: 品牌3 | AG3: 品牌4
I4: 预算数量 | J4: 预算选用价格
G5: 单价(元) | H5: 合价(元) | J5: 建议下浮率 | K5: 单价（元） | L5: 总价（元） | M5: 单价（元） | N5: 总价（元） | O5: 单价（元） | P5: 总价（元） | Q5: 单价（元） | R5: 总价（元） | S5: 询价均值 | T5: 询价最低值 | U5: 公司名称 | V5: 联系人、联系电话 | W5: 单价（元） | X5: 总价（元） | Y5: 公司名称 | Z5: 联系人、联系电话 | AA5: 单价（元） | AB5: 总价（元） | AC5: 公司名称 | AD5: 联系人、联系电话 | AE5: 单价（元） | AF5: 总价（元） | AG5: 公司名称 | AH5: 联系人、联系电话 | AI5: 单价（元） | AJ5: 总价（元）
A6: 一 | B6: 采购子包1:提升泵及配套设备 | L6: ==SUM(L7:L8) -> 1703337.1 | N6: ==SUM(N7:N8) -> 1149012 | P6: ==SUM(P7:P8) -> 2200000 | R6: ==SUM(R7:R8) -> 1365891
A7: 1 | B7: 提升水泵 | C7: 潜污泵，Q=2083m3/h，H=9.5m，N=75kW，带变频控制、导轨及自耦系统 | D7: 潜污泵，Q=2083m3/h，H=9.5m，N=75kW，带变频控制、导轨及自耦系统 | E7: 台 | F7: 2 | G7: 683200 | H7: ==G7*F7 -> 1366400 | I7: 2 | J7: 0.125 | K7: ==ROUND(S7*(1-J7),2) -> 499774.19 | L7: ==ROUND(K7*I7,2) -> 999548.38 | M7: 383004（Q=1300m3/h,H=25m,P=140kW） | N7: ==383004*3 -> 1149012 | O7: 440000（Q=1565m3/h，H=9.0m，N=55kw） | P7: ==440000*5 -> 2200000 | Q7: 322908（Q=1880m3/h ，H=6.0m ，N=55kW） | R7: ==322908*2 -> 645816 | S7: ==AVERAGE(W7,AA7,AE7,AI7) -> 571170.5 | T7: ==MIN(W7,AA7,AE7,AI7) -> 334682 | U7: KSB | V7: 李晖13829709122 | W7: 780000 | X7: ==W7*F7 -> 1560000 | Y7: 飞力 | Z7: 陈工18218182708 | AA7: 490000 | AB7: ==AA7*F7 -> 980000 | AC7: 海斯特 | AD7: 王兰军18666867936 | AE7: 680000 | AF7: ==AE7*F7 -> 1360000 | AG7: ABS | AH7: 曹昀13503012388 | AI7: 334682 | AJ7: ==AI7*I7 -> 669364
A8: 2 | B8: 提升水泵 | C8: 潜污泵，Q=1041m3/h，H=9.5m，N=37kW，带变频控制、导轨及自耦系统 | D8: 潜污泵，Q=1041m3/h，H=9.5m，N=37kW，带变频控制、导轨及自耦系统 | E8: 台 | F8: 2 | G8: 494500 | H8: ==G8*F8 -> 989000 | I8: 2 | J8: 0.125 | K8: ==ROUND(S8*(1-J8),2) -> 351894.38 | L8: ==ROUND(K8*I8,2) -> 703788.76 | Q8: 240025（Q=1460m3/h ，H=6.0m ，N=37kW） | R8: ==240025*3 -> 720075 | S8: ==AVERAGE(W8,AA8,AE8,AI8) -> 402165 | T8: ==MIN(W8,AA8,AE8,AI8) -> 218660 | U8: KSB | V8: 李晖13829709122 | W8: 665000 | X8: ==W8*F8 -> 1330000 | Y8: 飞力 | Z8: 陈工18218182708 | AA8: 390000 | AB8: ==AA8*F8 -> 780000 | AC8: 海斯特 | AD8: 王兰军18666867936 | AE8: 335000 | AF8: ==AE8*F8 -> 670000 | AG8: ABS | AH8: 曹昀13503012388 | AI8: 218660 | AJ8: ==AI8*I8 -> 437320
A9: 二 | B9: 采购子包2:内进流格栅除污机及其配套设备 | L9: ==SUM(L10:L19) -> 4007279.6 | N9: ==SUM(N10:N19) -> 5696600 | P9: ==SUM(P10:P19) -> 5100000 | R9: ==SUM(R10:R19) -> 7184068
A10: 1 | B10: 细格栅 | C10: 内进流孔板式格栅，渠宽1.5m，栅隙5mm，N=0.75kW，单台过水量≥2100m3/h，主体不锈钢 | D10: 内进流孔板式格栅，渠宽1.5m，栅隙5mm，N=0.75kW，单台过水量≥2100m3/h，主体不锈钢 | E10: 台 | F10: 3 | G10: 2377400 | H10: ==G10 -> 2377400 | I10: 3 | J10: 0.365 | K10: ==ROUND(S10*(1-J10),2) -> 601274.44 | L10: ==ROUND(K10*I10,2) -> 1803823.3 | M10: 531160 （Q=1565m3/h，b=5mm） | N10: ==265.58*10000 -> 2655800 | O10: 700000 | P10: ==O10*3 -> 2100000 | Q10: ==2744068/3 -> 914689.33 | R10: ==Q10*3 -> 2744068 | S10: ==AVERAGE(X10,AB10+AB11+AB12+AB13+AB14,AF10+AF11+AF12+AF13+AF14)/3 -> 946888.89 | T10: ==MIN(W10,AA10,AE10,AI10) -> 722433.33 | U10: 北排 | V10: 刘小姐13560026763 | W10: ==2167300/3 -> 722433.33 | X10: ==W10*F10 -> 2167300 | Y10: 悉美 | Z10: 王磷13602392272 | AA10: 890500 | AB10: ==AA10*F10 -> 2671500 | AC10: 艾维 | AD10: 谢泽才18620056917 | AE10: 860000 | AF10: ==AE10*F10 -> 2580000
A11: 2 | B11: 螺旋压榨机 | C11: 过滤精度3mm， N=2.2kW | D11: 过滤精度3mm， N=2.2kW | E11: 台 | F11: 2 | I11: 2 | U11: 北排 | V11: 刘小姐13560026763 | Y11: 悉美 | Z11: 王磷13602392272 | AA11: 182600 | AB11: ==AA11*F11 -> 365200 | AC11: 艾维 | AD11: 谢泽才18620056917 | AE11: 162500 | AF11: ==AE11*F11 -> 325000
A12: 3 | B12: 输渣管 | C12: 与格栅系统配套，长度≈12m，不锈钢材质，含支腿及观察口 | D12: 与格栅系统配套，长度≈12m，不锈钢材质，含支腿及观察口 | E12: 套 | F12: 1 | I12: 1 | U12: 北排 | V12: 刘小姐13560026763 | Y12: 悉美 | Z12: 王磷13602392272 | AA12: 18000 | AB12: ==AA12*F12 -> 18000 | AC12: 艾维 | AD12: 谢泽才18620056917 | AE12: 100000 | AF12: ==AE12*F12 -> 100000
A13: 4 | B13: 冲洗泵组 | C13: 立式多级泵组，单泵Q=8m³/h，H=81m，N=3kW，带变频控制、进口过滤器 | D13: 立式多级泵组，单泵Q=8m³/h，H=81m，N=3kW，带变频控制、进口过滤器 | E13: 台 | F13: 5 | I13: 5 | U13: 北排 | V13: 刘小姐13560026763 | Y13: 悉美 | Z13: 王磷13602392272 | AA13: 15000 | AB13: ==AA13*F13 -> 75000 | AC13: 艾维 | AD13: 谢泽才18620056917 | AE13: 22000 | AF13: ==AE13*F13 -> 110000
A14: 5 | B14: 储水箱 | C14: 不锈钢方形水箱，V=12m3，含成套冲洗水管路控制阀门、接头、过滤器、仪表等 | D14: 不锈钢方形水箱，V=12m3，含成套冲洗水管路控制阀门、接头、过滤器、仪表等 | E14: 个 | F14: 1 | I14: 1 | U14: 北排 | V14: 刘小姐13560026763 | Y14: 悉美 | Z14: 王磷13602392272 | AA14: 10000 | AB14: ==AA14*F14 -> 10000 | AC14: 艾维 | AD14: 谢泽才18620056917 | AE14: 100000 | AF14: ==AE14*F14 -> 100000
A15: 6 | B15: 膜格栅 | C15: 内进流孔板式格栅，渠宽1.6m，栅隙1mm，N=2.2kW ，网板宽度1800mm，单台过水量≥1580m3/h | D15: 内进流孔板式格栅，渠宽1.6m，栅隙1mm，N=2.2kW ，网板宽度1800mm，单台过水量≥1580m3/h | E15: 台 | F15: 3 | G15: 2935300 | H15: ==G15 -> 2935300 | I15: 3 | J15: 0.375 | K15: ==ROUND(S15*(1-J15),2) -> 734485.42 | L15: ==ROUND(K15*F15,2) -> 2203456.3 | M15: 608160（Q=1565m3/h，b=1mm） | N15: ==304.08*10000 -> 3040800 | O15: 750000 | P15: ==O15*4 -> 3000000 | Q15: ==4440000/3 -> 1480000 | R15: ==Q15*3 -> 4440000 | S15: ==AVERAGE(X15,AB15+AB16+AB17+AB18+AB19,AF15+AF16+AF17+AF18+AF19)/3 -> 1175176.7 | T15: ==MIN(W15,AA15,AE15,AI15) -> 884896.67 | U15: 北排 | V15: 刘小姐13560026763 | W15: ==2654690/3 -> 884896.67 | X15: ==W15*F15 -> 2654690 | Y15: 悉美 | Z15: 王磷13602392272 | AA15: 1229500 | AB15: ==AA15*F15 -> 3688500 | AC15: 艾维 | AD15: 谢泽才18620056917 | AE15: 1020000 | AF15: ==AE15*F15 -> 3060000
A16: 7 | B16: 螺旋压榨机 | C16: 过滤精度2mm，N=3kW | D16: 过滤精度2mm，N=3kW | E16: 台 | F16: 2 | I16: 2 | U16: 北排 | V16: 刘小姐13560026763 | Y16: 悉美 | Z16: 王磷13602392272 | AA16: 188700 | AB16: ==AA16*F16 -> 377400 | AC16: 艾维 | AD16: 谢泽才18620056917 | AE16: 163500 | AF16: ==AE16*F16 -> 327000
A17: 8 | B17: 输渣管 | C17: 与格栅系统配套，长度≈16m，不锈钢材质，含支腿及观察口 | D17: 与格栅系统配套，长度≈16m，不锈钢材质，含支腿及观察口 | E17: 套 | F17: 1 | I17: 1 | U17: 北排 | V17: 刘小姐13560026763 | Y17: 悉美 | Z17: 王磷13602392272 | AA17: 21000 | AB17: ==AA17*F17 -> 21000 | AC17: 艾维 | AD17: 谢泽才18620056917 | AE17: 110000 | AF17: ==AE17*F17 -> 110000
A18: 9 | B18: 恒压冲洗泵组 | C18: 立式多级泵组，单泵Q=30m³/h，H=80m，N=11kW，带变频控制、进口过滤器 | D18: 立式多级泵组，单泵Q=30m³/h，H=80m，N=11kW，带变频控制、进口过滤器 | E18: 台 | F18: 3 | I18: 3 | U18: 北排 | V18: 刘小姐13560026763 | Y18: 悉美 | Z18: 王磷13602392272 | AA18: 35000 | AB18: ==AA18*F18 -> 105000 | AC18: 艾维 | AD18: 谢泽才18620056917 | AE18: 40666.67 | AF18: ==AE18*F18 -> 122000.01
A19: 10 | B19: 储水箱 | C19: 不锈钢方形水箱，V=12m3，含成套冲洗水管路控制阀门、接头、过滤器、仪表等 | D19: 不锈钢方形水箱，V=12m3，含成套冲洗水管路控制阀门、接头、过滤器、仪表等 | E19: 个 | F19: 1 | I19: 1 | U19: 北排 | V19: 刘小姐13560026763 | Y19: 悉美 | Z19: 王磷13602392272 | AA19: 10000 | AB19: ==AA19*F19 -> 10000 | AC19: 艾维 | AD19: 谢泽才18620056917 | AE19: 101000 | AF19: ==AE19*F19 -> 101000
A20: 三 | B20: 采购子包3:立式搅拌器及配套设备 | L20: ==SUM(L21:L22) -> 1007787.5 | N20: ==SUM(N21:N22) -> 1650000 | P20: ==SUM(P21:P22) -> 690000 | R20: ==SUM(R21:R22) -> 1248390
A21: 1 | B21: 厌氧搅拌器 | C21: 不锈钢立式搅拌器，D=4m，N=4kW，带变频控制，缺氧Ⅰ | D21: 不锈钢立式搅拌器，D=4m，N=4kW，带变频控制，缺氧Ⅰ | E21: 台 | F21: 4 | G21: 156000 | H21: ==G21*F21 -> 624000 | I21: 5 | J21: 0.26 | K21: ==ROUND(S21*(1-J21),2) -> 94464.7 | L21: ==ROUND(K21*I21,2) -> 472323.5 | M21: 55000（D=580mm；转速475rpm；N=7.6kw） | N21: ==165*10000 -> 1650000 | O21: 115000 | P21: ==O21*2 -> 230000 | Q21: 83226 | R21: ==Q21*10 -> 832260 | S21: ==AVERAGE(W21,AA21,AE21,AI21) -> 127655 | T21: ==MIN(W21,AA21,AE21,AI21) -> 120310 | U21: 菲力 | V21: 史伟15161663888 | W21: 135000 | X21: ==W21*I21 -> 675000 | Y21: 莱宁 | Z21: 王晨18664634927 | AA21: 不报价 | AB21: 不报价 | AC21: 力维 | AD21: 方经理13801994720 | AE21: 120310 | AF21: ==AE21*I21 -> 601550
A22: 2 | B22: 缺氧搅拌器 | C22: 不锈钢立式搅拌器，D=4.2m，N=7.5kW，带变频控制，缺氧Ⅱ | D22: 不锈钢立式搅拌器，D=4.2m，N=7.5kW，带变频控制，缺氧Ⅱ | E22: 套 | F22: 4 | G22: 169000 | H22: ==G22*F22 -> 676000 | I22: 5 | J22: 0.26 | K22: ==ROUND(S22*(1-J22),2) -> 107092.8 | L22: ==ROUND(K22*I22,2) -> 535464 | O22: 115000 | P22: ==O22*4 -> 460000 | Q22: 83226 | R22: ==Q22*5 -> 416130 | S22: ==AVERAGE(W22,AA22,AE22,AI22) -> 144720 | T22: ==MIN(W22,AA22,AE22,AI22) -> 129440 | U22: 菲力 | V22: 史伟15161663888 | W22: 160000 | X22: ==W22*I22 -> 800000 | Y22: 莱宁 | Z22: 王晨18664634927 | AA22: 不报价 | AB22: 不报价 | AC22: 力维 | AD22: 方经理13801994720 | AE22: 129440 | AF22: ==AE22*I22 -> 647200
A23: 四 | B23: 采购子包4:潜水推流器及配套设备 | L23: ==L24 -> 600838 | N23: ==N24 -> 2210000 | P23: ==P24 -> 2160000 | R23: ==R24 -> 334650
A24: 1 | B24: 缺氧推流器 | C24: 不锈钢低速推流器，N=15kW | D24: 不锈钢低速推流器，N=15kW | E24: 台 | F24: 4 | G24: 170000 | H24: ==G24*F24 -> 680000 | I24: 5 | J24: 0.51 | K24: ==ROUND(S24*(1-J24),2) -> 120167.6 | L24: ==ROUND(K24*I24,2) -> 600838 | M24: 85000（D=2500mm;转速48rpm；N=6.8kw） | N24: ==221*10000 -> 2210000 | O24: 135000 | P24: ==O24*16 -> 2160000 | Q24: 111550 | R24: ==Q24*3 -> 334650 | S24: ==AVERAGE(W24,AA24,AE24,AI24) -> 245240 | T24: ==MIN(W24,AA24,AE24,AI24) -> 195000 | U24: KSB | V24: 李晖13829709122 | W24: 195000 | X24: ==W24*I24 -> 975000 | Y24: 飞力 | Z24: 陈工18218182708 | AA24: 225000 | AB24: ==AA24*I24 -> 1125000 | AC24: 海斯特 | AD24: 王兰军18666867936 | AE24: 285000 | AF24: ==AE24*I24 -> 1425000 | AG24: ABS | AH24: 曹昀13503012388 | AI24: 275960 | AJ24: ==AI24*I24 -> 1379800
A25: 五 | B25: 采购子包5:MBR膜池工艺系统及配套设备（50%） | L25: ==L26 -> 33055671 | N25: ==N26 -> 63188094 | P25: ==P26 -> / | R25: ==R26 -> 25984134
A26: 1 | B26: 膜组器系统 | C26: PVDF中空纤维膜组器，单渠道出水量Q≥9375m3/d，组器框架不锈钢材质，含产水、曝气接头等 | D26: PVDF中空纤维膜组器,单渠道出水量Q≥9375m3/d,组器框架不锈钢材质,含产水、曝气接头等,每个渠道含8套膜组器 | E26: 台 | F26: 8 | G26: 32000000 | H26: 32000000 | I26: 1 | J26: 0.02 | K26: ==ROUND(S26*(1-J26),2) -> 33055671 | L26: ==K26*I26 -> 33055671 | M26: 6507.31万元（100000m3/d），其中膜组器2860000.00元（Q=6250m3/d） | N26: ==65073094-1885000 -> 63188094 | O26: / | P26: / | Q26: ==23714533+2269601.11 -> 25984134 | R26: ==Q26 -> 25984134 | S26: 33730276 | T26: ==AA26 -> 29726630 | U26: 碧水源 | V26: 车学理13380060528 | W26: 3152000 | X26: ==W26*F26 -> 25216000 | Y26: 三达膜 | Z26: 王立才13459293295 | AA26: 29726630 | AB26: ==AA26 -> 29726630 | AC26: 立升 | AD26: 房明亮15050461263 | AE26: 不报价 | AF26: 不报价
A27: 2 | B27: 进水闸门 | C27: 不锈钢附壁方闸门，B×H=1000×1000mm，N=0.75kW，带手电一体启闭机 | D27: 不锈钢附壁方闸门，B×H=1000×1000mm，N=0.75kW，带手电一体启闭机 | E27: 台 | F27: 8 | U27: 碧水源 | V27: 车学理13380060528 | W27: 58000 | X27: ==W27*F27 -> 464000 | Y27: 三达膜 | Z27: 王立才13459293295 | AC27: 立升 | AD27: 房明亮15050461263 | AE27: 不报价 | AF27: 不报价
A28: 3 | B28: 出水闸门 | C28: 不锈钢附壁方闸门，B×H=1000×1000mm，N=0.75kW，带手电一体启闭机 | D28: 不锈钢附壁方闸门，B×H=1000×1000mm，N=0.75kW，带手电一体启闭机 | E28: 台 | F28: 8 | U28: 碧水源 | V28: 车学理13380060528 | W28: 58000 | X28: ==W28*F28 -> 464000 | Y28: 三达膜 | Z28: 王立才13459293295 | AC28: 立升 | AD28: 房明亮15050461263 | AE28: 不报价 | AF28: 不报价
A29: 4 | B29: 电动葫芦 | C29: 起重量5T，起吊高度12m，行程约340m，N=0.8×2+7.5kW | D29: 起重量5T，起吊高度12m，行程约340m，N=0.8×2+7.5kW | E29: 台 | F29: 2 | U29: 碧水源 | V29: 车学理13380060528 | W29: 436000 | X29: ==W29*F29 -> 872000 | Y29: 三达膜 | Z29: 王立才13459293295 | AC29: 立升 | AD29: 房明亮15050461263 | AE29: 不报价 | AF29: 不报价
A30: 5 | B30: 产水泵 | C30: 卧式离心泵，Q=481m3/h，H=17m，N=37kW，汽蚀余量≤3m，带变频控制 | D30: 卧式离心泵，Q=481m3/h，H=20m，N=37kW，汽蚀余量≤3m，带变频控制 | E30: 台 | F30: 9 | U30: 碧水源 | V30: 车学理13380060528 | W30: 54620 | X30: ==W30*F30 -> 491580 | Y30: 三达膜 | Z30: 王立才13459293295 | AC30: 立升 | AD30: 房明亮15050461263 | AE30: 不报价 | AF30: 不报价
A31: 6 | B31: 产水专用设备 | C31: Φ500×1100mm，SS316材质，每套含2个音叉液位计 | D31: Φ500×1100mm，SS316材质，每套含2个音叉液位计 | E31: 台 | F31: 8 | U31: 碧水源 | V31: 车学理13380060528 | W31: 17795 | X31: ==W31*F31 -> 142360 | Y31: 三达膜 | Z31: 王立才13459293295 | AC31: 立升 | AD31: 房明亮15050461263 | AE31: 不报价 | AF31: 不报价
A32: 7 | B32: CIP泵 | C32: 卧式离心泵，Q=251m3/h,H=12m,N=15kW，带变频控制 | D32: 卧式离心泵，Q=251m3/h,H=12m,N=15kW，带变频控制 | E32: 台 | F32: 2 | U32: 碧水源 | V32: 车学理13380060528 | W32: 43346 | X32: ==W32*F32 -> 86692 | Y32: 三达膜 | Z32: 王立才13459293295 | AC32: 立升 | AD32: 房明亮15050461263 | AE32: 不报价 | AF32: 不报价
A33: 8 | B33: 液环真空泵 | C33: Q=165m3/h，最大真空度84%，N=4kW | D33: Q=165m3/h，最大真空度84%，N=4kW | E33: 台 | F33: 2 | U33: 碧水源 | V33: 车学理13380060528 | W33: 30000 | X33: ==W33*F33 -> 60000 | Y33: 三达膜 | Z33: 王立才13459293295 | AC33: 立升 | AD33: 房明亮15050461263 | AE33: 不报价 | AF33: 不报价
A34: 9 | B34: 真空罐 | C34: V=1m3，Φ800×2400mm | D34: V=1m3，Φ800×2400mm | E34: 台 | F34: 1 | U34: 碧水源 | V34: 车学理13380060528 | W34: 10000 | X34: ==W34*F34 -> 10000 | Y34: 三达膜 | Z34: 王立才13459293295 | AC34: 立升 | AD34: 房明亮15050461263 | AE34: 不报价 | AF34: 不报价
A35: 10 | B35: 气水分离罐 | C35: V=0.12m3，φ500×780mm | D35: V=0.12m3，φ500×780mm | E35: 台 | F35: 1 | U35: 碧水源 | V35: 车学理13380060528 | W35: 3000 | X35: ==W35*F35 -> 3000 | Y35: 三达膜 | Z35: 王立才13459293295 | AC35: 立升 | AD35: 房明亮15050461263 | AE35: 不报价 | AF35: 不报价
A36: 11 | B36: 空压机 | C36: 螺杆式空压机，Q=1.0m3/min，P=0.80MPa，N=7.5kW | D36: 螺杆式空压机，Q=1.0m3/min，P=0.80MPa，N=7.5kW | E36: 台 | F36: 2 | U36: 碧水源 | V36: 车学理13380060528 | W36: 43000 | X36: ==W36*F36 -> 86000 | Y36: 三达膜 | Z36: 王立才13459293295 | AC36: 立升 | AD36: 房明亮15050461263 | AE36: 不报价 | AF36: 不报价
A37: 12 | B37: 冷干机 | C37: Q=1.5m3/min，N=0.55kW | D37: Q=1.5m3/min，N=0.55kW | E37: 台 | F37: 1 | U37: 碧水源 | V37: 车学理13380060528 | W37: 7000 | X37: ==W37*F37 -> 7000 | Y37: 三达膜 | Z37: 王立才13459293295 | AC37: 立升 | AD37: 房明亮15050461263 | AE37: 不报价 | AF37: 不报价
A38: 13 | B38: 储气罐 | C38: V=1m3，工作压力0.8MPa | D38: V=1m3，工作压力0.8MPa | E38: 台 | F38: 1 | U38: 碧水源 | V38: 车学理13380060528 | W38: 10000 | X38: ==W38*F38 -> 10000 | Y38: 三达膜 | Z38: 王立才13459293295 | AC38: 立升 | AD38: 房明亮15050461263 | AE38: 不报价 | AF38: 不报价
A39: 14 | B39: 剩余污泥泵 | C39: 无堵塞卧式离心泵，Q=65m3/h，H=20m，N=11kW | D39: 无堵塞卧式离心泵，Q=65m3/h，H=20m，N=11kW | E39: 台 | F39: 2 | U39: 碧水源 | V39: 车学理13380060528 | W39: 58000 | X39: ==W39*F39 -> 116000 | Y39: 三达膜 | Z39: 王立才13459293295 | AC39: 立升 | AD39: 房明亮15050461263 | AE39: 不报价 | AF39: 不报价
A40: 17 | B40: 手动对夹式蝶阀 | D40: DN300,1.0MPa,阀板:铸铁 | E40: 个 | F40: 16 | U40: 碧水源 | V40: 车学理13380060528 | W40: 2682 | X40: ==W40*F40 -> 42912 | Y40: 三达膜 | Z40: 王立才13459293295 | AC40: 立升 | AD40: 房明亮15050461263 | AE40: 不报价 | AF40: 不报价
A41: 18 | B41: 手动对夹式蝶阀 | D41: DN300,1.0MPa,阀板:铸铁 | E41: 个 | F41: 2 | U41: 碧水源 | V41: 车学理13380060528 | W41: 2682 | X41: ==W41*F41 -> 5364 | Y41: 三达膜 | Z41: 王立才13459293295 | AC41: 立升 | AD41: 房明亮15050461263 | AE41: 不报价 | AF41: 不报价
A42: 19 | B42: 手动对夹式蝶阀 | D42: DN250,1.0MPa,阀体阀板：UPVC | E42: 个 | F42: 2 | U42: 碧水源 | V42: 车学理13380060528 | W42: 1890 | X42: ==W42*F42 -> 3780 | Y42: 三达膜 | Z42: 王立才13459293295 | AC42: 立升 | AD42: 房明亮15050461263 | AE42: 不报价 | AF42: 不报价
A43: 20 | B43: 手动对夹式蝶阀 | D43: DN250,1.0MPa,阀体阀板：UPVC | E43: 个 | F43: 2 | U43: 碧水源 | V43: 车学理13380060528 | W43: 1890 | X43: ==W43*F43 -> 3780 | Y43: 三达膜 | Z43: 王立才13459293295 | AC43: 立升 | AD43: 房明亮15050461263 | AE43: 不报价 | AF43: 不报价
A44: 21 | B44: 手动对夹式蝶阀 | D44: DN150,1.0MPa,阀板:铸铁 | E44: 个 | F44: 10 | U44: 碧水源 | V44: 车学理13380060528 | W44: 900 | X44: ==W44*F44 -> 9000 | Y44: 三达膜 | Z44: 王立才13459293295 | AC44: 立升 | AD44: 房明亮15050461263 | AE44: 不报价 | AF44: 不报价
A45: 22 | B45: 手动对夹式蝶阀 | D45: DN150,1.0MPa,阀板:铸铁 | E45: 个 | F45: 5 | U45: 碧水源 | V45: 车学理13380060528 | W45: 900 | X45: ==W45*F45 -> 4500 | Y45: 三达膜 | Z45: 王立才13459293295 | AC45: 立升 | AD45: 房明亮15050461263 | AE45: 不报价 | AF45: 不报价
A46: 23 | B46: 手动对夹式蝶阀 | D46: DN150,1.0MPa,阀板:铸铁（图纸的材质UPVC） | E46: 个 | F46: 1 | U46: 碧水源 | V46: 车学理13380060528 | W46: 900 | X46: ==W46*F46 -> 900 | Y46: 三达膜 | Z46: 王立才13459293295 | AC46: 立升 | AD46: 房明亮15050461263 | AE46: 不报价 | AF46: 不报价
A47: 24 | B47: 手动对夹式蝶阀 | D47: DN125,1.0MPa,阀板:SS316 | E47: 个 | F47: 72 | U47: 碧水源 | V47: 车学理13380060528 | W47: 775 | X47: ==W47*F47 -> 55800 | Y47: 三达膜 | Z47: 王立才13459293295 | AC47: 立升 | AD47: 房明亮15050461263 | AE47: 不报价 | AF47: 不报价
A48: 25 | B48: 手动对夹式蝶阀 | D48: DN100,1.0MPa,阀板:铸铁，涡轮式 | E48: 个 | F48: 72 | U48: 碧水源 | V48: 车学理13380060528 | W48: 576 | X48: ==W48*F48 -> 41472 | Y48: 三达膜 | Z48: 王立才13459293295 | AC48: 立升 | AD48: 房明亮15050461263 | AE48: 不报价 | AF48: 不报价
A49: 26 | B49: 手动对夹式蝶阀 | D49: DN50,1.0MPa，阀板:铸铁，涡轮式 | E49: 个 | F49: 19 | U49: 碧水源 | V49: 车学理13380060528 | W49: 366 | X49: ==W49*F49 -> 6954 | Y49: 三达膜 | Z49: 王立才13459293295 | AC49: 立升 | AD49: 房明亮15050461263 | AE49: 不报价 | AF49: 不报价
A50: 27 | B50: 手动对夹式蝶阀 | D50: DN200,1.0MPa,阀体阀板：UPVC | E50: 个 | F50: 3 | U50: 碧水源 | V50: 车学理13380060528 | W50: 1695 | X50: ==W50*F50 -> 5085 | Y50: 三达膜 | Z50: 王立才13459293295 | AC50: 立升 | AD50: 房明亮15050461263 | AE50: 不报价 | AF50: 不报价
A51: 28 | B51: 手动对夹式蝶阀 | D51: DN200,1.0MPa,阀体阀板：铸铁 | E51: 个 | F51: 1 | U51: 碧水源 | V51: 车学理13380060528 | W51: 1341 | X51: ==W51*F51 -> 1341 | Y51: 三达膜 | Z51: 王立才13459293295 | AC51: 立升 | AD51: 房明亮15050461263 | AE51: 不报价 | AF51: 不报价
... A79: 56 | B79: 快速接头 | D79: DN125，SS316，含一个法兰 | E79: 个 | F79: 8 | U79: 碧水源 | V79: 车学理13380060528 | W79: 1420 | X79: ==W79*F79 -> 11360 | Y79: 三达膜 | Z79: 王立才13459293295 | AC79: 立升 | AD79: 房明亮15050461263 | AE79: 不报价 | AF79: 不报价
A80: 57 | B80: 气动三偏心蝶阀 | D80: DN80 | E80: 个 | F80: 5
A81: 58 | B81: 气动三偏心蝶阀 | D81: DN200 | E81: 个 | F81: 8
A82: 59 | B82: 气动三偏心蝶阀 | D82: DN150 | E82: 个 | F82: 4
A83: 60 | B83: 气动三偏心蝶阀 | D83: DN125 | E83: 个 | F83: 4
A84: 61 | B84: 气动三偏心蝶阀 | D84: DN100 | E84: 个 | F84: 4
A85: 62 | B85: 气动球阀 | D85: DN100 | E85: 个 | F85: 6
A86: 63 | B86: 气动球阀 | D86: DN125 | E86: 个 | F86: 4
A87: 64 | B87: 气动球阀 | D87: DN150 | E87: 个 | F87: 4
A88: 65 | B88: 气动球阀 | D88: DN20 | E88: 个 | F88: 2
A89: 66 | B89: 气动球阀 | D89: DN25 | E89: 个 | F89: 6
A90: 67 | B90: 气动球阀 | D90: DN40 | E90: 个 | F90: 6
A91: 68 | B91: 气动球阀 | D91: DN65 | E91: 个 | F91: 2
... A93: 70 | B93: 电动调节阀 | D93: DN80 | E93: 个 | F93: 2
A94: 71 | B94: 气动法兰式蝶阀 | C94: DN250，PN10，CIP管 | D94: DN250，PN10，CIP管 | E94: 台 | F94: 8 | G94: 5900 | H94: ==G94*F94 -> 47200 | U94: 碧水源 | V94: 车学理13380060528 | W94: 8800 | X94: ==W94*F94 -> 70400 | Y94: 三达膜 | Z94: 王立才13459293295 | AC94: 立升 | AD94: 房明亮15050461263 | AE94: 不报价 | AF94: 不报价
A95: 72 | B95: 气动对夹式蝶阀 | C95: DN150，PN10，剩余污泥总管 | D95: DN150，PN10，剩余污泥总管 | E95: 台 | F95: 1 | G95: 4000 | H95: ==G95*F95 -> 4000 | U95: 碧水源 | V95: 车学理13380060528 | W95: 5300 | X95: ==W95*F95 -> 5300 | Y95: 三达膜 | Z95: 王立才13459293295 | AC95: 立升 | AD95: 房明亮15050461263 | AE95: 不报价 | AF95: 不报价
A96: 73 | B96: 气动对夹式蝶阀 | C96: DN80，PN10，产水专用设备抽真空 | D96: DN80，PN10，产水专用设备抽真空 | E96: 台 | F96: 8 | G96: 3300 | H96: ==G96*F96 -> 26400 | U96: 碧水源 | V96: 车学理13380060528 | W96: 3800 | X96: ==W96*F96 -> 30400 | Y96: 三达膜 | Z96: 王立才13459293295 | AC96: 立升 | AD96: 房明亮15050461263 | AE96: 不报价 | AF96: 不报价
A97: 74 | B97: 气动对夹式蝶阀 | C97: DN80，PN10，真空罐进口 | D97: DN80，PN10，真空罐进口 | E97: 台 | F97: 1 | G97: 3300 | H97: ==G97*F97 -> 3300 | U97: 碧水源 | V97: 车学理13380060528 | W97: 3500 | X97: ==W97*F97 -> 3500 | Y97: 三达膜 | Z97: 王立才13459293295 | AC97: 立升 | AD97: 房明亮15050461263 | AE97: 不报价 | AF97: 不报价
A98: 75 | B98: 气动对夹式蝶阀 | C98: DN50，PN10，真空罐排水 | D98: DN50，PN10，真空罐排水 | E98: 台 | F98: 1 | G98: 2900 | H98: ==G98*F98 -> 2900 | U98: 碧水源 | V98: 车学理13380060528 | W98: 1650 | X98: ==W98*F98 -> 1650 | Y98: 三达膜 | Z98: 王立才13459293295 | AC98: 立升 | AD98: 房明亮15050461263 | AE98: 不报价 | AF98: 不报价
A99: 76 | B99: 气动球阀 | C99: DN20，PN10，真空罐排气 | D99: DN20，PN10，真空罐排气 | E99: 台 | F99: 1 | G99: 2500 | H99: ==G99*F99 -> 2500 | U99: 碧水源 | V99: 车学理13380060528 | W99: 2600 | X99: ==W99*F99 -> 2600 | Y99: 三达膜 | Z99: 王立才13459293295 | AC99: 立升 | AD99: 房明亮15050461263 | AE99: 不报价 | AF99: 不报价
A100: 77 | B100: 气动球阀 | C100: DN15，PN10，气水分离罐补水 | D100: DN15，PN10，气水分离罐补水 | E100: 台 | F100: 1 | G100: 2000 | H100: ==G100*F100 -> 2000 | U100: 碧水源 | V100: 车学理13380060528 | W100: 2600 | X100: ==W100*F100 -> 2600 | Y100: 三达膜 | Z100: 王立才13459293295 | AC100: 立升 | AD100: 房明亮15050461263 | AE100: 不报价 | AF100: 不报价
A101: 78 | B101: 电磁阀 | C101: DN20，PN10，储气罐排污 | D101: DN20，PN10，储气罐排污 | E101: 台 | F101: 1 | G101: 3600 | H101: ==G101*F101 -> 3600 | U101: 碧水源 | V101: 车学理13380060528 | W101: 585 | X101: ==W101*F101 -> 585 | Y101: 三达膜 | Z101: 王立才13459293295 | AC101: 立升 | AD101: 房明亮15050461263 | AE101: 不报价 | AF101: 不报价
A102: 79 | B102: 气动对夹式蝶阀 | C102: DN350，PN10，产水干管 | D102: DN350，PN10，产水干管 | E102: 台 | F102: 8 | G102: 13100 | H102: ==G102*F102 -> 104800 | U102: 碧水源 | V102: 车学理13380060528 | W102: 18000 | X102: ==W102*F102 -> 144000 | Y102: 三达膜 | Z102: 王立才13459293295 | AC102: 立升 | AD102: 房明亮15050461263 | AE102: 不报价 | AF102: 不报价
A103: 80 | B103: 气动对夹式蝶阀 | C103: DN300，PN10，吹扫干管 | D103: DN300，PN10，吹扫干管 | E103: 台 | F103: 8 | G103: 6700 | H103: ==G103*F103 -> 53600 | U103: 碧水源 | V103: 车学理13380060528 | W103: 13500 | X103: ==W103*F103 -> 108000 | Y103: 三达膜 | Z103: 王立才13459293295 | AC103: 立升 | AD103: 房明亮15050461263 | AE103: 不报价 | AF103: 不报价
A104: 81 | B104: 气动对夹式蝶阀 | C104: DN300,PN10, 清水池补水管 | D104: DN300,PN10, 清水池补水管 | E104: 台 | F104: 1 | G104: 6700 | H104: ==G104*F104 -> 6700 | U104: 碧水源 | V104: 车学理13380060528 | W104: 13500 | X104: ==W104*F104 -> 13500 | Y104: 三达膜 | Z104: 王立才13459293295 | AC104: 立升 | AD104: 房明亮15050461263 | AE104: 不报价 | AF104: 不报价
A105: 82 | B105: 在线MLSS仪 | D105: 量程0~20g/L，输出信号4~20mA | E105: 套 | F105: 2 | U105: 碧水源 | V105: 车学理13380060528 | W105: 45325 | X105: ==W105*F105 -> 90650 | Y105: 三达膜 | Z105: 王立才13459293295 | AC105: 立升 | AD105: 房明亮15050461263 | AE105: 不报价 | AF105: 不报价
A106: 83 | B106: 静压式液位计 | D106: 量程0～5m，输出信号4～20mA | E106: 套 | F106: 2 | U106: 碧水源 | V106: 车学理13380060528 | W106: 8600 | X106: ==W106*F106 -> 17200 | Y106: 三达膜 | Z106: 王立才13459293295 | AC106: 立升 | AD106: 房明亮15050461263 | AE106: 不报价 | AF106: 不报价
A107: 84 | B107: 压力变送器 | D107: 量程－100～200kPa，输出信号4～20mA，一体式 | E107: 套 | F107: 8 | U107: 碧水源 | V107: 车学理13380060528 | W107: 6000 | X107: ==W107*F107 -> 48000 | Y107: 三达膜 | Z107: 王立才13459293295 | AC107: 立升 | AD107: 房明亮15050461263 | AE107: 不报价 | AF107: 不报价
A108: 85 | B108: 电磁流量计 | D108: DN300，量程0～750m3/h，橡胶衬里，不锈钢电极，输出信号4～20mA，1.0MPa，分体式 | E108: 套 | F108: 8 | U108: 碧水源 | V108: 车学理13380060528 | W108: 30000 | X108: ==W108*F108 -> 240000 | Y108: 三达膜 | Z108: 王立才13459293295 | AC108: 立升 | AD108: 房明亮15050461263 | AE108: 不报价 | AF108: 不报价
A109: 86 | B109: 在线浊度仪 | D109: 量程0～20NTU，输出信号4～20mA，分体式 | E109: 套 | F109: 2 | U109: 碧水源 | V109: 车学理13380060528 | W109: 35000 | X109: ==W109*F109 -> 70000 | Y109: 三达膜 | Z109: 王立才13459293295 | AC109: 立升 | AD109: 房明亮15050461263 | AE109: 不报价 | AF109: 不报价
A110: 87 | B110: 电磁流量计 | D110: DN250，量程0～350m3/h，橡胶衬里,不锈钢电极，输出信号4～20mA，1.0MPa，分体式 | E110: 套 | F110: 1 | U110: 碧水源 | V110: 车学理13380060528 | W110: 25000 | X110: ==W110*F110 -> 25000 | Y110: 三达膜 | Z110: 王立才13459293295 | AC110: 立升 | AD110: 房明亮15050461263 | AE110: 不报价 | AF110: 不报价
A111: 88 | B111: 音叉液位计 | D111: 双叉标准型，螺纹连接 | E111: 套 | F111: 18 | U111: 碧水源 | V111: 车学理13380060528 | W111: 6500 | X111: ==W111*F111 -> 117000 | Y111: 三达膜 | Z111: 王立才13459293295 | AC111: 立升 | AD111: 房明亮15050461263 | AE111: 不报价 | AF111: 不报价
A112: 89 | B112: 液位计 | D112: 测量范围0～4m，介质：NaClO，输出信号4～20mA | E112: 套 | F112: 1 | U112: 碧水源 | V112: 车学理13380060528 | W112: 9300 | X112: ==W112*F112 -> 9300 | Y112: 三达膜 | Z112: 王立才13459293295 | AC112: 立升 | AD112: 房明亮15050461263 | AE112: 不报价 | AF112: 不报价
A113: 90 | B113: 液位计 | D113: 测量范围0～4m，介质：柠檬酸，输出信号4～20mA | E113: 套 | F113: 1 | U113: 碧水源 | V113: 车学理13380060528 | W113: 9300 | X113: ==W113*F113 -> 9300 | Y113: 三达膜 | Z113: 王立才13459293295 | AC113: 立升 | AD113: 房明亮15050461263 | AE113: 不报价 | AF113: 不报价
A114: 91 | B114: 电磁流量计 | D114: DN50，量程0～10m3/h，四氟衬里，钛电极，输出信号4～20mA，1.0MPa，分体式 | E114: 套 | F114: 1 | U114: 碧水源 | V114: 车学理13380060528 | W114: 17690 | X114: ==W114*F114 -> 17690 | Y114: 三达膜 | Z114: 王立才13459293295 | AC114: 立升 | AD114: 房明亮15050461263 | AE114: 不报价 | AF114: 不报价
A115: 92 | B115: 电磁流量计 | D115: DN50，量程0～10m3/h，四氟衬里，钽电极，输出信号4～20mA，1.0MPa，分体式 | E115: 套 | F115: 1 | U115: 碧水源 | V115: 车学理13380060528 | W115: 17690 | X115: ==W115*F115 -> 17690 | Y115: 三达膜 | Z115: 王立才13459293295 | AC115: 立升 | AD115: 房明亮15050461263 | AE115: 不报价 | AF115: 不报价
A116: 93 | B116: 电磁流量计 | D116: DN150，量程0～100m3/h，橡胶衬里,不锈钢电极，输出信号4～20mA，1.0MPa，分体式 | E116: 台 | F116: 1 | U116: 碧水源 | V116: 车学理13380060528 | W116: 20000 | X116: ==W116*F116 -> 20000 | Y116: 三达膜 | Z116: 王立才13459293295 | AC116: 立升 | AD116: 房明亮15050461263 | AE116: 不报价 | AF116: 不报价
... A139: 116 | B139: 污泥回流泵接线盒 | D139: 非标定制，不锈钢304，IP55,支架安装 | E139: 台 | F139: 6 | U139: 碧水源 | V139: 车学理13380060528 | W139: 1500 | X139: ==W139*F139 -> 9000 | Y139: 三达膜 | Z139: 王立才13459293295 | AC139: 立升 | AD139: 房明亮15050461263 | AE139: 不报价 | AF139: 不报价
A140: 117 | B140: 膜车间主站PLCA | E140: 套 | F140: 1 | U140: 碧水源 | V140: 车学理13380060528 | W140: 315000 | X140: ==W140*F140 -> 315000 | Y140: 三达膜 | Z140: 王立才13459293295 | AC140: 立升 | AD140: 房明亮15050461263 | AE140: 不报价 | AF140: 不报价
A141: 118 | B141: 膜车间远程站PLCA.1-膜车间远程站PLCA.4 | E141: 套 | F141: 4 | U141: 碧水源 | V141: 车学理13380060528 | W141: 112000 | X141: ==W141*F141 -> 448000 | Y141: 三达膜 | Z141: 王立才13459293295 | AC141: 立升 | AD141: 房明亮15050461263 | AE141: 不报价 | AF141: 不报价
A142: 119 | B142: 交换机 | E142: 个 | F142: 1 | U142: 碧水源 | V142: 车学理13380060528 | W142: 12750 | X142: ==W142*F142 -> 12750 | Y142: 三达膜 | Z142: 王立才13459293295 | AC142: 立升 | AD142: 房明亮15050461263 | AE142: 不报价 | AF142: 不报价
A143: 120 | B143: 膜控制系统软件编制 | E143: 项 | F143: 1 | U143: 碧水源 | V143: 车学理13380060528 | W143: 150000 | X143: ==W143*F143 -> 150000 | Y143: 三达膜 | Z143: 王立才13459293295 | AC143: 立升 | AD143: 房明亮15050461263 | AE143: 不报价 | AF143: 不报价
A144: 121 | B144: 膜控制系统现场调试服务 | E144: 项 | F144: 1 | U144: 碧水源 | V144: 车学理13380060528 | W144: 125000 | X144: ==W144*F144 -> 125000 | Y144: 三达膜 | Z144: 王立才13459293295 | AC144: 立升 | AD144: 房明亮15050461263 | AE144: 不报价 | AF144: 不报价
A145: 122 | B145: 仪表保护箱 | E145: 个 | F145: 32 | U145: 碧水源 | V145: 车学理13380060528 | W145: 3750 | X145: ==W145*F145 -> 120000 | Y145: 三达膜 | Z145: 王立才13459293295 | AC145: 立升 | AD145: 房明亮15050461263 | AE145: 不报价 | AF145: 不报价
A146: 123 | B146: 安装 | D146: 工艺设备、电气设备、仪表、阀门安装，工艺管道、电缆等材料及安装 | E146: 项 | F146: 1 | U146: 碧水源 | V146: 车学理13380060528 | W146: 6000000 | X146: ==W146*F146 -> 6000000 | Y146: 三达膜 | Z146: 王立才13459293295 | AC146: 立升 | AD146: 房明亮15050461263 | AE146: 不报价 | AF146: 不报价
A147: 六 | B147: 采购子包6:精确曝气系统及配套设备 | L147: ==L148 -> 3503352.6 | N147: ==N148 -> 5542000 | P147: ==P148 -> 3146847.6 | R147: ==R148 -> /
A148: 1 | B148: 电动线性空气调节阀 | D148: 适用于生化池空气管 道 | E148: 套 | F148: 4 | G148: 4000000 | H148: ==G148 -> 4000000 | I148: 4 | J148: 0.08 | K148: ==ROUND(S148*(1-J148),2) -> 3503352.6 | L148: ==K148 -> 3503352.6 | M148: ==220000+340000+200000+130000+180000+2760000+50000+20000*2+1500000+110000+12000 -> 5542000 | N148: ==M148 -> 5542000 | O148: ==2240000+120000+190000+266000+64064+47200+77800+91260+6600+36603+7320.6 -> 3146847.6 | P148: ==O148 -> 3146847.6 | Q148: / | R148: / | S148: ==AVERAGE(W148,AA148,AE148,AI148) -> 3807992 | T148: ==MIN(W148,AA148,AE148,AI148) -> 3415984 | U148: 冰得 | V148: 郑饶15899960814 | W148: 4200000 | X148: ==W148 -> 4200000 | Y148: 西门子 | Z148: 黄志豪13826107878@163.com | AA148: 不报价 | AB148: 不报价 | AC148: 威立雅 | AD148: 刘建源13590204531 | AE148: 模式不合适 | AF148: 模式不合适 | AG148: 赛莱默 | AH148: 孙河洋18688805759 | AI148: 3415984 | AJ148: ==AI148 -> 3415984
A149: 2 | B149: 热式气体流量计 | E149: 套 | F149: 4 | I149: 4 | U149: 冰得 | V149: 郑饶15899960814 | Y149: 西门子 | Z149: 黄志豪13826107878@163.com | AC149: 威立雅 | AD149: 刘建源13590204531 | AG149: 赛莱默 | AH149: 孙河洋18688805759
A150: 3 | B150: 曝气就地控制系统 | E150: 套 | F150: 4 | I150: 4 | U150: 冰得 | V150: 郑饶15899960814 | Y150: 西门子 | Z150: 黄志豪13826107878@163.com | AC150: 威立雅 | AD150: 刘建源13590204531 | AG150: 赛莱默 | AH150: 孙河洋18688805759
...

Sheet 工艺专业
A1: 设备价格表（含税）
A2: 单位工程：工艺专业
A3: 序号 | B3: 设备名称 | C3: 概算规格、型号 | D3: 施工图预算规格、型号 | E3: 单位 | F3: 数量 | G3: 概算 | I3: 南站水厂 | O3: 环城北 | P3: 中部净水厂 | Q3: 洛溪水厂 | R3: 询价均值 | S3: 询价最低值 | T3: 品牌1 | Z3: 品牌2 | AF3: 品牌3 | AL3: 品牌4
I4: 预算数量 | J4: 预算选用价格 | M4: 招控价选用价格
G5: 单价(元) | H5: 合价(元) | J5: 建议下浮率 | K5: 单价（元） | L5: 总价（元） | M5: 单价 | N5: 差额 | O5: 单价（元） | P5: 单价（元） | Q5: 单价（元） | T5: 公司名称 | U5: 联系人、联系电话 | V5: 单价（元） | W5: 下浮率 | X5: 下浮后单价（元） | Y5: 总价（元） | Z5: 公司名称 | AA5: 联系人、联系电话 | AB5: 单价（元） | AC5: 下浮率 | AD5: 下浮后单价（元） | AE5: 总价（元） | AF5: 公司名称 | AG5: 联系人、联系电话 | AH5: 单价（元） | AI5: 下浮率 | AJ5: 下浮后单价（元） | AK5: 总价（元） | AL5: 公司名称 | AM5: 联系人、联系电话 | AN5: 单价（元） | AO5: 下浮率 | AP5: 下浮后单价（元） | AQ5: 总价（元）
A6: 一 | B6: 进水闸门井、粗格栅及进水泵房
A7: 1 | B7: 进水速闭闸门 | D7: 断电速闭, 1400x1400mm , N=3kW ,配套一体式执行机构 | E7: 台 | F7: 1 | G7: ==416700 -> 416700 | H7: ==G7*F7 -> 416700 | I7: 1 | J7: ==AC7 -> 0.2 | K7: ==S7 -> 119200 | L7: ==F7*K7 -> 119200 | O7: 400000 | P7: 185000 (∅1200,P=1.5kW) | Q7: 780000 (DN1600 ，PN= 1.0MPa ，N=3kW) | R7: ==AVERAGE(X7,AD7,AJ7,AP7) -> 299200 | S7: ==MIN(X7,AD7,AJ7,AP7) -> 119200 | T7: 新环环保 | U7: 连皓文13500036502 | V7: 490000 | W7: 0.2 | X7: ==V7*(1-W7) -> 392000 | Y7: ==X7*I7 -> 392000 | Z7: 无锡通用 | AA7: 杨培根18961775586 | AB7: 149000 | AC7: 0.2 | AD7: ==AB7*(1-AC7) -> 119200 | AE7: ==AB7*I7 -> 149000 | AF7: 江苏南通 | AG7: 李向阳 15896274137 | AH7: 386400 | AJ7: ==AH7*(1-AI7) -> 386400 | AK7: ==AH7*I7 -> 386400
A8: 3 | B8: 格栅进水闸门 | D8: 不锈钢附壁方闸门, 1500 × 1500mm , N=2.2kW ,带手电一体启闭机 | E8: 台 | F8: 3 | G8: 123800 | H8: ==G8*F8 -> 371400 | I8: 3 | J8: ==AC8 -> 0.2 | K8: ==S8 -> 47920 | L8: ==F8*K8 -> 143760 | O8: 60375（B×H=1.50×1.35m，渠深2m，N=1.5kW） | P8: 123667（BxH=2.1X2.9m,P=2.2kw） | Q8: 68650(B*H= 1200*1200m N=0.45kw) | R8: ==AVERAGE(X8,AD8,AJ8,AP8) -> 74760 | S8: ==MIN(X8,AD8,AJ8,AP8) -> 47920 | T8: 新环环保 | U8: 连皓文13500036502 | V8: 118000 | W8: 0.2 | X8: ==V8*(1-W8) -> 94400 | Y8: ==X8*I8 -> 283200 | Z8: 无锡通用 | AA8: 杨培根18961775586 | AB8: 59900 | AC8: 0.2 | AD8: ==AB8*(1-AC8) -> 47920 | AE8: ==AB8*I8 -> 179700 | AF8: 江苏南通 | AG8: 李向阳 15896274137 | AH8: 81960 | AJ8: ==AH8*(1-AI8) -> 81960 | AK8: ==AH8*I8 -> 245880
A9: 4 | B9: 粗格栅 | D9: 钢丝绳牵引式格栅除污机,渠宽 1700mm ,栅隙 15mm , N=1.5+0.55kW ,单台过水量≥ 3300m3/h ,带防臭罩 | E9: 台 | F9: 2 | G9: 241700 | H9: ==G9*F9 -> 483400 | I9: 2 | J9: ==AC9 -> 0.2 | K9: ==S9 -> 228000 | L9: ==F9*K9 -> 456000 | Q9: 180000 | R9: ==AVERAGE(X9,AD9,AJ9,AP9) -> 356533.33 | S9: ==MIN(X9,AD9,AJ9,AP9) -> 228000 | T9: 新环环保 | U9: 连皓文13500036502 | V9: 650000 | W9: 0.2 | X9: ==V9*(1-W9) -> 520000 | Y9: ==X9*I9 -> 1040000 | Z9: 无锡通用 | AA9: 杨培根18961775586 | AB9: 285000 | AC9: 0.2 | AD9: ==AB9*(1-AC9) -> 228000 | AE9: ==AB9*I9 -> 570000 | AF9: 江苏南通 | AG9: 李向阳 15896274137 | AH9: 321600 | AJ9: ==AH9*(1-AI9) -> 321600 | AK9: ==AH9*I9 -> 643200
A10: 5 | B10: 格栅出水闸门 | D10: 不锈钢附壁方闸门, 1500 × 1500mm , N=2.2kW ,带手电一体启闭机 | E10: 台 | F10: 3 | G10: 123900 | H10: ==G10*F10 -> 371700 | I10: 3 | J10: ==AC10 -> 0.2 | K10: ==S10 -> 47920 | L10: ==F10*K10 -> 143760 | O10: 60375（B×H=1.50×1.35m，渠深2m，N=1.5kW） | P10: 123667（BxH=2.1X2.9m,P=2.2kw） | Q10: 107265 | R10: ==AVERAGE(X10,AD10,AJ10,AP10) -> 74760 | S10: ==MIN(X10,AD10,AJ10,AP10) -> 47920 | T10: 新环环保 | U10: 连皓文13500036502 | V10: 118000 | W10: 0.2 | X10: ==V10*(1-W10) -> 94400 | Y10: ==X10*I10 -> 283200 | Z10: 无锡通用 | AA10: 杨培根18961775586 | AB10: 59900 | AC10: 0.2 | AD10: ==AB10*(1-AC10) -> 47920 | AE10: ==AB10*I10 -> 179700 | AF10: 江苏南通 | AG10: 李向阳 15896274137 | AH10: 81960 | AJ10: ==AH10*(1-AI10) -> 81960 | AK10: ==AH10*I10 -> 245880
A11: 6 | B11: 泵房进水闸门 | D11: 不锈钢附壁方闸门, 1500 × 1500mm , N=2.2kW ,带手电一体启闭机 | E11: 台 | F11: 3 | G11: 124000 | H11: ==G11*F11 -> 372000 | I11: 3 | J11: ==AC11 -> 0.2 | K11: ==S11 -> 47920 | L11: ==F11*K11 -> 143760 | O11: 60375（B×H=1.50×1.35m，渠深2m，N=1.5kW） | P11: 123667（BxH=2.1X2.9m,P=2.2kw） | Q11: 107265 | R11: ==AVERAGE(X11,AD11,AJ11,AP11) -> 74760 | S11: ==MIN(X11,AD11,AJ11,AP11) -> 47920 | T11: 新环环保 | U11: 连皓文13500036502 | V11: 118000 | W11: 0.2 | X11: ==V11*(1-W11) -> 94400 | Y11: ==X11*I11 -> 283200 | Z11: 无锡通用 | AA11: 杨培根18961775586 | AB11: 59900 | AC11: 0.2 | AD11: ==AB11*(1-AC11) -> 47920 | AE11: ==AB11*I11 -> 179700 | AF11: 江苏南通 | AG11: 李向阳 15896274137 | AH11: 81960 | AJ11: ==AH11*(1-AI11) -> 81960 | AK11: ==AH11*I11 -> 245880
A12: 7 | B12: 螺旋输送机 | D12: 不锈钢无轴螺旋,Φ 300mm ,有效长度 L ≥ 10.0m N=2.2kW ,带密闭盖 | E12: 台 | F12: 1 | G12: 50400 | H12: ==G12*F12 -> 50400 | I12: 1 | J12: ==W12 -> 0.2 | K12: ==S12 -> 54400 | L12: ==F12*K12 -> 54400 | O12: 37900（DN300（U型断面）） | Q12: 104000 （400mm） | R12: ==AVERAGE(X12,AD12,AJ12,AP12) -> 88000 | S12: ==MIN(X12,AD12,AJ12,AP12) -> 54400 | T12: 新环环保 | U12: 连皓文13500036502 | V12: 68000 | W12: 0.2 | X12: ==V12*(1-W12) -> 54400 | Y12: ==X12*I12 -> 54400 | Z12: 无锡通用 | AA12: 杨培根18961775586 | AB12: 115000 | AC12: 0.2 | AD12: ==AB12*(1-AC12) -> 92000 | AE12: ==AB12*I12 -> 115000 | AF12: 江苏南通 | AG12: 李向阳 15896274137 | AH12: 117600 | AJ12: ==AH12*(1-AI12) -> 117600 | AK12: ==AH12*I12 -> 117600
A13: 8 | B13: 螺旋输送机 | D13: 不锈钢无轴螺旋,Φ 300mm ,有效长度 L ≥ 10.0m N=2.2kW ,带密闭盖 | E13: 台 | F13: 1 | G13: 66300 | H13: ==G13*F13 -> 66300 | I13: 1 | J13: ==W13 -> 0.2 | K13: ==S13 -> 54400 | L13: ==F13*K13 -> 54400 | O13: 37900（DN300（U型断面）） | Q13: 104000 （400mm） | R13: ==AVERAGE(X13,AD13,AJ13,AP13) -> 88000 | S13: ==MIN(X13,AD13,AJ13,AP13) -> 54400 | T13: 新环环保 | U13: 连皓文13500036502 | V13: 68000 | W13: 0.2 | X13: ==V13*(1-W13) -> 54400 | Y13: ==X13*I13 -> 54400 | Z13: 无锡通用 | AA13: 杨培根18961775586 | AB13: 115000 | AC13: 0.2 | AD13: ==AB13*(1-AC13) -> 92000 | AE13: ==AB13*I13 -> 115000 | AF13: 江苏南通 | AG13: 李向阳 15896274137 | AH13: 117600 | AJ13: ==AH13*(1-AI13) -> 117600 | AK13: ==AH13*I13 -> 117600
A14: 9 | B14: 垃圾斗车 | D14: 容积 1 立方米,与螺旋输送机配套 | E14: 个 | F14: 1 | G14: 5200 | H14: ==G14*F14 -> 5200 | I14: 1 | J14: ==AC14 -> 0.2 | K14: ==S14 -> 5200 | L14: ==F14*K14 -> 5200 | O14: 6000 | Q14: 5000 | R14: ==AVERAGE(X14,AD14,AJ14,AP14) -> 6466.6667 | S14: ==MIN(X14,AD14,AJ14,AP14) -> 5200 | T14: 新环环保 | U14: 连皓文13500036502 | V14: 8000 | W14: 0.2 | X14: ==V14*(1-W14) -> 6400 | Y14: ==X14*I14 -> 6400 | Z14: 无锡通用 | AA14: 杨培根18961775586 | AB14: 6500 | AC14: 0.2 | AD14: ==AB14*(1-AC14) -> 5200 | AE14: ==AB14*I14 -> 6500 | AF14: 江苏南通 | AG14: 李向阳 15896274137 | AH14: 7800 | AJ14: ==AH14*(1-AI14) -> 7800 | AK14: ==AH14*I14 -> 7800
A15: 10 | B15: 电动葫芦 | D15: 起重量 3T ,起吊高度 18m ,行程 26m , N=4.9kW | E15: 台 | F15: 1 | G15: 33600 | H15: ==G15*F15 -> 33600 | I15: 1 | J15: ==AI15 -> 0 | K15: ==S15 -> 14500 | L15: ==F15*K15 -> 14500 | O15: 65000（起吊重量3T，4.5+0.4kw） | P15: 30000 | Q15: 81054（12m） | R15: ==AVERAGE(X15,AD15,AJ15,AP15) -> 48000 | S15: ==MIN(X15,AD15,AJ15,AP15) -> 14500 | T15: 广州起重机械 | U15: 谢启康13430264951 | V15: 105000 | W15: 0.1 | X15: ==V15*(1-W15) -> 94500 | Y15: ==X15*I15 -> 94500 | Z15: 广州泰克力 | AA15: 陈经理13570054553 | AB15: 35000 | AD15: ==AB15*(1-AC15) -> 35000 | AE15: ==AB15*I15 -> 35000 | AF15: 广东永通 | AG15: 陈经理13924880284 | AH15: 14500 | AJ15: ==AH15*(1-AI15) -> 14500 | AK15: ==AH15*I15 -> 14500
A16: 11 | B16: 进水电动偏心半球 阀 | D16: DN1400 , PN10 , N=4kW | E16: 台 | F16: 1 | G16: 884500 | H16: ==G16*F16 -> 884500 | I16: 1 | J16: ==AC16 -> 0 | K16: ==S16 -> 847055 | L16: ==F16*K16 -> 847055 | M16: ==K16*0.85 -> 719996.75 | N16: ==M16*I16-I16*K16 -> -127058.25 | O16: 459000（液压偏心半球阀DN1200） | Q16: 860000 （DN1600） | R16: ==AVERAGE(X16,AD16,AJ16,AP16) -> 1013076.5 | S16: ==MIN(X16,AD16,AJ16,AP16) -> 847055 | T16: 冠龙 | U16: 黄经理13925121566 | V16: 1813997 | W16: 0.35 | X16: ==V16*(1-W16) -> 1179098.1 | Y16: ==X16*I16 -> 1179098.1 | Z16: 德国VAG | AA16: 吴居并13922353009 | AB16: 847055 | AD16: ==AB16*(1-AC16) -> 847055 | AE16: ==AB16*I16 -> 847055 | AF16: 丹麦AVK | AG16: 蔡文亮13570037656 | AH16: 不生产 | AJ16: 不生产 | AK16: 不生产
A17: 12 | B17: 止回阀 | D17: DN700 , PN10 | E17: 个 | F17: 2 | G17: 162500 | H17: ==G17*F17 -> 325000 | I17: 2 | J17: ==AI17 -> 0 | K17: ==S17 -> 53234 | L17: ==F17*K17 -> 106468 | O17: 8000（DN600） | Q17: 51186 | R17: ==AVERAGE(X17,AD17,AJ17,AP17) -> 83412.333 | S17: ==MIN(X17,AD17,AJ17,AP17) -> 53234 | T17: 冠龙 | U17: 黄经理13925121566 | V17: 158200 | W17: 0.35 | X17: ==V17*(1-W17) -> 102830 | Y17: ==X17*I17 -> 205660 | Z17: 德国VAG | AA17: 吴居并13922353009 | AB17: 94173 | AD17: ==AB17*(1-AC17) -> 94173 | AE17: ==AB17*I17 -> 188346 | AF17: 丹麦AVK | AG17: 蔡文亮13570037656 | AH17: 53234 | AJ17: ==AH17*(1-AI17) -> 53234 | AK17: ==AH17*I17 -> 106468
A18: 13 | B18: 橡胶接头 | D18: DN700 , PN10 | E18: 个 | F18: 2 | G18: 3200 | H18: ==G18*F18 -> 6400 | I18: 2 | J18: ==AI18 -> 0 | K18: ==S18 -> 6515 | L18: ==F18*K18 -> 13030 | O18: 8039（DN600） | Q18: 4830 | R18: ==AVERAGE(X18,AD18,AJ18,AP18) -> 11286.033 | S18: ==MIN(X18,AD18,AJ18,AP18) -> 6515 | T18: 冠龙 | U18: 黄经理13925121566 | V18: 14534 | W18: 0.35 | X18: ==V18*(1-W18) -> 9447.1 | Y18: ==X18*I18 -> 18894.2 | Z18: 德国VAG | AA18: 吴居并13922353009 | AB18: 17896 | AD18: ==AB18*(1-AC18) -> 17896 | AE18: ==AB18*I18 -> 35792 | AF18: 丹麦AVK | AG18: 蔡文亮13570037656 | AH18: 6515 | AJ18: ==AH18*(1-AI18) -> 6515 | AK18: ==AH18*I18 -> 13030
A19: 14 | B19: 电动蝶阀 | D19: DN700 , PN10 ,开关型 | E19: 个 | F19: 2 | G19: 87200 | H19: ==G19*F19 -> 174400 | I19: 2 | J19: ==W19 -> 0.35 | K19: ==S19 -> 61006.4 | L19: ==F19*K19 -> 122012.8 | O19: 108822 （DN1400） | Q19: 97886 (DN900) | R19: ==AVERAGE(X19,AD19,AJ19,AP19) -> 76832.133 | S19: ==MIN(X19,AD19,AJ19,AP19) -> 61006.4 | T19: 冠龙 | U19: 黄经理13925121566 | V19: 93856 | W19: 0.35 | X19: ==V19*(1-W19) -> 61006.4 | Y19: ==X19*I19 -> 122012.8 | Z19: 德国VAG | AA19: 吴居并13922353009 | AB19: 99108 | AD19: ==AB19*(1-AC19) -> 99108 | AE19: ==AB19*I19 -> 198216 | AF19: 丹麦AVK | AG19: 蔡文亮13570037656 | AH19: 70382 | AJ19: ==AH19*(1-AI19) -> 70382 | AK19: ==AH19*I19 -> 140764
A20: 15 | B20: 橡胶接头 | D20: DN1400 , PN10 | E20: 个 | F20: 1 | G20: 14200 | H20: ==G20*F20 -> 14200 | I20: 1 | J20: ==AI20 -> 0 | K20: ==S20 -> 17482 | L20: ==F20*K20 -> 17482 | O20: 46434 | Q20: 5750 （DN800） | R20: ==AVERAGE(X20,AD20,AJ20,AP20) -> 38090.95 | S20: ==MIN(X20,AD20,AJ20,AP20) -> 17482 | T20: 冠龙 | U20: 黄经理13925121566 | V20: 55449 | W20: 0.35 | X20: ==V20*(1-W20) -> 36041.85 | Y20: ==X20*I20 -> 36041.85 | Z20: 德国VAG | AA20: 吴居并13922353009 | AB20: 60749 | AD20: ==AB20*(1-AC20) -> 60749 | AE20: ==AB20*I20 -> 60749 | AF20: 丹麦AVK | AG20: 蔡文亮13570037656 | AH20: 17482 | AJ20: ==AH20*(1-AI20) -> 17482 | AK20: ==AH20*I20 -> 17482
A21: 16 | B21: 电动蝶阀 | D21: DN500 , PN10 ,开关型 | E21: 个 | F21: 2 | G21: 72700 | H21: ==G21*F21 -> 145400 | I21: 2 | J21: ==AI21 -> 0 | K21: ==S21 -> 40808 | L21: ==F21*K21 -> 81616 | O21: 35897（DN600） | Q21: 35149 （DN200） | R21: ==AVERAGE(X21,AD21,AJ21,AP21) -> 57820.117 | S21: ==MIN(X21,AD21,AJ21,AP21) -> 40808 | T21: 冠龙 | U21: 黄经理13925121566 | V21: 77219 | W21: 0.35 | X21: ==V21*(1-W21) -> 50192.35 | Y21: ==X21*I21 -> 100384.7 | Z21: 德国VAG | AA21: 吴居并13922353009 | AB21: 82460 | AD21: ==AB21*(1-AC21) -> 82460 | AE21: ==AB21*I21 -> 164920 | AF21: 丹麦AVK | AG21: 蔡文亮13570037656 | AH21: 40808 | AJ21: ==AH21*(1-AI21) -> 40808 | AK21: ==AH21*I21 -> 81616
A22: 17 | B22: 蝶阀 | D22: DN1200 , PN10 | E22: 个 | F22: 1 | G22: 74100 | H22: ==G22*F22 -> 74100 | I22: 1 | J22: ==W22 -> 0.35 | K22: ==S22 -> 61425 | L22: ==F22*K22 -> 61425 | O22: 93812(电动 ) | Q22: 114800(电动调节法兰式蝶阀) | R22: ==AVERAGE(X22,AD22,AJ22,AP22) -> 92438 | S22: ==MIN(X22,AD22,AJ22,AP22) -> 61425 | T22: 冠龙 | U22: 黄经理13925121566 | V22: 94500 | W22: 0.35 | X22: ==V22*(1-W22) -> 61425 | Y22: ==X22*I22 -> 61425 | Z22: 德国VAG | AA22: 吴居并13922353009 | AB22: 130451 | AD22: ==AB22*(1-AC22) -> 130451 | AE22: ==AB22*I22 -> 130451 | AF22: 丹麦AVK | AG22: 蔡文亮13570037656 | AH22: 85438 | AJ22: ==AH22*(1-AI22) -> 85438 | AK22: ==AH22*I22 -> 85438
A23: 18 | B23: 止回阀 | D23: DN500，PN10 | E23: 个 | F23: 2 | G23: 3837.6 | H23: ==G23*F23 -> 7675.2 | I23: 2 | J23: ==AI23 -> 0 | K23: ==S23 -> 43851 | L23: ==F23*K23 -> 87702 | O23: 8000（DN600） | Q23: 38512 （DN600） | R23: ==AVERAGE(X23,AD23,AJ23,AP23) -> 50769 | S23: ==MIN(X23,AD23,AJ23,AP23) -> 43851 | T23: 冠龙 | U23: 黄经理13925121566 | V23: 69300 | W23: 0.35 | X23: ==V23*(1-W23) -> 45045 | Y23: ==X23*I23 -> 90090 | Z23: 德国VAG | AA23: 吴居并13922353009 | AB23: 63411 | AD23: ==AB23*(1-AC23) -> 63411 | AE23: ==AB23*I23 -> 126822 | AF23: 丹麦AVK | AG23: 蔡文亮13570037656 | AH23: 43851 | AJ23: ==AH23*(1-AI23) -> 43851 | AK23: ==AH23*I23 -> 87702
A24: 19 | B24: 手动蝶阀 | D24: DN100，PN10 | E24: 个 | F24: 4 | G24: 288.725 | H24: ==G24*F24 -> 1154.9 | I24: 4 | J24: ==AI24 -> 0 | K24: ==S24 -> 515 | L24: ==F24*K24 -> 2060 | Q24: / | R24: ==AVERAGE(X24,AD24,AJ24,AP24) -> 4024.5 | S24: ==MIN(X24,AD24,AJ24,AP24) -> 515 | T24: 冠龙 | U24: 黄经理13925121566 | V24: 2030 | W24: 0.35 | X24: ==V24*(1-W24) -> 1319.5 | Y24: ==X24*I24 -> 5278 | Z24: 德国VAG | AA24: 吴居并13922353009 | AB24: 10239 | AD24: ==AB24*(1-AC24) -> 10239 | AE24: ==AB24*I24 -> 40956 | AF24: 丹麦AVK | AG24: 蔡文亮13570037656 | AH24: 515 | AJ24: ==AH24*(1-AI24) -> 515 | AK24: ==AH24*I24 -> 2060
A25: 20 | B25: 手动蝶阀 | D25: DN150，PN10 | E25: 个 | F25: ==6+5 -> 11 | G25: 465.253 | H25: ==G25*F25 -> 5117.783 | I25: ==6+5 -> 11 | J25: ==AI25 -> 0 | K25: ==S25 -> 904 | L25: ==F25*K25 -> 9944 | Q25: 1863 | R25: ==AVERAGE(X25,AD25,AJ25,AP25) -> 4568.1667 | S25: ==MIN(X25,AD25,AJ25,AP25) -> 904 | T25: 冠龙 | U25: 黄经理13925121566 | V25: 3010 | W25: 0.35 | X25: ==V25*(1-W25) -> 1956.5 | Y25: ==X25*I25 -> 21521.5 | Z25: 德国VAG | AA25: 吴居并13922353009 | AB25: 10844 | AD25: ==AB25*(1-AC25) -> 10844 | AE25: ==AB25*I25 -> 119284 | AF25: 丹麦AVK | AG25: 蔡文亮13570037656 | AH25: 904 | AJ25: ==AH25*(1-AI25) -> 904 | AK25: ==AH25*I25 -> 9944
A26: 21 | B26: 止回阀 | D26: DN100，PN10 | E26: 个 | F26: 4 | H26: ==G26*F26 -> 0 | I26: 4 | J26: ==W26 -> 0.35 | K26: ==S26 -> 1619.8 | L26: ==F26*K26 -> 6479.2 | Q26: 4485 （DN200） | R26: ==AVERAGE(X26,AD26,AJ26,AP26) -> 2514.6 | S26: ==MIN(X26,AD26,AJ26,AP26) -> 1619.8 | T26: 冠龙 | U26: 黄经理13925121566 | V26: 2492 | W26: 0.35 | X26: ==V26*(1-W26) -> 1619.8 | Y26: ==X26*I26 -> 6479.2 | Z26: 德国VAG | AA26: 吴居并13922353009 | AB26: 4125 | AD26: ==AB26*(1-AC26) -> 4125 | AE26: ==AB26*I26 -> 16500 | AF26: 丹麦AVK | AG26: 蔡文亮13570037656 | AH26: 1799 | AJ26: ==AH26*(1-AI26) -> 1799 | AK26: ==AH26*I26 -> 7196
A27: 22 | B27: 止回阀 | D27: DN150，PN10 | E27: 个 | F27: 3 | G27: 2408 | H27: ==G27*F27 -> 7224 | I27: 3 | J27: ==AI27 -> 0 | K27: ==S27 -> 3047 | L27: ==F27*K27 -> 9141 | Q27: 3022.5 | R27: ==AVERAGE(X27,AD27,AJ27,AP27) -> 3731.6333 | S27: ==MIN(X27,AD27,AJ27,AP27) -> 3047 | T27: 冠龙 | U27: 黄经理13925121566 | V27: 4746 | W27: 0.35 | X27: ==V27*(1-W27) -> 3084.9 | Y27: ==X27*I27 -> 9254.7 | Z27: 德国VAG | AA27: 吴居并13922353009 | AB27: 5063 | AD27: ==AB27*(1-AC27) -> 5063 | AE27: ==AB27*I27 -> 15189 | AF27: 丹麦AVK | AG27: 蔡文亮13570037656 | AH27: 3047 | AJ27: ==AH27*(1-AI27) -> 3047 | AK27: ==AH27*I27 -> 9141
A28: 23 | B28: 球阀 | D28: DN32 | E28: 个 | F28: 5 | G28: 16.499 | H28: ==G28*F28 -> 82.495 | I28: 5 | J28: ==AI28 -> 0 | K28: ==S28 -> 215 | L28: ==F28*K28 -> 1075 | Q28: 40（DN25） | R28: ==AVERAGE(X28,AD28,AJ28,AP28) -> 1518 | S28: ==MIN(X28,AD28,AJ28,AP28) -> 215 | T28: 冠龙 | U28: 黄经理13925121566 | V28: 1280 | W28: 0.35 | X28: ==V28*(1-W28) -> 832 | Y28: ==X28*I28 -> 4160 | Z28: 德国VAG | AA28: 吴居并13922353009 | AB28: 3507 | AD28: ==AB28*(1-AC28) -> 3507 | AE28: ==AB28*I28 -> 17535 | AF28: 丹麦AVK | AG28: 蔡文亮13570037656 | AH28: 215 | AJ28: ==AH28*(1-AI28) -> 215 | AK28: ==AH28*I28 -> 1075
A29: 24 | B29: 手动蝶阀 | D29: DN200，PN10 | E29: 个 | F29: 2 | G29: 2437.948 | H29: ==G29*F29 -> 4875.896 | I29: 2 | J29: ==AI29 -> 0 | K29: ==S29 -> 1458 | L29: ==F29*K29 -> 2916 | Q29: 1863 （DN150） | R29: ==AVERAGE(X29,AD29,AJ29,AP29) -> 5211.3 | S29: ==MIN(X29,AD29,AJ29,AP29) -> 1458 | T29: 冠龙 | U29: 黄经理13925121566 | V29: 4326 | W29: 0.35 | X29: ==V29*(1-W29) -> 2811.9 | Y29: ==X29*I29 -> 5623.8 | Z29: 德国VAG | AA29: 吴居并13922353009 | AB29: 11364 | AD29: ==AB29*(1-AC29) -> 11364 | AE29: ==AB29*I29 -> 22728 | AF29: 丹麦AVK | AG29: 蔡文亮13570037656 | AH29: 1458 | AJ29: ==AH29*(1-AI29) -> 1458 | AK29: ==AH29*I29 -> 2916
A30: 25 | B30: 止回阀 | D30: DN50，PN10 | E30: 个 | F30: 2 | G30: 138.4 | H30: ==G30*F30 -> 276.8 | I30: 2 | J30: ==W30 -> 0.35 | K30: ==S30 -> 800.8 | L30: ==F30*K30 -> 1601.6 | Q30: / | R30: ==AVERAGE(X30,AD30,AJ30,AP30) -> 1767.9333 | S30: ==MIN(X30,AD30,AJ30,AP30) -> 800.8 | T30: 冠龙 | U30: 黄经理13925121566 | V30: 1232 | W30: 0.35 | X30: ==V30*(1-W30) -> 800.8 | Y30: ==X30*I30 -> 1601.6 | Z30: 德国VAG | AA30: 吴居并13922353009 | AB30: 3260 | AD30: ==AB30*(1-AC30) -> 3260 | AE30: ==AB30*I30 -> 6520 | AF30: 丹麦AVK | AG30: 蔡文亮13570037656 | AH30: 1243 | AJ30: ==AH30*(1-AI30) -> 1243 | AK30: ==AH30*I30 -> 2486
A31: 26 | B31: 手动蝶阀 | D31: DN50，PN10 | E31: 个 | F31: 2 | G31: 210.004 | H31: ==G31*F31 -> 420.008 | I31: 2 | J31: ==AI31 -> 0 | K31: ==S31 -> 298 | L31: ==F31*K31 -> 596 | Q31: / | R31: ==AVERAGE(X31,AD31,AJ31,AP31) -> 3561.6667 | S31: ==MIN(X31,AD31,AJ31,AP31) -> 298 | T31: 冠龙 | U31: 黄经理13925121566 | V31: 1260 | W31: 0.35 | X31: ==V31*(1-W31) -> 819 | Y31: ==X31*I31 -> 1638 | Z31: 德国VAG | AA31: 吴居并13922353009 | AB31: 9568 | AD31: ==AB31*(1-AC31) -> 9568 | AE31: ==AB31*I31 -> 19136 | AF31: 丹麦AVK | AG31: 蔡文亮13570037656 | AH31: 298 | AJ31: ==AH31*(1-AI31) -> 298 | AK31: ==AH31*I31 -> 596
A32: 27 | B32: 闸阀 | D32: DN50，PN10 | E32: 个 | F32: 4 | H32: ==G32*F32 -> 0 | I32: 4 | J32: 0 | K32: 300 | L32: ==F32*K32 -> 1200 | Q32: / | R32: ==AVERAGE(X32,AD32,AJ32,AP32) -> 100 | S32: ==MIN(X32,AD32,AJ32,AP32) -> 0 | AD32: ==AB32*(1-AC32) -> 0 | AJ32: ==AH32*(1-AI32) -> 0 | AO32: 参考大龙 | AP32: 300
A33: 二 | B33: 细格栅渠
A34: 1 | B34: 格栅进出水闸门 | D34: 不锈钢门式插板闸,渠宽 1.5m ,渠深 2.5m ,水深 1.3m , N=2.2kW | E34: 台 | F34: 8 | G34: 88300 | H34: ==G34*F34 -> 706400 | I34: 8 | J34: ==AC34 -> 0.2 | K34: ==S34 -> 40400 | L34: ==K34*I34 -> 323200 | O34: 87600（B×H=1.6×2.4m，渠深30m，N=1.5kW） | Q34: 56000（B*H=900*2400m） | R34: ==AVERAGE(X34,AD34,AJ34,AP34) -> 57533.333 | S34: ==MIN(X34,AD34,AJ34,AP34) -> 40400 | T34: 新环环保 | U34: 连皓文13500036502 | V34: 88000 | W34: 0.2 | X34: ==V34*(1-W34) -> 70400 | Y34: ==X34*I34 -> 563200 | Z34: 无锡通用 | AA34: 杨培根18961775586 | AB34: 50500 | AC34: 0.2 | AD34: ==AB34*(1-AC34) -> 40400 | AE34: ==AB34*I34 -> 404000 | AF34: 江苏南通 | AG34: 李向阳 15896274137 | AH34: 61800 | AJ34: ==AH34*(1-AI34) -> 61800 | AK34: ==AH34*I34 -> 494400
A35: 2 | B35: 垃圾斗车 | D35: 容积 1 立方米,与螺旋压榨机配套 | E35: 台 | F35: 1 | G35: 5200 | H35: ==G35*F35 -> 5200 | I35: 1 | J35: ==AC35 -> 0.2 | K35: ==S35 -> 5200 | L35: ==K35*I35 -> 5200 | O35: 6000 | Q35: 5000 | R35: ==AVERAGE(X35,AD35,AJ35,AP35) -> 6466.6667 | S35: ==MIN(X35,AD35,AJ35,AP35) -> 5200 | T35: 新环环保 | U35: 连皓文13500036502 | V35: 8000 | W35: 0.2 | X35: ==V35*(1-W35) -> 6400 | Y35: ==X35*I35 -> 6400 | Z35: 无锡通用 | AA35: 杨培根18961775586 | AB35: 6500 | AC35: 0.2 | AD35: ==AB35*(1-AC35) -> 5200 | AE35: ==AB35*I35 -> 6500 | AF35: 江苏南通 | AG35: 李向阳 15896274137 | AH35: 7800 | AJ35: ==AH35*(1-AI35) -> 7800 | AK35: ==AH35*I35 -> 7800
A36: 三 | B36: 曝气沉砂池
A37: 1 | B37: 进水闸门 | D37: 不锈钢附壁方闸门, B × H=1500mm × 2500mm , N=2.2kW ,带手电一体启闭机 | E37: 套 | F37: 2 | G37: 85600 | H37: ==G37*F37 -> 171200 | I37: 2 | J37: ==AC37 -> 0.2 | K37: ==S37 -> 50800 | L37: ==K37*I37 -> 101600 | O37: 60375（B×H=1.50×1.35m，渠深2m，N=1.5kW） | Q37: 62080（BxH=2000x1500 ） | R37: ==AVERAGE(X37,AD37,AJ37,AP37) -> 85000 | S37: ==MIN(X37,AD37,AJ37,AP37) -> 50800 | T37: 新环环保 | U37: 连皓文13500036502 | V37: 118000 | W37: 0.2 | X37: ==V37*(1-W37) -> 94400 | Y37: ==X37*I37 -> 188800 | Z37: 无锡通用 | AA37: 杨培根18961775586 | AB37: 63500 | AC37: 0.2 | AD37: ==AB37*(1-AC37) -> 50800 | AE37: ==AB37*I37 -> 127000 | AF37: 江苏南通 | AG37: 李向阳 15896274137 | AH37: 109800 | AJ37: ==AH37*(1-AI37) -> 109800 | AK37: ==AH37*I37 -> 219600
A38: 2 | B38: 桥式刮砂机 | D38: 行程 L=22.3m ,宽度 B=4.4m , N=0.75+1.1kW ,水下部件不锈钢 | E38: 套 | F38: 2 | G38: 136200 | H38: ==G38*F38 -> 272400 | I38: 2 | J38: ==W38 -> 0.2 | K38: ==S38 -> 156800 | L38: ==K38*I38 -> 313600 | O38: 975000（15万m3/d） | Q38: 150000（L=18.5m） | R38: ==AVERAGE(X38,AD38,AJ38,AP38) -> 204933.33 | S38: ==MIN(X38,AD38,AJ38,AP38) -> 156800 | T38: 新环环保 | U38: 连皓文13500036502 | V38: 196000 | W38: 0.2 | X38: ==V38*(1-W38) -> 156800 | Y38: ==X38*I38 -> 313600 | Z38: 无锡通用 | AA38: 杨培根18961775586 | AB38: 295000 | AC38: 0.2 | AD38: ==AB38*(1-AC38) -> 236000 | AE38: ==AB38*I38 -> 590000 | AF38: 江苏南通 | AG38: 李向阳 15896274137 | AH38: 222000 | AJ38: ==AH38*(1-AI38) -> 222000 | AK38: ==AH38*I38 -> 444000
A39: 3 | B39: 排砂泵 | D39: Q=12L/s , H=10m , N=0.55kW ,定制设备,含水下吸砂管系统及配件,砂接触部件为耐磨耐腐蚀材质 | E39: 套 | F39: 4 | G39: 29900 | H39: ==G39*F39 -> 119600 | I39: 4 | J39: ==W39 -> 0.2 | K39: ==S39 -> 8000 | L39: ==K39*I39 -> 32000 | Q39: 15000（Q=30m3/h） | R39: ==AVERAGE(X39,AD39,AJ39,AP39) -> 36266.667 | S39: ==MIN(X39,AD39,AJ39,AP39) -> 8000 | T39: 新环环保 | U39: 连皓文13500036502 | V39: 10000 | W39: 0.2 | X39: ==V39*(1-W39) -> 8000 | Y39: ==X39*I39 -> 32000 | Z39: 无锡通用 | AA39: 杨培根18961775586 | AB39: 28500 | AC39: 0.2 | AD39: ==AB39*(1-AC39) -> 22800 | AE39: ==AB39*I39 -> 114000 | AF39: 江苏南通 | AG39: 李向阳 15896274137 | AH39: 78000 | AJ39: ==AH39*(1-AI39) -> 78000 | AK39: ==AH39*I39 -> 312000
A40: 4 | B40: 砂水分离器 | D40: Q=15~20L/s , N=1.5kW ,不锈钢材质 | E40: 套 | F40: 2 | G40: 61300 | H40: ==G40*F40 -> 122600 | I40: 2 | J40: ==W40 -> 0.2 | K40: ==S40 -> 57600 | L40: ==K40*I40 -> 115200 | Q40: 80000 | R40: ==AVERAGE(X40,AD40,AJ40,AP40) -> 74000 | S40: ==MIN(X40,AD40,AJ40,AP40) -> 57600 | T40: 新环环保 | U40: 连皓文13500036502 | V40: 72000 | W40: 0.2 | X40: ==V40*(1-W40) -> 57600 | Y40: ==X40*I40 -> 115200 | Z40: 无锡通用 | AA40: 杨培根18961775586 | AB40: 78000 | AC40: 0.2 | AD40: ==AB40*(1-AC40) -> 62400 | AE40: ==AB40*I40 -> 156000 | AF40: 江苏南通 | AG40: 李向阳 15896274137 | AH40: 102000 | AJ40: ==AH40*(1-AI40) -> 102000 | AK40: ==AH40*I40 -> 204000
A41: 5 | B41: 垃圾斗车 | D41: 容积 1 立方米,与砂水分离器配套 | E41: 个 | F41: 1 | G41: 5200 | H41: ==G41*F41 -> 5200 | I41: 1 | J41: ==AC41 -> 0.2 | K41: ==S41 -> 5200 | L41: ==K41*I41 -> 5200 | Q41: 5000 | R41: ==AVERAGE(X41,AD41,AJ41,AP41) -> 6466.6667 | S41: ==MIN(X41,AD41,AJ41,AP41) -> 5200 | T41: 新环环保 | U41: 连皓文13500036502 | V41: 8000 | W41: 0.2 | X41: ==V41*(1-W41) -> 6400 | Y41: ==X41*I41 -> 6400 | Z41: 无锡通用 | AA41: 杨培根18961775586 | AB41: 6500 | AC41: 0.2 | AD41: ==AB41*(1-AC41) -> 5200 | AE41: ==AB41*I41 -> 6500 | AF41: 江苏南通 | AG41: 李向阳 15896274137 | AH41: 7800 | AJ41: ==AH41*(1-AI41) -> 7800 | AK41: ==AH41*I41 -> 7800
A42: 6 | B42: 整流栅条 | D42: 玻璃钢栅条, L × B ×δ =2100mm × 100mm × 8mm | E42: 条 | F42: 160 | G42: 2000 | H42: ==G42*F42 -> 320000 | I42: 160 | J42: ==AC42 -> 0.2 | K42: ==S42 -> 304 | L42: ==K42*I42 -> 48640 | Q42: 220 | R42: ==AVERAGE(X42,AD42,AJ42,AP42) -> 1121.3333 | S42: ==MIN(X42,AD42,AJ42,AP42) -> 304 | T42: 新环环保 | U42: 连皓文13500036502 | V42: 3000 | W42: 0.2 | X42: ==V42*(1-W42) -> 2400 | Y42: ==X42*I42 -> 384000 | Z42: 无锡通用 | AA42: 杨培根18961775586 | AB42: 380 | AC42: 0.2 | AD42: ==AB42*(1-AC42) -> 304 | AE42: ==AB42*I42 -> 60800 | AF42: 江苏南通 | AG42: 李向阳 15896274137 | AH42: 660 | AJ42: ==AH42*(1-AI42) -> 660 | AK42: ==AH42*I42 -> 105600
A43: 7 | B43: 曝气风机 | D43: 罗茨鼓风机, Q=12m3/min , P=40kPa , N=15kW ,含进出口消声器、隔音罩及放空阀配件,含变频 | E43: 台 | F43: 3 | G43: 361000 | H43: ==G43*F43 -> 1083000 | I43: 3 | J43: ==AC43 -> 0 | K43: ==S43 -> 23300 | L43: ==K43*I43 -> 69900 | Q43: 130000（Q=9.0m3/min） | R43: ==AVERAGE(X43,AD43,AJ43,AP43) -> 72188.89 | S43: ==MIN(X43,AD43,AJ43,AP43) -> 23300 | T43: 百事德 | U43: 吴旭东13801532692 | V43: 33266.67 | X43: ==V43*(1-W43) -> 33266.67 | Y43: ==X43*I43 -> 99800.01 | Z43: 华东风机 | AA43: 刘凯15098911867 | AB43: 23300 | AD43: ==AB43*(1-AC43) -> 23300 | AE43: ==AB43*I43 -> 69900 | AF43: 德国艾珍 | AG43: 张总13342912691 | AH43: 160000 | AJ43: ==AH43*(1-AI43) -> 160000 | AK43: ==AH43*I43 -> 480000 | AL43: 英格索兰hibon | AM43: 何工13189049131 | AN43: 550000 | AQ43: ==AN43*I43 -> 1650000
A44: 8 | B44: 电动调节蝶阀 | D44: DN200 , PN10 | E44: 台 | F44: 3 | G44: 24900 | H44: ==G44*F44 -> 74700 | I44: 3 | J44: ==W44 -> 0.35 | K44: ==S44 -> 28923.7 | L44: ==K44*I44 -> 86771.1 | O44: 10500 | Q44: 34620 （DN250） | R44: ==AVERAGE(X44,AD44,AJ44,AP44) -> 40244.9 | S44: ==MIN(X44,AD44,AJ44,AP44) -> 28923.7 | T44: 冠龙 | U44: 黄经理13925121566 | V44: 44498 | W44: 0.35 | X44: ==V44*(1-W44) -> 28923.7 | Y44: ==X44*I44 -> 86771.1 | Z44: 德国VAG | AA44: 吴居并13922353009 | AB44: 49865 | AD44: ==AB44*(1-AC44) -> 49865 | AE44: ==AB44*I44 -> 149595 | AF44: 丹麦AVK | AG44: 蔡文亮13570037656 | AH44: 41946 | AJ44: ==AH44*(1-AI44) -> 41946 | AK44: ==AH44*I44 -> 125838
A45: 四 | B45: 膜格栅渠
A46: 1 | B46: 格栅进水闸门 | D46: 不锈钢叠梁闸,渠宽 1.6m ,渠深 5.25m ,水深 3.2m | E46: 台 | F46: 10 | G46: 24800 | H46: ==G46*F46 -> 248000 | I46: 10 | J46: ==AC46 -> 0.2 | K46: ==S46 -> 42800 | L46: ==K46*I46 -> 428000 | O46: 112425 （1400×5000） | R46: ==AVERAGE(X46,AD46,AJ46,AP46) -> 56133.333 | S46: ==MIN(X46,AD46,AJ46,AP46) -> 42800 | T46: 新环环保 | U46: 连皓文13500036502 | V46: 55000 | W46: 0.2 | X46: ==V46*(1-W46) -> 44000 | Y46: ==X46*I46 -> 440000 | Z46: 无锡通用 | AA46: 杨培根18961775586 | AB46: 53500 | AC46: 0.2 | AD46: ==AB46*(1-AC46) -> 42800 | AE46: ==AB46*I46 -> 535000 | AF46: 江苏南通 | AG46: 李向阳 15896274137 | AH46: 81600 | AJ46: ==AH46*(1-AI46) -> 81600 | AK46: ==AH46*I46 -> 816000
A47: 2 | B47: 垃圾斗车 | D47: 容积 1 立方米,与螺旋压榨机配套 | E47: 套 | F47: 1 | G47: 5200 | H47: ==G47*F47 -> 5200 | I47: 1 | J47: ==AC47 -> 0.2 | K47: ==S47 -> 5200 | L47: ==K47*I47 -> 5200 | O47: 6000 | Q47: 5000 | R47: ==AVERAGE(X47,AD47,AJ47,AP47) -> 6466.6667 | S47: ==MIN(X47,AD47,AJ47,AP47) -> 5200 | T47: 新环环保 | U47: 连皓文13500036502 | V47: 8000 | W47: 0.2 | X47: ==V47*(1-W47) -> 6400 | Y47: ==X47*I47 -> 6400 | Z47: 无锡通用 | AA47: 杨培根18961775586 | AB47: 6500 | AC47: 0.2 | AD47: ==AB47*(1-AC47) -> 5200 | AE47: ==AB47*I47 -> 6500 | AF47: 江苏南通 | AG47: 李向阳 15896274137 | AH47: 7800 | AJ47: ==AH47*(1-AI47) -> 7800 | AK47: ==AH47*I47 -> 7800
A48: 3 | B48: 电动调节蝶阀 | D48: DN700 , PN10 ,预处理池出水管 | E48: 个 | F48: 4 | G48: 87200 | H48: ==G48*F48 -> 348800 | I48: 4 | J48: ==W48 -> 0.35 | K48: ==S48 -> 63811.15 | L48: ==K48*I48 -> 255244.6 | O48: 53846（DN600） | Q48: 97886 （DN900） | R48: ==AVERAGE(X48,AD48,AJ48,AP48) -> 85832.717 | S48: ==MIN(X48,AD48,AJ48,AP48) -> 63811.15 | T48: 冠龙 | U48: 黄经理13925121566 | V48: 98171 | W48: 0.35 | X48: ==V48*(1-W48) -> 63811.15 | Y48: ==X48*I48 -> 255244.6 | Z48: 德国VAG | AA48: 吴居并13922353009 | AB48: 109913 | AD48: ==AB48*(1-AC48) -> 109913 | AE48: ==AB48*I48 -> 439652 | AF48: 丹麦AVK | AG48: 蔡文亮13570037656 | AH48: 83774 | AJ48: ==AH48*(1-AI48) -> 83774 | AK48: ==AH48*I48 -> 335096
A49: 五 | B49: 预处理区的其它设备
A50: 1 | B50: 可调式出水堰板 | D50: LxW=3250mmx350mm δ=5mm SS304 | E50: 块 | F50: 2 | G50: ==1404.62*3.25*0.35 -> 1597.7552 | H50: ==F50*G50 -> 3195.5105 | I50: 2 | J50: ==AC50 -> 0.2 | K50: ==S50 -> 960 | L50: ==K50*I50 -> 1920 | Q50: 1500 | R50: ==AVERAGE(X50,AD50,AJ50,AP50) -> 5112 | S50: ==MIN(X50,AD50,AJ50,AP50) -> 960 | T50: 新环环保 | U50: 连皓文13500036502 | V50: 15000 | W50: 0.2 | X50: ==V50*(1-W50) -> 12000 | Y50: ==X50*I50 -> 24000 | Z50: 无锡通用 | AA50: 杨培根18961775586 | AB50: 1200 | AC50: 0.2 | AD50: ==AB50*(1-AC50) -> 960 | AE50: ==AB50*I50 -> 2400 | AF50: 江苏南通 | AG50: 李向阳 15896274137 | AH50: 2376 | AJ50: ==AH50*(1-AI50) -> 2376 | AK50: ==AH50*I50 -> 4752
A51: 2 | B51: 可调式出水堰板 | D51: LxW=2900mmx350mm δ=5mm SS304 | E51: 块 | F51: 4 | G51: ==1404.62*2.9*0.35 -> 1425.6893 | H51: ==F51*G51 -> 5702.7572 | I51: 4 | J51: ==AC51 -> 0.2 | K51: ==S51 -> 880 | L51: ==K51*I51 -> 3520 | Q51: 1500 | R51: ==AVERAGE(X51,AD51,AJ51,AP51) -> 4201.3333 | S51: ==MIN(X51,AD51,AJ51,AP51) -> 880 | T51: 新环环保 | U51: 连皓文13500036502 | V51: 12000 | W51: 0.2 | X51: ==V51*(1-W51) -> 9600 | Y51: ==X51*I51 -> 38400 | Z51: 无锡通用 | AA51: 杨培根18961775586 | AB51: 1100 | AC51: 0.2 | AD51: ==AB51*(1-AC51) -> 880 | AE51: ==AB51*I51 -> 4400 | AF51: 江苏南通 | AG51: 李向阳 15896274137 | AH51: 2124 | AJ51: ==AH51*(1-AI51) -> 2124 | AK51: ==AH51*I51 -> 8496
A52: 六 | B52: AAOA生化池 | AE52: ==AB52*F52 -> 0
A53: 1 | B53: 盘式微孔曝气器 | D53: 膜片直径 300mm , EPDM 材质,通气量≥ 4m3/(h ·只 ) ,氧利用率≥ 20% | E53: 个 | F53: 2592 | G53: ==941000/2592 -> 363.04012 | H53: ==G53*F53 -> 941000 | I53: 2592 | J53: ==AI53 -> 0 | K53: ==S53+45 -> 150 | L53: ==K53*I53 -> 388800 | O53: 150 | Q53: 240 | R53: ==AVERAGE(X53,AD53,AJ53,AP53) -> 146.5 | S53: ==MIN(X53,AD53,AJ53,AP53) -> 105 | T53: 耶格尔 | U53: 彭宏一15223193129 | V53: 188 | X53: ==V53*(1-W53) -> 188 | Y53: ==X53*I53 -> 487296 | Z53: 帕萨旺 | AA53: 蒋13916712400 | AB53: 未报价 | AE53: 未报价 | AF53: 诺庞 | AG53: 芮安邦13584228855 | AH53: 105 | AJ53: ==AH53*(1-AI53) -> 105 | AK53: ==AH53*I53 -> 272160
A54: 2 | B54: 内回流泵(缺氧 ~ 厌氧) | D54: 不锈钢穿墙泵, Q=3125m3/h , H=1.2m , N=18kW ,带变频控制、起吊装置 | E54: 台 | F54: 4 | G54: 200000 | H54: ==G54*F54 -> 800000 | I54: 4 | J54: ==W54 -> 0 | K54: ==S54 -> 270000 | L54: ==K54*I54 -> 1080000 | M54: ==K54*0.9 -> 243000 | N54: ==M54*I54-I54*K54 -> -108000 | O54: 224640 （Q=3906m3/h） | Q54: 85000（Q=2090m3/h） | R54: ==AVERAGE(X54,AD54,AJ54,AP54) -> 349563.33 | S54: ==MIN(X54,AD54,AJ54,AP54) -> 270000 | T54: 德国KSB | U54: 李晖13829709122 | V54: 270000 | X54: ==V54*(1-W54) -> 270000 | Y54: ==X54*I54 -> 1080000 | Z54: 苏尔寿ABS | AA54: 曹昀13503012388 | AB54: 328690 | AD54: ==AB54*(1-AC54) -> 328690 | AE54: ==AB54*I54 -> 1314760 | AF54: 海斯特 | AG54: 王兰军18666867936 | AH54: 450000 | AJ54: ==AH54*(1-AI54) -> 450000 | AK54: ==AH54*I54 -> 1800000
A55: 3 | B55: 内回流泵(好氧 ~ 缺氧) | D55: 不锈钢穿墙泵, Q=2344m3/h , H=1.2m , N=18kW ,带变频控制、起吊装置 | E55: 台 | F55: 6 | G55: 180000 | H55: ==G55*F55 -> 1080000 | I55: 6 | J55: ==W55 -> 0 | K55: ==S55 -> 210000 | L55: ==K55*I55 -> 1260000 | M55: ==K55*0.9 -> 189000 | N55: ==M55*I55-I55*K55 -> -126000 | O55: 138000 | Q55: 85000（Q=2090m3/h） | R55: ==AVERAGE(X55,AD55,AJ55,AP55) -> 288793.33 | S55: ==MIN(X55,AD55,AJ55,AP55) -> 210000 | T55: 德国KSB | U55: 李晖13829709122 | V55: 210000 | X55: ==V55*(1-W55) -> 210000 | Y55: ==X55*I55 -> 1260000 | Z55: 苏尔寿ABS | AA55: 曹昀13503012388 | AB55: 296380 | AD55: ==AB55*(1-AC55) -> 296380 | AE55: ==AB55*I55 -> 1778280 | AF55: 海斯特 | AG55: 王兰军18666867936 | AH55: 360000 | AJ55: ==AH55*(1-AI55) -> 360000 | AK55: ==AH55*I55 -> 2160000
A56: 4 | B56: 进水闸门(厌氧) | D56: 不锈钢附壁方闸门, B × H=1200 × 700mm , N=1.5kW ,带手电一体启闭机 | E56: 套 | F56: 2 | G56: 91100 | H56: ==G56*F56 -> 182200 | I56: 2 | J56: ==AC56 -> 0 | K56: ==S56 -> 38500 | L56: ==K56*I56 -> 77000 | O56: 42000 （800X1000） | Q56: 52800（B*H=900*2000m） | R56: ==AVERAGE(X56,AD56,AJ56,AP56) -> 52900 | S56: ==MIN(X56,AD56,AJ56,AP56) -> 38500 | T56: 新环环保 | U56: 连皓文13500036502 | V56: 82000 | W56: 0.2 | X56: ==V56*(1-W56) -> 65600 | Y56: ==X56*I56 -> 131200 | Z56: 无锡通用 | AA56: 杨培根18961775586 | AB56: 38500 | AD56: ==AB56*(1-AC56) -> 38500 | AE56: ==AB56*I56 -> 77000 | AF56: 江苏南通 | AG56: 李向阳 15896274137 | AH56: 54600 | AJ56: ==AH56*(1-AI56) -> 54600 | AK56: ==AH56*I56 -> 109200
A57: 5 | B57: 回流闸门(好氧 ~ 缺氧) | D57: 不锈钢附壁方闸门, B × H=1600 × 700mm , N=1.5kW ,带手电一体启闭机 | E57: 套 | F57: 2 | G57: 95800 | H57: ==G57*F57 -> 191600 | I57: 2 | J57: ==AC57 -> 0 | K57: ==S57 -> 42500 | L57: ==K57*I57 -> 85000 | O57: 57000 （1800X1000） | Q57: 52800（B*H=900*2000m） | R57: ==AVERAGE(X57,AD57,AJ57,AP57) -> 57553.333 | S57: ==MIN(X57,AD57,AJ57,AP57) -> 42500 | T57: 新环环保 | U57: 连皓文13500036502 | V57: 88000 | W57: 0.2 | X57: ==V57*(1-W57) -> 70400 | Y57: ==X57*I57 -> 140800 | Z57: 无锡通用 | AA57: 杨培根18961775586 | AB57: 42500 | AD57: ==AB57*(1-AC57) -> 42500 | AE57: ==AB57*I57 -> 85000 | AF57: 江苏南通 | AG57: 李向阳 15896274137 | AH57: 59760 | AJ57: ==AH57*(1-AI57) -> 59760 | AK57: ==AH57*I57 -> 119520
A58: 6 | B58: 进水闸门(缺氧) | D58: 不锈钢附壁方闸门, B × H=1200 × 700mm , N=1.5kW ,带手电一体启闭机 | E58: 套 | F58: 2 | G58: 84100 | H58: ==G58*F58 -> 168200 | I58: 2 | J58: ==AC58 -> 0 | K58: ==S58 -> 38500 | L58: ==K58*I58 -> 77000 | O58: 42000 （800X1000） | Q58: 52800（B*H=900*2000m） | R58: ==AVERAGE(X58,AD58,AJ58,AP58) -> 52900 | S58: ==MIN(X58,AD58,AJ58,AP58) -> 38500 | T58: 新环环保 | U58: 连皓文13500036502 | V58: 82000 | W58: 0.2 | X58: ==V58*(1-W58) -> 65600 | Y58: ==X58*I58 -> 131200 | Z58: 无锡通用 | AA58: 杨培根18961775586 | AB58: 38500 | AD58: ==AB58*(1-AC58) -> 38500 | AE58: ==AB58*I58 -> 77000 | AF58: 江苏南通 | AG58: 李向阳 15896274137 | AH58: 54600 | AJ58: ==AH58*(1-AI58) -> 54600 | AK58: ==AH58*I58 -> 109200
A59: 7 | B59: 回流闸门(膜池 ~ 好氧) | D59: 不锈钢附壁方闸门, B × H=2200 × 700mm , N=1.5kW ,带手电一体启闭机 | E59: 套 | F59: 2 | G59: 95600 | H59: ==G59*F59 -> 191200 | I59: 2 | J59: ==AC59 -> 0 | K59: ==S59 -> 52500 | L59: ==K59*I59 -> 105000 | O59: 61200（B×H=0.80×2.60m，渠深3.3m，N=1.5kW） | Q59: 52800（B*H=900*2000m） | R59: ==AVERAGE(X59,AD59,AJ59,AP59) -> 65633.333 | S59: ==MIN(X59,AD59,AJ59,AP59) -> 52500 | T59: 新环环保 | U59: 连皓文13500036502 | V59: 95000 | W59: 0.2 | X59: ==V59*(1-W59) -> 76000 | Y59: ==X59*I59 -> 152000 | Z59: 无锡通用 | AA59: 杨培根18961775586 | AB59: 52500 | AD59: ==AB59*(1-AC59) -> 52500 | AE59: ==AB59*I59 -> 105000 | AF59: 江苏南通 | AG59: 李向阳 15896274137 | AH59: 68400 | AJ59: ==AH59*(1-AI59) -> 68400 | AK59: ==AH59*I59 -> 136800
A60: 8 | B60: 巴氏计量槽 | D60: 膜池回流渠,喉道宽度 1200mm ,量程 0.035~2m3/s ,不锈钢材质,含明渠流量计 | E60: 套 | F60: 2 | G60: 39300 | H60: ==G60*F60 -> 78600 | I60: 2 | J60: ==W60 -> 0.2 | K60: ==S60 -> 20000 | L60: ==K60*I60 -> 40000 | Q60: 34000 | R60: ==AVERAGE(X60,AD60,AJ60,AP60) -> 28933.333 | S60: ==MIN(X60,AD60,AJ60,AP60) -> 20000 | T60: 新环环保 | U60: 连皓文13500036502 | V60: 25000 | W60: 0.2 | X60: ==V60*(1-W60) -> 20000 | Y60: ==X60*I60 -> 40000 | Z60: 无锡通用 | AA60: 杨培根18961775586 | AB60: 33200 | AD60: ==AB60*(1-AC60) -> 33200 | AE60: ==AB60*I60 -> 66400 | AF60: 江苏南通 | AG60: 李向阳 15896274137 | AH60: 33600 | AJ60: ==AH60*(1-AI60) -> 33600 | AK60: ==AH60*I60 -> 67200
A61: 9 | B61: 巴氏计量槽 | D61: 好氧回流渠,喉道宽度 1000mm ,量程 0.03~1.5m3/s ,不锈钢材质,含明渠流量计 | E61: 套 | F61: 2 | G61: 30800 | H61: ==G61*F61 -> 61600 | I61: 2 | J61: ==W61 -> 0.2 | K61: ==S61 -> 16800 | L61: ==K61*I61 -> 33600 | O61: 30000 | Q61: 34000 （1200mm） | R61: ==AVERAGE(X61,AD61,AJ61,AP61) -> 23900 | S61: ==MIN(X61,AD61,AJ61,AP61) -> 16800 | T61: 新环环保 | U61: 连皓文13500036502 | V61: 21000 | W61: 0.2 | X61: ==V61*(1-W61) -> 16800 | Y61: ==X61*I61 -> 33600 | Z61: 无锡通用 | AA61: 杨培根18961775586 | AB61: 31500 | AD61: ==AB61*(1-AC61) -> 31500 | AE61: ==AB61*I61 -> 63000 | AF61: 江苏南通 | AG61: 李向阳 15896274137 | AH61: 23400 | AJ61: ==AH61*(1-AI61) -> 23400 | AK61: ==AH61*I61 -> 46800
A62: 10 | B62: 絮凝搅拌器 | D62: 不锈钢立式搅拌器, D=2m , N=5.5kW ,转速 48rpm | E62: 套 | F62: 3 | G62: 54900 | H62: ==G62*F62 -> 164700 | I62: 2 | J62: ==W62 -> 0 | K62: ==S62 -> 106500 | L62: ==K62*I62 -> 213000 | M62: ==K62*0.9 -> 95850 | N62: ==M62*I62-I62*K62 -> -21300 | O62: 55000（D=580mm;转速475rpm；N=7.6kw） | Q62: 111550（N=3.5kW D=2100mm 44rpm） | R62: ==AVERAGE(X62,AD62,AJ62,AP62) -> 114718 | S62: ==MIN(X62,AD62,AJ62,AP62) -> 106500 | T62: 普罗名特 | U62: 吴健良13450431558 | V62: 106500 | W62: 0 | X62: ==V62*(1-W62) -> 106500 | Y62: ==X62*I62 -> 213000 | Z62: 米顿罗 | AA62: 任行卓13052536000 | AB62: 120000 | AD62: ==AB62*(1-AC62) -> 120000 | AE62: ==AB62*I62 -> 240000 | AF62: 格兰富-ALLDOS | AG62: 宋思亮13802905937 | AH62: 117654 | AI62: 0 | AJ62: ==AH62*(1-AI62) -> 117654 | AK62: ==AH62*I62 -> 235308
A63: 11 | B63: 絮凝搅拌器 | D63: 不锈钢立式搅拌器, D=2m , N=4kW ,转速 28rpm | E63: 套 | F63: 3 | G63: 0 | H63: ==G63*F63 -> 0 | I63: 2 | J63: ==W63 -> 0 | K63: ==S63 -> 98800 | L63: ==K63*I63 -> 197600 | M63: ==K63*0.9 -> 88920 | N63: ==M63*I63-I63*K63 -> -19760 | O63: 55000（D=580mm;转速475rpm；N=7.6kw） | Q63: 111550（N=3.5kW D=2100mm 44rpm） | R63: ==AVERAGE(X63,AD63,AJ63,AP63) -> 105982.67 | S63: ==MIN(X63,AD63,AJ63,AP63) -> 98800 | T63: 普罗名特 | U63: 吴健良13450431558 | V63: 98800 | W63: 0 | X63: ==V63*(1-W63) -> 98800 | Y63: ==X63*I63 -> 197600 | Z63: 米顿罗 | AA63: 任行卓13052536000 | AB63: 110000 | AD63: ==AB63*(1-AC63) -> 110000 | AE63: ==AB63*I63 -> 220000 | AF63: 格兰富-ALLDOS | AG63: 宋思亮13802905937 | AH63: 109148 | AI63: 0 | AJ63: ==AH63*(1-AI63) -> 109148 | AK63: ==AH63*I63 -> 218296
A64: 12 | B64: 出水闸门 | D64: 不锈钢附壁方闸门, B × H=2000 × 2000mm , N=1.5kW ,带手电一体启闭机,下开式 | E64: 套 | F64: 2 | G64: 132500 | H64: ==G64*F64 -> 265000 | I64: 2 | J64: ==AC64 -> 0 | K64: ==S64 -> 79500 | L64: ==K64*I64 -> 159000 | M64: ==K64*0.9 -> 71550 | N64: ==M64*I64-I64*K64 -> -15900 | O64: 60000（BXH=2.2mX2.0m,P=2.2kW） | Q64: 52800（B*H=900*2000m） | R64: ==AVERAGE(X64,AD64,AJ64,AP64) -> 106366.67 | S64: ==MIN(X64,AD64,AJ64,AP64) -> 79500 | T64: 新环环保 | U64: 连皓文13500036502 | V64: 130000 | W64: 0.2 | X64: ==V64*(1-W64) -> 104000 | Y64: ==X64*I64 -> 208000 | Z64: 无锡通用 | AA64: 杨培根18961775586 | AB64: 79500 | AD64: ==AB64*(1-AC64) -> 79500 | AE64: ==AB64*I64 -> 159000 | AF64: 江苏南通 | AG64: 李向阳 15896274137 | AH64: 135600 | AJ64: ==AH64*(1-AI64) -> 135600 | AK64: ==AH64*I64 -> 271200
A65: 13 | B65: 膜池回流泵 | D65: 不锈钢穿墙泵, Q=2604m3/h , H=1.2m , N=15kW ,带变频控制、起吊装置 | E65: 套 | F65: 6 | G65: 180000 | H65: ==G65*F65 -> 1080000 | I65: 6 | J65: ==W65 -> 0.3 | K65: ==S65 -> 154000 | L65: ==K65*I65 -> 924000 | O65: 138000 （Q=2344m3/h | Q65: 248800（Q=3480m3/h） | R65: ==AVERAGE(X65,AD65,AJ65,AP65) -> 276173.33 | S65: ==MIN(X65,AD65,AJ65,AP65) -> 154000 | T65: 德国KSB | U65: 李晖13829709122 | V65: 220000 | W65: 0.3 | X65: ==V65*(1-W65) -> 154000 | Y65: ==X65*I65 -> 924000 | Z65: 苏尔寿ABS | AA65: 曹昀13503012388 | AB65: 305920 | AD65: ==AB65*(1-AC65) -> 305920 | AE65: ==AB65*I65 -> 1835520 | AF65: 海斯特 | AG65: 王兰军18666867936 | AH65: 380000 | AI65: 0.03 | AJ65: ==AH65*(1-AI65) -> 368600 | AK65: ==AH65*I65 -> 2280000
A66: 14 | B66: 手动对夹蝶阀 | D66: DN200，PN10，SS304 | E66: 个 | F66: 24 | I66: 24 | J66: ==AI66 -> 0 | K66: ==S66 -> 1458 | L66: ==K66*I66 -> 34992 | O66: 9773（电动） | Q66: 6500 | R66: ==AVERAGE(X66,AD66,AJ66,AP66) -> 7050.5833 | S66: ==MIN(X66,AD66,AJ66,AP66) -> 1458 | T66: 冠龙 | U66: 黄经理13925121566 | V66: 12815 | W66: 0.35 | X66: ==V66*(1-W66) -> 8329.75 | Y66: ==X66*I66 -> 199914 | Z66: 德国VAG | AA66: 吴居并13922353009 | AB66: 11364 | AD66: ==AB66*(1-AC66) -> 11364 | AE66: ==AB66*I66 -> 272736 | AF66: 丹麦AVK | AG66: 蔡文亮13570037656 | AH66: 1458 | AJ66: ==AH66*(1-AI66) -> 1458 | AK66: ==AH66*I66 -> 34992
A67: 七 | B67: MBR膜池
A68: 1 | B68: 电动葫芦 | D68: 起重量5T，起吊高度12m，行程约340m，N=0.8×2+7.5kW | E68: 台 | F68: 1 | I68: 2 | J68: ==W68 -> 0 | K68: ==S68 -> 436000 | L68: ==K68*I68 -> 872000 | M68: ==K68*0.9 -> 392400 | N68: ==M68*I68-I68*K68 -> -87200 | S68: ==MIN(X68,AD68,AJ68,AP68) -> 436000 | T68: 碧水源 | U68: 车学理13380060528 | V68: 436000 | X68: ==V68*(1-W68) -> 436000
A69: 2 | B69: 电动单梁起重机 | D69: 起重量2T，起吊高度10m，跨度5.4m，行程31m，N=3.4kW（含检修平台，领证，在原报价基础上+5500/台） | E69: 台 | F69: 2 | I69: 2 | K69: 90000 | L69: ==K69*I69 -> 180000 | O69: 90000（T=3t,LK=6.0m,H=24m,N=（4.5+0.4×2）+0.8×2kW） | R69: ==AVERAGE(X69,AD69,AJ69,AP69) -> 0 | S69: ==MIN(X69,AD69,AJ69,AP69) -> 0 | T69: 碧水源 | U69: 车学理13380060528 | AD69: ==AB69*(1-AC69) -> 0
A70: 七 | B70: 出水及消毒区
A71: 1 | B71: 紫外线消毒系统 | D71: 管道式,处理能力 2.5 万 m3/d ,变化系数 1.5 , N=21kW | E71: 台 | F71: 2 | G71: 2400000 | H71: ==G71*F71 -> 4800000 | I71: 2 | J71: ==W71 -> 0 | K71: ==S71 -> 845000 | L71: ==K71*I71 -> 1690000 | M71: ==1000000 -> 1000000 | N71: ==M71*I71-I71*K71 -> 310000 | O71: 1900000（5万m/d） | Q71: 754000（发票金额2570000） | R71: ==AVERAGE(X71,AD71,AJ71,AP71) -> 2581666.7 | S71: ==MIN(X71,AD71,AJ71,AP71) -> 845000 | T71: 安力斯 | U71: 叶林蓬13928833012 | V71: 845000 | X71: ==V71*(1-W71) -> 845000 | Y71: ==X71*I71 -> 1690000 | Z71: 特洁安 | AA71: 麦均生13923216789 | AB71: 4500000 | AD71: ==AB71*(1-AC71) -> 4500000 | AE71: ==AB71*I71 -> 9000000 | AF71: 威德高 | AG71: 陈工18218182708 | AH71: 2400000 | AJ71: ==AH71*(1-AI71) -> 2400000 | AK71: ==AH71*I71 -> 4800000
A72: 2 | B72: 手电两用蝶阀 | D72: DN1200 1.0MPA 阀板:铸铁 | E72: 套 | F72: 1 | G72: 208500 | H72: ==G72*F72 -> 208500 | I72: 1 | J72: ==W72 -> 0.35 | K72: ==S72 -> 122495.1 | L72: ==K72*I72 -> 122495.1 | O72: 93812(电动) | R72: ==AVERAGE(X72,AD72,AJ72,AP72) -> 149728.37 | S72: ==MIN(X72,AD72,AJ72,AP72) -> 122495.1 | T72: 冠龙 | U72: 黄经理13925121566 | V72: 188454 | W72: 0.35 | X72: ==V72*(1-W72) -> 122495.1 | Y72: ==X72*I72 -> 122495.1 | Z72: 德国VAG | AA72: 吴居并13922353009 | AB72: 186236 | AD72: ==AB72*(1-AC72) -> 186236 | AE72: ==AB72*I72 -> 186236 | AF72: 丹麦AVK | AG72: 蔡文亮13570037656 | AH72: 140454 | AJ72: ==AH72*(1-AI72) -> 140454 | AK72: ==AH72*I72 -> 140454
A73: 3 | B73: 巴氏计量槽 | D73: 地面出水渠,喉道宽度 1200mm ,不锈钢材质,含明渠流量计 | E73: 套 | F73: 1 | G73: 31400 | H73: ==G73*F73 -> 31400 | I73: 1 | J73: ==W73 -> 0.2 | K73: ==S73 -> 20000 | L73: ==K73*I73 -> 20000 | O73: 30000（喉道处B=1000mm SS304 壁厚4mm） | R73: ==AVERAGE(X73,AD73,AJ73,AP73) -> 28933.333 | S73: ==MIN(X73,AD73,AJ73,AP73) -> 20000 | T73: 新环环保 | U73: 连皓文13500036502 | V73: 25000 | W73: 0.2 | X73: ==V73*(1-W73) -> 20000 | Y73: ==X73*I73 -> 20000 | Z73: 无锡通用 | AA73: 杨培根18961775586 | AB73: 33200 | AD73: ==AB73*(1-AC73) -> 33200 | AE73: ==AB73*I73 -> 33200 | AF73: 江苏南通 | AG73: 李向阳 15896274137 | AH73: 33600 | AJ73: ==AH73*(1-AI73) -> 33600 | AK73: ==AH73*I73 -> 33600
A74: 4 | B74: 中水取水闸门 | D74: 不锈钢附壁圆闸门 φ D400 , N=1.5kW ,带手电一体启闭机 | E74: 套 | F74: 1 | G74: 86000 | H74: ==G74*F74 -> 86000 | I74: 1 | J74: ==W74 -> 0.2 | K74: ==S74 -> 29500 | L74: ==K74*I74 -> 29500 | O74: 37536（DN800） | R74: ==AVERAGE(X74,AD74,AJ74,AP74) -> 39366.667 | S74: ==MIN(X74,AD74,AJ74,AP74) -> 29500 | T74: 新环环保 | U74: 连皓文13500036502 | V74: 53000 | W74: 0.2 | X74: ==V74*(1-W74) -> 42400 | Y74: ==X74*I74 -> 42400 | Z74: 无锡通用 | AA74: 杨培根18961775586 | AB74: 29500 | AD74: ==AB74*(1-AC74) -> 29500 | AE74: ==AB74*I74 -> 29500 | AF74: 江苏南通 | AG74: 李向阳 15896274137 | AH74: 46200 | AJ74: ==AH74*(1-AI74) -> 46200 | AK74: ==AH74*I74 -> 46200
A75: 5 | B75: 恒压供水系统 | D75: 立式多级泵组( 3 个泵), 160m3/h , H=50m ,单泵功率N=15kW ,带稳压罐系统、变频控制、导轨及自耦系统及排气阀 | E75: 套 | F75: 3 | G75: 284000 | H75: ==G75*F75 -> 852000 | I75: 1 | J75: ==AI75 -> 0.03 | K75: ==S75 -> 363750 | L75: ==K75*I75 -> 363750 | R75: ==AVERAGE(AD75,AJ75,AP75) -> 363750 | S75: ==MIN(AD75,AJ75,AP75) -> 363750 | T75: 德国KSB | U75: 李晖13829709122 | V75: 未报价 | W75: 0.3 | Y75: 未报价 | Z75: 苏尔寿ABS | AA75: 曹昀13503012388 | AB75: 未报价 | AE75: 未报价 | AF75: 海斯特 | AG75: 王兰军18666867936 | AH75: 375000 | AI75: 0.03 | AJ75: ==AH75*(1-AI75) -> 363750 | AK75: ==AH75*I75 -> 375000
A76: 6 | B76: 手电两用蝶阀 | D76: DN300 1.0MPA 阀板:铸铁 | E76: 套 | F76: 1 | G76: 81500 | H76: ==G76*F76 -> 81500 | I76: 1 | J76: ==AI76 -> 0 | K76: ==S76 -> 29093 | L76: ==K76*I76 -> 29093 | R76: ==AVERAGE(X76,AD76,AJ76,AP76) -> 51155.717 | S76: ==MIN(X76,AD76,AJ76,AP76) -> 29093 | T76: 冠龙 | U76: 黄经理13925121566 | V76: 68691 | W76: 0.35 | X76: ==V76*(1-W76) -> 44649.15 | Y76: ==X76*I76 -> 44649.15 | Z76: 德国VAG | AA76: 吴居并13922353009 | AB76: 79725 | AD76: ==AB76*(1-AC76) -> 79725 | AE76: ==AB76*I76 -> 79725 | AF76: 丹麦AVK | AG76: 蔡文亮13570037656 | AH76: 29093 | AJ76: ==AH76*(1-AI76) -> 29093 | AK76: ==AH76*I76 -> 29093
A77: 7 | B77: 双法手动蝶阀 | D77: DN900 PN10 | E77: 个 | F77: 1 | I77: 1 | J77: ==W77 -> 0.35 | K77: ==S77 -> 32760 | L77: ==K77*I77 -> 32760 | R77: ==AVERAGE(X77,AD77,AJ77,AP77) -> 49301.333 | S77: ==MIN(X77,AD77,AJ77,AP77) -> 32760 | T77: 冠龙 | U77: 黄经理13925121566 | V77: 50400 | W77: 0.35 | X77: ==V77*(1-W77) -> 32760 | Y77: ==X77*I77 -> 32760 | Z77: 德国VAG | AA77: 吴居并13922353009 | AB77: 66918 | AD77: ==AB77*(1-AC77) -> 66918 | AE77: ==AB77*I77 -> 66918 | AF77: 丹麦AVK | AG77: 蔡文亮13570037656 | AH77: 48226 | AJ77: ==AH77*(1-AI77) -> 48226 | AK77: ==AH77*I77 -> 48226
A78: 8 | B78: 双法手动蝶阀 | D78: DN500 PN10 | E78: 个 | F78: 8 | I78: 8 | J78: ==W78 -> 0.35 | K78: ==S78 -> 11602.5 | L78: ==K78*I78 -> 92820 | R78: ==AVERAGE(X78,AD78,AJ78,AP78) -> 18287.167 | S78: ==MIN(X78,AD78,AJ78,AP78) -> 11602.5 | T78: 冠龙 | U78: 黄经理13925121566 | V78: 17850 | W78: 0.35 | X78: ==V78*(1-W78) -> 11602.5 | Y78: ==X78*I78 -> 92820 | Z78: 德国VAG | AA78: 吴居并13922353009 | AB78: 30893 | AD78: ==AB78*(1-AC78) -> 30893 | AE78: ==AB78*I78 -> 247144 | AF78: 丹麦AVK | AG78: 蔡文亮13570037656 | AH78: 12366 | AJ78: ==AH78*(1-AI78) -> 12366 | AK78: ==AH78*I78 -> 98928
A79: 9 | B79: 双法橡胶接头 | D79: DN1400 PN10 Q235B | E79: 个 | F79: 1 | I79: 1 | J79: ==AI79 -> 0 | K79: ==S79 -> 17482 | L79: ==K79*I79 -> 17482 | O79: 36337 | R79: ==AVERAGE(X79,AD79,AJ79,AP79) -> 38090.95 | S79: ==MIN(X79,AD79,AJ79,AP79) -> 17482 | T79: 冠龙 | U79: 黄经理13925121566 | V79: 55449 | W79: 0.35 | X79: ==V79*(1-W79) -> 36041.85 | Y79: ==X79*I79 -> 36041.85 | Z79: 德国VAG | AA79: 吴居并13922353009 | AB79: 60749 | AD79: ==AB79*(1-AC79) -> 60749 | AE79: ==AB79*I79 -> 60749 | AF79: 丹麦AVK | AG79: 蔡文亮13570037656 | AH79: 17482 | AJ79: ==AH79*(1-AI79) -> 17482 | AK79: ==AH79*I79 -> 17482
A80: 10 | B80: 双法手动闸阀 | D80: DN100 PN0 Q235B | E80: 个 | F80: 1 | I80: 1 | J80: ==AI80 -> 0 | K80: ==S80 -> 1021 | L80: ==K80*I80 -> 1021 | Q80: 2295 （DN200） | R80: ==AVERAGE(X80,AD80,AJ80,AP80) -> 1442.6333 | S80: ==MIN(X80,AD80,AJ80,AP80) -> 1021 | T80: 冠龙 | U80: 黄经理13925121566 | V80: 1666 | W80: 0.35 | X80: ==V80*(1-W80) -> 1082.9 | Y80: ==X80*I80 -> 1082.9 | Z80: 德国VAG | AA80: 吴居并13922353009 | AB80: 2224 | AD80: ==AB80*(1-AC80) -> 2224 | AE80: ==AB80*I80 -> 2224 | AF80: 丹麦AVK | AG80: 蔡文亮13570037656 | AH80: 1021 | AJ80: ==AH80*(1-AI80) -> 1021 | AK80: ==AH80*I80 -> 1021
A81: 11 | B81: 双法手动闸阀 | D81: DN80 PN10 | E81: 个 | F81: 6 | I81: 6 | J81: ==AI81 -> 0 | K81: ==S81 -> 884 | L81: ==K81*I81 -> 5304 | R81: ==AVERAGE(X81,AD81,AJ81,AP81) -> 1234.6333 | S81: ==MIN(X81,AD81,AJ81,AP81) -> 884 | T81: 冠龙 | U81: 黄经理13925121566 | V81: 1386 | W81: 0.35 | X81: ==V81*(1-W81) -> 900.9 | Y81: ==X81*I81 -> 5405.4 | Z81: 德国VAG | AA81: 吴居并13922353009 | AB81: 1919 | AD81: ==AB81*(1-AC81) -> 1919 | AE81: ==AB81*I81 -> 11514 | AF81: 丹麦AVK | AG81: 蔡文亮13570037656 | AH81: 884 | AJ81: ==AH81*(1-AI81) -> 884 | AK81: ==AH81*I81 -> 5304
A82: 12 | B82: 双法止回阀 | D82: DN80 PN10 | E82: 个 | F82: 3 | I82: 3 | J82: ==W82 -> 0.35 | K82: ==S82 -> 1146.6 | L82: ==K82*I82 -> 3439.8 | R82: ==AVERAGE(X82,AD82,AJ82,AP82) -> 2030.5333 | S82: ==MIN(X82,AD82,AJ82,AP82) -> 1146.6 | T82: 冠龙 | U82: 黄经理13925121566 | V82: 1764 | W82: 0.35 | X82: ==V82*(1-W82) -> 1146.6 | Y82: ==X82*I82 -> 3439.8 | Z82: 德国VAG | AA82: 吴居并13922353009 | AB82: 3512 | AD82: ==AB82*(1-AC82) -> 3512 | AE82: ==AB82*I82 -> 10536 | AF82: 丹麦AVK | AG82: 蔡文亮13570037656 | AH82: 1433 | AJ82: ==AH82*(1-AI82) -> 1433 | AK82: ==AH82*I82 -> 4299
A83: 13 | B83: 排气阀 | D83: DN15 | E83: 个 | F83: 2 | G83: 67.64 | I83: 2 | K83: ==40.8 -> 40.8 | L83: ==K83*I83 -> 81.6 | R83: ==AVERAGE(X83,AD83,AJ83,AP83) -> 837.225 | S83: ==MIN(X83,AD83,AJ83,AP83) -> 450.45 | T83: 冠龙 | U83: 黄经理13925121566 | V83: 693 | W83: 0.35 | X83: ==V83*(1-W83) -> 450.45 | Y83: ==X83*I83 -> 900.9 | Z83: 德国VAG | AA83: 吴居并13922353009 | AB83: 1224 | AD83: ==AB83*(1-AC83) -> 1224 | AE83: ==AB83*I83 -> 2448 | AF83: 丹麦AVK | AG83: 蔡文亮13570037656 | AH83: 不生产 | AK83: 不生产
A84: 八 | B84: 浓缩池
A85: 1 | B85: 污泥浓缩机 | D85: 中心传动悬挂式,Φ 12.0m , N=0.75kW ,水下部件不锈钢材质 | E85: 台 | F85: 2 | G85: 232600 | H85: ==G85*F85 -> 465200 | I85: 2 | J85: ==W85 -> 0.2 | K85: ==S85 -> 144000 | L85: ==K85*I85 -> 288000 | O85: 130000 | R85: ==AVERAGE(X85,AD85,AJ85,AP85) -> 173533.33 | S85: ==MIN(X85,AD85,AJ85,AP85) -> 144000 | T85: 广东新环 | U85: 连皓文13500036502 | V85: 180000 | W85: 0.2 | X85: ==V85*(1-W85) -> 144000 | Y85: ==X85*I85 -> 288000 | Z85: 无锡通用 | AA85: 杨培根18961775586 | AB85: 175000 | AD85: ==AB85*(1-AC85) -> 175000 | AE85: ==AB85*I85 -> 350000 | AF85: 江苏南通 | AG85: 李向阳 15896274137 | AH85: 201600 | AJ85: ==AH85*(1-AI85) -> 201600 | AK85: ==AH85*I85 -> 403200
A86: 2 | B86: 排泥泵 | D86: 单螺杆泵, Q=65m 3 /h , H=20m , N=7.5kW ,带变频控制 | E86: 台 | F86: 2 | G86: 200000 | H86: ==G86*F86 -> 400000 | I86: 2 | J86: ==AI86 -> 0 | K86: ==S86 -> 49300 | L86: ==K86*I86 -> 98600 | O86: 35800（Q=30m3/h,H=10m,3kw） | R86: ==AVERAGE(X86,AD86,AJ86,AP86) -> 87900 | S86: ==MIN(X86,AD86,AJ86,AP86) -> 49300 | T86: 耐驰 | U86: 葛银祖13902234800 | V86: 126500 | X86: ==V86*(1-W86) -> 126500 | Y86: ==X86*I86 -> 253000 | Z86: 西派克 | AA86: 陈浩13681732464 | AB86: 不报价 | AE86: 不报价 | AF86: 尼科 | AG86: 陈生13166269987 | AH86: 49300 | AJ86: ==AH86*(1-AI86) -> 49300 | AK86: ==AH86*I86 -> 98600
A87: 3 | B87: 手动闸阀（法兰式带加长杆） | D87: DN150，PN10，L=1m | E87: 个 | F87: 3 | I87: 3 | J87: ==W87 -> 0.35 | K87: ==S87 -> 2529.8 | L87: ==K87*I87 -> 7589.4 | R87: ==AVERAGE(X87,AD87,AJ87,AP87) -> 4834.9333 | S87: ==MIN(X87,AD87,AJ87,AP87) -> 2529.8 | T87: 冠龙 | U87: 黄经理13925121566 | V87: 3892 | W87: 0.35 | X87: ==V87*(1-W87) -> 2529.8 | Y87: ==X87*I87 -> 7589.4 | Z87: 德国VAG | AA87: 吴居并13922353009 | AB87: 6292 | AD87: ==AB87*(1-AC87) -> 6292 | AE87: ==AB87*I87 -> 18876 | AF87: 丹麦AVK | AG87: 蔡文亮13570037656 | AH87: 5683 | AJ87: ==AH87*(1-AI87) -> 5683 | AK87: ==AH87*I87 -> 17049
A88: 4 | B88: 手动闸阀 | D88: DN150，PN10 | E88: 个 | F88: 5 | I88: 5 | J88: ==W88 -> 0.35 | K88: ==S88 -> 1792.7 | L88: ==K88*I88 -> 8963.5 | R88: ==AVERAGE(X88,AD88,AJ88,AP88) -> 2415.5667 | S88: ==MIN(X88,AD88,AJ88,AP88) -> 1792.7 | T88: 冠龙 | U88: 黄经理13925121566 | V88: 2758 | W88: 0.35 | X88: ==V88*(1-W88) -> 1792.7 | Y88: ==X88*I88 -> 8963.5 | Z88: 德国VAG | AA88: 吴居并13922353009 | AB88: 3412 | AD88: ==AB88*(1-AC88) -> 3412 | AE88: ==AB88*I88 -> 17060 | AF88: 丹麦AVK | AG88: 蔡文亮13570037656 | AH88: 2042 | AJ88: ==AH88*(1-AI88) -> 2042 | AK88: ==AH88*I88 -> 10210
A89: 5 | B89: 手动闸阀 | D89: DN200，PN10 | E89: 个 | F89: 3 | I89: 3 | J89: ==W89 -> 0.35 | K89: ==S89 -> 2784.6 | L89: ==K89*I89 -> 8353.8 | O89: 3200 | R89: ==AVERAGE(X89,AD89,AJ89,AP89) -> 3795.8667 | S89: ==MIN(X89,AD89,AJ89,AP89) -> 2784.6 | T89: 冠龙 | U89: 黄经理13925121566 | V89: 4284 | W89: 0.35 | X89: ==V89*(1-W89) -> 2784.6 | Y89: ==X89*I89 -> 8353.8 | Z89: 德国VAG | AA89: 吴居并13922353009 | AB89: 5591 | AD89: ==AB89*(1-AC89) -> 5591 | AE89: ==AB89*I89 -> 16773 | AF89: 丹麦AVK | AG89: 蔡文亮13570037656 | AH89: 3012 | AJ89: ==AH89*(1-AI89) -> 3012 | AK89: ==AH89*I89 -> 9036
A90: 6 | B90: 止回阀 | D90: DN150，PN10 | E90: 个 | F90: 2 | I90: 2 | J90: ==AI90 -> 0 | K90: ==S90 -> 3047 | L90: ==K90*I90 -> 6094 | Q90: 4485 （DN200） | R90: ==AVERAGE(X90,AD90,AJ90,AP90) -> 3731.6333 | S90: ==MIN(X90,AD90,AJ90,AP90) -> 3047 | T90: 冠龙 | U90: 黄经理13925121566 | V90: 4746 | W90: 0.35 | X90: ==V90*(1-W90) -> 3084.9 | Y90: ==X90*I90 -> 6169.8 | Z90: 德国VAG | AA90: 吴居并13922353009 | AB90: 5063 | AD90: ==AB90*(1-AC90) -> 5063 | AE90: ==AB90*I90 -> 10126 | AF90: 丹麦AVK | AG90: 蔡文亮13570037656 | AH90: 3047 | AJ90: ==AH90*(1-AI90) -> 3047 | AK90: ==AH90*I90 -> 6094
A91: 7 | B91: 止回阀 | D91: DN50，PN10 | E91: 个 | F91: 1 | I91: 1 | J91: ==W91 -> 0.35 | K91: ==S91 -> 800.8 | L91: ==K91*I91 -> 800.8 | Q91: 483（对夹式） | R91: ==AVERAGE(X91,AD91,AJ91,AP91) -> 1767.9333 | S91: ==MIN(X91,AD91,AJ91,AP91) -> 800.8 | T91: 冠龙 | U91: 黄经理13925121566 | V91: 1232 | W91: 0.35 | X91: ==V91*(1-W91) -> 800.8 | Y91: ==X91*I91 -> 800.8 | Z91: 德国VAG | AA91: 吴居并13922353009 | AB91: 3260 | AD91: ==AB91*(1-AC91) -> 3260 | AE91: ==AB91*I91 -> 3260 | AF91: 丹麦AVK | AG91: 蔡文亮13570037656 | AH91: 1243 | AJ91: ==AH91*(1-AI91) -> 1243 | AK91: ==AH91*I91 -> 1243
A92: 8 | B92: 手动闸阀 | D92: DN50，PN10 | E92: 个 | F92: 1 | I92: 1 | J92: ==AI92 -> 0 | K92: ==S92 -> 624 | L92: ==K92*I92 -> 624 | R92: ==AVERAGE(X92,AD92,AJ92,AP92) -> 937.48333 | S92: ==MIN(X92,AD92,AJ92,AP92) -> 624 | T92: 冠龙 | U92: 黄经理13925121566 | V92: 973 | W92: 0.35 | X92: ==V92*(1-W92) -> 632.45 | Y92: ==X92*I92 -> 632.45 | Z92: 德国VAG | AA92: 吴居并13922353009 | AB92: 1556 | AD92: ==AB92*(1-AC92) -> 1556 | AE92: ==AB92*I92 -> 1556 | AF92: 丹麦AVK | AG92: 蔡文亮13570037656 | AH92: 624 | AJ92: ==AH92*(1-AI92) -> 624 | AK92: ==AH92*I92 -> 624
A93: 九 | B93: 放空泵房
A94: 1 | B94: 电动葫芦 | D94: 起重量 3T ,起吊高度 13m ,行程 14m , N=4.5kW | E94: 套 | F94: 1 | G94: 33600 | H94: ==G94*F94 -> 33600 | I94: 1 | J94: ==AI94 -> 0 | K94: ==G94 -> 33600 | L94: ==K94*I94 -> 33600 | O94: 65000 | Q94: 62586 | R94: ==AVERAGE(X94,AD94,AJ94,AP94) -> 41566.667 | S94: ==MIN(X94,AD94,AJ94,AP94) -> 13200 | T94: 广州起重机械 | U94: 谢启康13430264951 | V94: 87000 | W94: 0.1 | X94: ==V94*(1-W94) -> 78300 | Y94: ==X94*I94 -> 78300 | Z94: 广州泰克力 | AA94: 陈经理13570054553 | AB94: 33200 | AD94: ==AB94*(1-AC94) -> 33200 | AE94: ==AB94*I94 -> 33200 | AF94: 广东永通 | AG94: 陈经理13924880284 | AH94: 13200 | AJ94: ==AH94*(1-AI94) -> 13200 | AK94: ==AH94*I94 -> 13200
A95: 2 | B95: 放空泵 | D95: 潜污泵, 300m3/h , H=16m , N=22kW ,带变频控制、导轨及自耦系统 | E95: 套 | F95: 3 | G95: 35000 | H95: ==G95*F95 -> 105000 | I95: 3 | J95: ==AI95 -> 0.1 | K95: ==S95 -> 23728.5 | L95: ==K95*I95 -> 71185.5 | O95: 148000（H=20m） | Q95: 46500（Q=210m3/h） | R95: ==AVERAGE(X95,AD95,AJ95,AP95) -> 39156.75 | S95: ==MIN(X95,AD95,AJ95,AP95) -> 23728.5 | T95: 荏原 | U95: 韦国13798148955 | V95: 54585 | W95: 0 | X95: ==V95*(1-W95) -> 54585 | Y95: ==X95*I95 -> 163755 | Z95: 南方泵业 | AA95: 曾工13825006787 | AB95: 未生产 | AE95: 未生产 | AF95: 凯泉泵业 | AG95: 舒尧溢13825001721 | AH95: 26365 | AI95: 0.1 | AJ95: ==AH95*(1-AI95) -> 23728.5 | AK95: ==AH95*I95 -> 79095
A96: 3 | B96: 排涝泵 | D96: 潜污泵, 700m3/h , H=22m , N=75kW ,带变频控制、导轨及自耦系统 | E96: 套 | F96: 3 | G96: 120000 | H96: ==G96*F96 -> 360000 | I96: 3 | J96: ==AI96 -> 0.1 | K96: ==S96 -> 63819 | L96: ==K96*I96 -> 191457 | Q96: 109000（Q=1000m3/h） | R96: ==AVERAGE(X96,AD96,AJ96,AP96) -> 137875.5 | S96: ==MIN(X96,AD96,AJ96,AP96) -> 63819 | T96: 荏原 | U96: 韦国13798148955 | V96: 211932 | W96: 0 | X96: ==V96*(1-W96) -> 211932 | Y96: ==X96*I96 -> 635796 | Z96: 南方泵业 | AA96: 曾工13825006787 | AB96: 未生产 | AE96: 未生产 | AF96: 凯泉泵业 | AG96: 舒尧溢13825001721 | AH96: 70910 | AI96: 0.1 | AJ96: ==AH96*(1-AI96) -> 63819 | AK96: ==AH96*I96 -> 212730
A97: 4 | B97: 电动蝶阀 | D97: DN300 , PN10 ,开关型 | E97: 个 | F97: 3 | G97: 81500 | H97: ==G97*F97 -> 244500 | I97: 3 | J97: ==W97 -> 0.35 | K97: ==S97 -> 25841.4 | L97: ==K97*I97 -> 77524.2 | O97: 31200（DN350） | R97: ==AVERAGE(X97,AD97,AJ97,AP97) -> 35964.133 | S97: ==MIN(X97,AD97,AJ97,AP97) -> 25841.4 | T97: 冠龙 | U97: 黄经理13925121566 | V97: 39756 | W97: 0.35 | X97: ==V97*(1-W97) -> 25841.4 | Y97: ==X97*I97 -> 77524.2 | Z97: 德国VAG | AA97: 吴居并13922353009 | AB97: 47792 | AD97: ==AB97*(1-AC97) -> 47792 | AE97: ==AB97*I97 -> 143376 | AF97: 丹麦AVK | AG97: 蔡文亮13570037656 | AH97: 34259 | AJ97: ==AH97*(1-AI97) -> 34259 | AK97: ==AH97*I97 -> 102777
A98: 5 | B98: 电动蝶阀 | D98: DN500 , PN10 ,开关型 | E98: 个 | F98: 3 | G98: 91300 | H98: ==G98*F98 -> 273900 | I98: 3 | J98: ==AI98 -> 0 | K98: ==S98 -> 40808 | L98: ==K98*I98 -> 122424 | M98: ==K98*0.9 -> 36727.2 | N98: ==M98*I98-I98*K98 -> -12242.4 | O98: 35897（DN600） | R98: ==AVERAGE(X98,AD98,AJ98,AP98) -> 57820.117 | S98: ==MIN(X98,AD98,AJ98,AP98) -> 40808 | T98: 冠龙 | U98: 黄经理13925121566 | V98: 77219 | W98: 0.35 | X98: ==V98*(1-W98) -> 50192.35 | Y98: ==X98*I98 -> 150577.05 | Z98: 德国VAG | AA98: 吴居并13922353009 | AB98: 82460 | AD98: ==AB98*(1-AC98) -> 82460 | AE98: ==AB98*I98 -> 247380 | AF98: 丹麦AVK | AG98: 蔡文亮13570037656 | AH98: 40808 | AJ98: ==AH98*(1-AI98) -> 40808 | AK98: ==AH98*I98 -> 122424
A99: 6 | B99: 止回阀 | D99: DN300，PN10 | E99: 个 | F99: 3 | I99: 3 | J99: ==AI99 -> 0 | K99: ==S99 -> 12788 | L99: ==K99*I99 -> 38364 | M99: ==K99*0.9 -> 11509.2 | N99: ==M99*I99-I99*K99 -> -3836.4 | R99: ==AVERAGE(X99,AD99,AJ99,AP99) -> 14183.333 | S99: ==MIN(X99,AD99,AJ99,AP99) -> 12788 | T99: 冠龙 | U99: 黄经理13925121566 | V99: 23100 | W99: 0.35 | X99: ==V99*(1-W99) -> 15015 | Y99: ==X99*I99 -> 45045 | Z99: 德国VAG | AA99: 吴居并13922353009 | AB99: 14747 | AD99: ==AB99*(1-AC99) -> 14747 | AE99: ==AB99*I99 -> 44241 | AF99: 丹麦AVK | AG99: 蔡文亮13570037656 | AH99: 12788 | AJ99: ==AH99*(1-AI99) -> 12788 | AK99: ==AH99*I99 -> 38364
A100: 7 | B100: 止回阀 | D100: DN500，PN10 | E100: 个 | F100: 3 | I100: 3 | J100: ==AI100 -> 0 | K100: ==S100 -> 43851 | L100: ==K100*I100 -> 131553 | M100: ==K100*0.9 -> 39465.9 | N100: ==M100*I100-I100*K100 -> -13155.3 | O100: 8000（DN600） | R100: ==AVERAGE(X100,AD100,AJ100,AP100) -> 50769 | S100: ==MIN(X100,AD100,AJ100,AP100) -> 43851 | T100: 冠龙 | U100: 黄经理13925121566 | V100: 69300 | W100: 0.35 | X100: ==V100*(1-W100) -> 45045 | Y100: ==X100*I100 -> 135135 | Z100: 德国VAG | AA100: 吴居并13922353009 | AB100: 63411 | AD100: ==AB100*(1-AC100) -> 63411 | AE100: ==AB100*I100 -> 190233 | AF100: 丹麦AVK | AG100: 蔡文亮13570037656 | AH100: 43851 | AJ100: ==AH100*(1-AI100) -> 43851 | AK100: ==AH100*I100 -> 131553
...

Sheet 电气专业
A1: 设备价格表（含税）
A2: 单位工程：电气专业
A3: 序号 | B3: 设备名称 | C3: 概算规格、型号 | D3: 施工图预算规格、型号 | E3: 单位 | F3: 数量 | G3: 概算 | I3: 预算数量 | J3: 预算选用价格 | M3: 环城北 | O3: 中部水厂 | Q3: 洛溪水厂(首期) | S3: 南站水厂 | U3: 品牌1 | Y3: 品牌2 | AC3: 品牌3 | AG3: 品牌4
G4: 单价(元) | H4: 合价(元) | J4: 建议下浮率 | K4: 单价（元） | L4: 总价（元） | M4: 单价(元) | N4: 合价(元) | O4: 单价(元) | P4: 合价(元) | Q4: 单价(元) | R4: 合价(元) | S4: 询价均值 | T4: 询价最低价 | U4: 公司名称 | V4: 联系人、联系电话 | W4: 单价（元） | X4: 总价（元） | Y4: 公司名称 | Z4: 联系人、联系电话 | AA4: 单价（元） | AB4: 总价（元） | AC4: 公司名称 | AD4: 联系人、联系电话 | AE4: 单价（元） | AF4: 总价（元） | AG4: 公司名称 | AH4: 联系人、联系电话 | AI4: 单价（元） | AJ4: 总价（元）
B5: 光伏发电 | C5: 31.5KW | D5: 31.5KW | E5: m2 | F5: 194 | G5: ==H5/F5 -> 5154.6392 | H5: ==1000000 -> 1000000 | I5: 194 | J5: 0.8 | K5: ==T5*J5 -> 858.53608 | L5: ==I5*K5 -> 166556 | M5: ==N5/150 -> 1200 | N5: ==180000 -> 180000 | O5: 无 | Q5: 无 | S5: ==AVERAGE(W5,AA5,AE5,AI5) -> 1121.1211 | T5: ==MIN(W5,AA5,AE5,AI5) -> 1073.1701 | U5: 易事特 | V5: 陈焰明13925004039 | W5: ==X5/194 -> 1073.1701 | X5: ==208195 -> 208195 | Y5: 天合光能 | Z5: 马少凯18620931285 | AA5: ==AB5/194 -> 1169.0722 | AB5: ==31.5*7200 -> 226800 | AC5: 博燃环保 | AD5: 齐春军18923836432
B6: 电梯 | C6: 载重1350kg，速度1.75m/s | D6: 载重1350kg，速度1.75m/s | E6: 部 | F6: 3 | G6: ==H6/F6 -> 225149.42 | H6: 675448.26 | I6: 3 | J6: 0.9 | K6: ==T6*J6 -> 282047.53 | L6: ==I6*K6 -> 846142.6 | M6: ==N6/3 -> 291666.67 | N6: ==875000 -> 875000 | O6: ==217738.72/1 -> 217738.72 | P6: 217738.72 | Q6: ==R6/3 -> 131368.91 | R6: 394106.74 | S6: ==AVERAGE(W6,AA6,AE6,AI6) -> 326716.85 | T6: ==MIN(W6,AA6,AE6,AI6) -> 313386.15 | U6: 奥的斯 | V6: 王勇13922471918 | W6: ==X6/I6 -> 340047.55 | X6: 1020142.7 | Y6: 日立 | Z6: 陈总13246889088 | AA6: ==AB6/I6 -> 313386.15 | AB6: 940158.45 | AC6: 三菱 | AD6: 夏林涛13823799205
B7: 高压柜、直流屏 | C7: KYN28-12kV,800x1500x2300(WxDxH) | D7: KYN28-12kV,800x1500x2300(WxDxH) | E7: 台 | F7: 14 | G7: ==H7/F7 -> 50892.743 | H7: ==712498.4 -> 712498.4 | I7: 14 | J7: 1 | K7: ==T7*J7 -> 72087.667 | L7: ==I7*K7 -> 1009227.3 | M7: ==N7/14 -> 101365.71 | N7: ==1419120 -> 1419120 | O7: ==P7/12 -> 49055.342 | P7: ==588664.11 -> 588664.11 | Q7: ==R7/10 -> 100057.6 | R7: ==1000576 -> 1000576 | S7: ==AVERAGE(W7,AA7,AE7,AI7) -> 76261.833 | T7: ==MIN(W7,AA7,AE7,AI7) -> 72087.667 | U7: 颢成电气 | V7: 张总13352866588 | W7: ==X7/12 -> 80436 | X7: ==965232 -> 965232 | Y7: 白云电器 | Z7: 江德州15902087618 | AA7: ==AB7/12 -> 72087.667 | AB7: ==865052 -> 865052 | AC7: 尔安 | AD7: 冯总13424037926
B8: 低压进线柜 | C8: WxDxH=800x1000x2200mm | D8: WxDxH=800x1000x2200mm | E8: 台 | F8: 69 | G8: ==H8/F8 -> 76617.675 | H8: 5286619.5 | I8: 69 | J8: 1 | K8: ==T8*J8 -> 58355.767 | L8: ==I8*K8 -> 4026547.9 | M8: ==N8/150 -> 61126.667 | N8: ==9169000 -> 9169000 | O8: ==P8/63 -> 51633.21 | P8: ==3252892.2 -> 3252892.2 | Q8: ==R8/73 -> 80688.329 | R8: ==5890248 -> 5890248 | S8: ==AVERAGE(W8,AA8,AE8,AI8) -> 64487.123 | T8: ==MIN(W8,AA8,AE8,AI8) -> 58355.767 | U8: 颢成电气 | V8: 张总13352866588 | W8: ==X8/73 -> 58355.767 | X8: 4259971 | Y8: 白云电器 | Z8: 江德州15902087618 | AA8: ==AB8/69 -> 70618.478 | AB8: ==4872675 -> 4872675 | AC8: 尔安 | AD8: 冯总13424037926
B9: 变压器 | C9: SCB17-2500kVA,10kV/0.4kV,Uk=6% | D9: SCB15-2500kVA,10kV/0.4kV,Uk=6% | E9: 台 | F9: 2 | G9: ==H9/F9 -> 218384.01 | H9: 436768.02 | I9: 2 | J9: 0.8 | K9: ==T9*J9 -> 318400 | L9: ==I9*K9 -> 636800 | M9: ==N9/4 -> 200000 | N9: ==800000 -> 800000 | O9: ==P9/2 -> 236283 | P9: ==472566 -> 472566 | Q9: ==R9/3 -> 218900 | R9: ==656700 -> 656700 | S9: ==AVERAGE(W9,AA9,AE9,AI9) -> 399000 | T9: ==MIN(W9,AA9,AE9,AI9) -> 398000 | U9: 特变电工 | V9: 魏龙13380043790 | W9: ==X9/2 -> 398000 | X9: ==796000 -> 796000 | Y9: 明珠 | Z9: 甘经理13928809635 | AA9: ==AB9/2 -> 400000 | AB9: ==800000 -> 800000 | AC9: 广高高压 | AD9: 020-82266589
B10: 固定式柴油发电机组 | C10: 静音型,长行功率1600kW，自带ATS切换柜 | D10: 静音型,长行功率1600kW，自带ATS切换柜 | E10: 台 | F10: 1 | G10: ==H10/F10 -> 1250342.8 | H10: ==1250342.82 -> 1250342.8 | I10: 1 | J10: 0.9 | K10: ==T10*J10 -> 1575000 | L10: ==I10*K10 -> 1575000 | M10: ==N10/1 -> 800000 | N10: ==800000 -> 800000 | O10: ==P10/1 -> 998920 | P10: ==998920 -> 998920 | Q10: 无 | S10: ==AVERAGE(W10,AA10,AE10,AI10) -> 2170940.7 | T10: ==MIN(W10,AA10,AE10,AI10) -> 1750000 | U10: 进口卡特彼勒 | V10: 张总13041675888 | W10: ==X10/1 -> 2580000 | X10: ==2580000 -> 2580000 | Y10: 进口珀金斯 | Z10: 俞经理15985867496 | AA10: ==AB10/1 -> 1750000 | AB10: ==1750000 -> 1750000 | AC10: 进口康明斯 | AD10: 施总13802395095 | AE10: ==AF10/1 -> 2182822 | AF10: ==2182822 -> 2182822

Sheet 仪表自控专业设备
A1: 设备价格表（含税）
A2: 单位工程：仪表自控专业设备
A3: 序号 | B3: 设备名称 | C3: 概算规格、型号 | D3: 施工图预算规格、型号 | E3: 单位 | F3: 数量 | G3: 概算 | I3: 预算数量 | J3: 预算选用价格 | M3: 品牌1 | Q3: 品牌2 | U3: 品牌3 | Y3: 品牌4
G4: 单价(元) | H4: 合价(元) | J4: 建议下浮率 | K4: 单价（元） | L4: 总价（元） | M4: 公司名称 | N4: 联系人、联系电话 | O4: 单价（元） | P4: 总价（元） | Q4: 公司名称 | R4: 联系人、联系电话 | S4: 单价（元） | T4: 总价（元） | U4: 公司名称 | V4: 联系人、联系电话 | W4: 单价（元） | X4: 总价（元） | Y4: 公司名称 | Z4: 联系人、联系电话 | AA4: 单价（元） | AB4: 总价（元）
A5: 一 | B5: 工艺自控系统
B6: 中控室设备
A7: 1 | B7: I/O服务器 | C7: 1.名称:I/O服务器 2.规格:1)双路10核芯Xeon Silver 4210(2.20GHz)处理器;3)内存: 64GB ECC DDR4 RDIMM内存,最大支持640GB; 4)硬盘: 4x2.4TB 2.5" SAS(10K rpm)热插拔硬盘,最大支持16块热插拔硬盘,支持组建RAID0/1/1+0/5/7(本工程组建RAID 1+0); 5)I/O插槽: 1个全长PCI-E x16, 4个全长PCI-E x8和2个全长PCI-E x4插槽; 6)网卡: 双口千/百兆自适应工业以太网卡; 7)显示组件: 独立显卡(显存4GB);22"LCD显示器; 8)操作系统: 预装Windows Server 2019 企业版; 9)服务器机柜(合用): 工业标准,2000Hx1000Wx600D(mm),配22"LCD显示器专用托架,1U键盘托架1个;带鼠标键盘及显示器共享器(KVM转换器):PS/2 KVM接口适配器4口,VGA KVM切换口4个,RS485及RS-232 通讯口各2个; 10)其它: 4U机架式服务器;服务器采用工业标准服务器,电源、CPU、内存、I/O控制组件均采用冗余配置,服务器完全采用单机冗余方式;键盘、鼠标一套;16X DVD+/-RW;带通讯接口转换器:RS-485->PLC现场总线通讯接口; | E7: 套 | F7: 1 | G7: 138600 | H7: 138600 | K7: ==MIN(O7,S7,W7) -> 52800 | L7: ==F7*K7 -> 52800 | N7: 武宝凤 13826219800 | O7: 52800 | P7: ==F7*O7 -> 52800 | Q7: ABB | U7: 西门子 | V7: 张勇勤 18736008728 | W7: 95000 | X7: ==F7*W7 -> 95000
A8: 2 | B8: 监控服务器(组成双机热备服务器) | C8: 1)双路10核芯Xeon Silver 4210(2.20GHz)处理器;3)内存: 64GB ECC DDR4 RDIMM内存,最大支持640GB; 4)硬盘: 4x2.4TB 2.5" SAS(10K rpm)热插拔硬盘,最大支持16块热插拔硬盘,支持组建RAID0/1/1+0/5/7(本工程组建RAID 1+0); 5)I/O插槽: 1个全长PCI-E x16, 4个全长PCI-E x8和2个全长PCI-E x4插槽; 6)网卡: 双口千/百兆自适应工业以太网卡; 7)显示组件: 独立显卡(显存4GB);22"LCD显示器; 8)操作系统: 预装Windows Server 2019 企业版; 9)服务器机柜(合用): 工业标准,2000Hx1000Wx600D(mm),配22"LCD显示器专用托架,1U键盘托架1个;带鼠标键盘及显示器共享器(KVM转换器):PS/2 KVM接口适配器4口,VGA KVM切换口4个,RS485及RS-232 通讯口各2个; 10)其它: 4U机架式服务器;服务器采用工业标准服务器,电源、CPU、内存、I/O控制组件均采用冗余配置,服务器完全采用单机冗余方式;键盘、鼠标一套;16X DVD+/-RW;带通讯接口转换器:RS-485->PLC现场总线通讯接口; | E8: 套 | F8: 1 | G8: 138600 | H8: 138600 | K8: ==MIN(O8,S8,W8) -> 52800 | L8: ==F8*K8 -> 52800 | N8: 武宝凤 13826219800 | O8: 52800 | P8: ==F8*O8 -> 52800 | Q8: ABB | U8: 西门子 | V8: 张勇勤 18736008728 | W8: 95000 | X8: ==F8*W8 -> 95000
A9: 3 | B9: 工业以太网交换机 | C9: 支持工业光纤环以太网(冗余环,全负载状态下自愈时间<20ms);支持VLN功能,支持三层交换,支持流量控制,存储转发,带网管功能 | E9: 套 | F9: 5 | G9: 22000 | H9: 110000 | K9: ==MIN(O9,S9,W9) -> 56038 | L9: ==F9*K9 -> 280190 | N9: 武宝凤 13826219800 | O9: 56038 | P9: ==F9*O9 -> 280190 | Q9: ABB | U9: 西门子 | V9: 张勇勤 18736008728 | W9: 77053 | X9: ==F9*W9 -> 385265
A10: 4 | B10: 不间断电源 | C10: 在线式UPS,输入:380VAC,输出220VAC;10kVA120min备电,功率因数不小于0.98, RS232通讯接口 | E10: 套 | F10: 1 | G10: 38500 | H10: 38500 | K10: ==MIN(O10,S10,W10) -> 24350 | L10: ==F10*K10 -> 24350 | M10: 美国原厂SANTAK | N10: 施扬辉 13459466252 | O10: 24350 | P10: ==F10*O10 -> 24350 | Q10: 美国原厂艾默生Emerson | R10: 张新芬 13425171172 | S10: 37350 | T10: ==F10*S10 -> 37350 | U10: 日本原装APC | V10: 刘经理 15601761158 | W10: 48500 | X10: ==F10*W10 -> 48500 | Y10: 伊顿UPS | AC10: 梅兰日兰
A11: 5 | B11: 大屏幕无缝拼接墙系统(小间距LED拼接显示技术) | C11: 点间距：5.400(L)*1.920(H)=10.368m2;厚度(mm):≤14.50; 推荐最小观看距离≥3.0m; 视角(水平/垂直) ≥170度;屏幕亮度(cd/m2) ≥1000; 扫描驱动方式:1/32 扫描,恒流驱动; | E11: 套 | F11: 1 | G11: 379900 | H11: 379900 | K11: ==MIN(O11,S11,W11) -> 175180 | L11: ==F11*K11 -> 175180 | M11: 广州市炬诚电子科技 | Q11: 雷曼 | U11: 洲明 | W11: 175180 | X11: ==F11*W11 -> 175180
A12: 6 | B12: 便携式复合气体检测仪 | C12: 可充电锂电池供电,外壳防护等级IP67,防爆: 不低于Exd IIBT6;带RS232及USB接口,带95分贝声音报警(可设置多种报警音频);便携式,背光LCD同时显示各通道的气体浓度值,柱状图形显示电量;-10%%DC~+60%%DC; 工作湿度:≤95%RH,无冷凝(湿度>90%RH);测量范围:H2S: 0-100mg/m3; CH4:0-100%LEL; NH3:0-100ppm; O2: 0-25%VOL; | E12: 套 | F12: 2 | K12: ==MIN(O12,S12,W12) -> 28458 | L12: ==F12*K12 -> 56916 | M12: 英思科 | O12: 28458 | P12: ==F12*O12 -> 56916 | Q12: 罗斯蒙特 | U12: 霍尼威尔 | Y12: 科尔康
A13: 二 | B13: 中控室软件
A14: 1 | B14: 上位机软件狗 | C14: 运行版,无限点,软件与PLC实际硬件的一致 | E14: 套 | F14: 3 | G14: 118800 | H14: 356400 | K14: ==MIN(O14,S14,W14) -> 74267.46 | L14: ==F14*K14 -> 222802.38 | U14: 西门子 | V14: 张勇勤 18736008728 | W14: 74267.46 | X14: ==F14*W14 -> 222802.38
A15: 2 | B15: 上位机软件狗 | C15: 开发版+运行版,无限点,软件与PLC实际硬件的一致 | E15: 套 | F15: 1 | G15: 103700 | H15: 103700 | K15: ==MIN(O15,S15,W15) -> 35289.2 | L15: ==F15*K15 -> 35289.2 | U15: 西门子 | V15: 张勇勤 18736008728 | W15: ==16165+38248.4/2 -> 35289.2 | X15: ==F15*W15 -> 35289.2
A16: 3 | B16: 上位机画面开发 | E16: 套 | F16: 1 | G16: 8400 | H16: 8400 | K16: ==MIN(O16,S16,W16) -> 0 | L16: ==F16*K16 -> 0 | W16: 已含于工程师站软件内
A17: 4 | B17: PLC编程软件 | C17: 与PLC硬件系统配套,含编程电缆 | E17: 套 | F17: 1 | G17: 28100 | H17: 28100 | K17: ==MIN(O17,S17,W17) -> 0 | L17: ==F17*K17 -> 0 | W17: 已含于工程师站软件内
A18: 5 | B18: 数据库管理软件 | C18: SQL SERVER 2016企业版 | E18: 套 | F18: 2 | G18: 140732.58 | H18: 281465.16 | K18: ==MIN(O18,S18,W18) -> 53512 | L18: ==F18*K18 -> 107024 | U18: 西门子 | V18: 张勇勤 18736008728 | W18: 53512 | X18: ==F18*W18 -> 107024
A19: 6 | B19: 实时历史数据库管理软件 | C19: Historian实时数据库,用于实时监测数据的记录,60000点授权 | E19: 套 | F19: 1 | G19: 70366.31 | H19: 70366.31 | K19: ==MIN(O19,S19,W19) -> 414103 | L19: ==F19*K19 -> 414103 | U19: 西门子 | V19: 张勇勤 18736008728 | W19: 414103 | X19: ==F19*W19 -> 414103
A20: 7 | B20: 自控系统二次开发 | E20: 套 | F20: 1 | G20: 140732.58 | H20: 140732.58 | K20: ==MIN(O20,S20,W20) -> 0 | L20: ==F20*K20 -> 0
A21: 四 | B21: 网络电话系统设备
A22: 1 | B22: 网络电话机 | C22: 1) VOIP标准, 壁挂式, 防潮型, RJ45接口,PoE供电,IP65; 2) 支持WAN/LAN口桥模式与路由模式的选择,可以同时接入IP语音和数据业务; 3) 基于SIP标准协议,兼容任何采用SIP标准的IP电话系统;支持全部标准PBX功能; 4) 2路来电显示支 持2个同时并存的呼叫;NAT穿透, 支持STUN方式穿透; | E22: 台 | F22: 11 | G22: 20200 | H22: 222200 | K22: ==MIN(O22,S22,W22) -> 250 | L22: ==F22*K22 -> 2750 | M22: 鼎信通达 | N22: 陈玉楼 13825193113 | O22: 260 | P22: ==F22*O22 -> 2860 | Q22: Alcatel阿尔卡特H2 | R22: 谢海锋18620817000 | S22: 250 | T22: ==F22*S22 -> 2750 | U22: 申瓯 | W22: 300 | X22: ==F22*W22 -> 3300
A23: 2 | B23: IP PBX（IP电话网关） | C23: 1) 用户容量最大容量:300(最大224个本地模拟用户/300个IP用户) 2) 终端类型:模拟话机、IP话机、视频话机 3) 中继接口:提供16路FXO、2E1/T1接口 4) 信令协议:SS7、R2、PRI、QSIG、SIP 5) AC:100V~240V;50Hz/60Hz; 6) 标准19英寸2U机框; 7) 可管理性:支持集中/远程设备管理、信令跟踪、资源管理、告警管理、快速开局 | E23: 套 | F23: 1 | G23: 7700 | H23: 7700 | K23: ==MIN(O23,S23,W23) -> 3520 | L23: ==F23*K23 -> 3520 | M23: 星纵 | N23: 陈玉楼 13825193113 | O23: 11680 | P23: ==F23*O23 -> 11680 | Q23: 三汇 | R23: 谢海锋18620817000 | S23: 3520 | T23: ==F23*S23 -> 3520 | U23: 申瓯 | W23: 42000 | X23: ==F23*W23 -> 42000
B24: IP电话交换软件 | C24: 可通过以太网与外线电话、内部IP电话进行呼叫、通话(含电话话费) | E24: 套 | F24: 1 | G24: 6100 | H24: 6100 | M24: 松下 | N24: 含于整体设备 | Q24: 爱立信 | R24: 含于整体设备 | U24: 申瓯 | V24: 含于整体设备
A25: 七 | B25: 地面设备间
A26: 1 | B26: 地面自控室PLC测控站（1PLC站） | C26: 可编程控制器系统(含冗余CPU模块、冗余电源模块、冗余通讯模块)1) 104xDI,32xDO,4xAI,4xAO,I/O隔离,带电源、信号浪涌保护器;2) 支持工业以太网/Profibus/ControlNet/MB+;带工业以太网、工业现场总线通讯接口(注:污水厂全厂PLC自控设备的工业现场总线通讯接口应统一)及 RS485接口,带相关总线通讯适配器;3) 10.4英寸工业用带背光TFT彩色LCD触摸屏(1024x768像素);4) 配套在线式UPS 220VAC 5kVA 120min不间断电源;5) 含导轨式,24电口(不少于4个PoE口),8光口千兆工业以太网PoE交换机(支持光纤环,网管型),防潮型,IP65。6) 含导轨式,8路,485通信管理机。7) 1套PLC机柜2200Hx800Wx1000D(mm),(含PLC程序及触摸屏组态)。 | E26: 套 | F26: 1 | G26: 347050 | H26: 347050 | K26: ==MIN(O26,S26,W26) -> 179000 | L26: ==F26*K26 -> 179000 | N26: 武宝凤 13826219800 | O26: 179000 | P26: ==F26*O26 -> 179000 | Q26: ABB | U26: 西门子 | V26: 张勇勤 18736008728 | W26: 310000 | X26: ==F26*W26 -> 310000 | Y26: 施耐德 | Z26: 李越13826163590
A27: 2 | B27: 多通道有毒气体检测仪 (氧气、毒气和可燃气体) | C27: 1) 控制器电源输入: DC24V%%P10%, 50Hz;电源输出:DC24V%%P10%;2) 报警方式:声、光报警,数字及光柱显示;控制器及每路探测器均带独立声光报警;3) 工作温度:-20%%DC~+55%%DC; 工作湿度:≤95%RH, 不凝露;4) 背光TFT彩色触摸屏,全中文菜单操作; 带温、湿度监测功能；5) 内置防浪涌功能, 有效防止感应雷及浪涌对设备的伤害;6) 功耗:正常及报警不大于7W/路;自带24V后备电源(5小时电量)；7) 壁挂式控制器,8通道,不锈钢外壳,防护等级IP66, 防爆: 不低于Exd IIBT6;8) 输出信号:Modbus协议 RS485工业现场总线;每路探头带2级报警(自定义);9) 支持8路气体检测,气体检测探头输入信号:带RS485工业现场总线长度≥100米；10) 附气体检测探头(均独立, 不锈钢IP67,防爆: 不低于ExdIIBT6;精度%%P1%FS):1# H2S: 0-25mg/m3; 2# CH4: 0-100%LEL; 3#NH3: 0-100ppm;4# O2: 0-25%VOL; 5# 温度: -40%%DC~120%%DC; 6# 湿度: 0%RH~100%RH; | E27: 套 | F27: 1 | G27: 30000 | H27: 30000 | K27: ==MIN(O27,S27,W27) -> 28458 | L27: ==F27*K27 -> 28458 | M27: 英思科 | O27: 28458 | P27: ==F27*O27 -> 28458 | Q27: 罗斯蒙特 | U27: 霍尼威尔 | Y27: 科尔康
A28: 八 | B28: 预处理区
A29: 1 | B29: 预处理区PLC测控站（2PLC站） | C29: 可编程控制器系统(含冗余CPU模块、冗余电源模块、冗余通讯模块)1) 416xDI,104xDO,32xAI,24xAO,I/O隔离,带电源、信号浪涌保护器; 2) 支持工业以太网/Profibus/ControlNet/MB+;带工业以太网、工业现场总线通讯接口(注:污水厂全厂PLC自控设备的工业现场总线通讯接口应统一)及RS485接口,带相关总线通讯适配器;3) 10.4英寸工业用带背光TFT彩色LCD触摸屏(1024x768像素);4) 配套在线式UPS 220VAC 5kVA 120min不间断电源;5) 含导轨式,16电口(不少于4个PoE口),16光口千兆工业以太网PoE交换机(支持光纤环,网管型),防潮型,IP65。6) 含导轨式,8路,485通信管理机。7) 3套PLC机柜2200Hx800Wx1000D(mm),(含PLC程序及触摸屏组态)。 | E29: 套 | F29: 1 | G29: 347050 | H29: 347050 | K29: ==MIN(O29,S29,W29) -> 179000 | L29: ==F29*K29 -> 179000 | N29: 武宝凤 13826219800 | O29: 179000 | P29: ==F29*O29 -> 179000 | Q29: ABB | U29: 西门子 | V29: 张勇勤 18736008728 | W29: 490000 | X29: ==F29*W29 -> 490000 | Y29: 施耐德 | Z29: 李越13826163590
A30: 2 | B30: I/O服务器 | C30: 1)24xDI,8xDO,I/O隔离,带电源、信号浪涌保护器。2)支持工业以太网/Profibus/ControlNet/MB+;带工业以太网、工业现场总线通讯接口(注:污水厂全厂PLC自控设备的工业现场总线通讯接口应统一)及RS485接口,带相关总线通讯适配器。3)I/O站机箱800Hx600Wx250D(mm)IP54。 | E30: 套 | F30: 5 | G30: 138621.61 | H30: 693108.05 | K30: ==MIN(O30,S30,W30) -> 27000 | L30: ==F30*K30 -> 135000 | N30: 武宝凤 13826219800 | O30: 27000 | P30: ==F30*O30 -> 135000 | Q30: ABB | U30: 西门子 | V30: 张勇勤 18736008728 | W30: 65000 | X30: ==F30*W30 -> 325000 | Y30: 施耐德 | Z30: 李越13826163590
A31: 3 | B31: 超声波液位计 | C31: 1) 绝对液位:0-12m,精度%%P0.5%,分体式,电源AC220V;2) 一对传感器IP68,波束角4%%D,传感器电缆15m/15m;3) 双通道变送器IP65,带立柱式不锈钢保护箱及附件;4) 栅前及栅后液位/液位差/故障状态,工业现场总线通讯+4~20mA模拟量接口;5) LCD现场显示 | E31: 套 | F31: 9 | G31: 8700 | H31: 78300 | K31: ==MIN(O31,S31,W31) -> 18392 | L31: ==F31*K31 -> 165528 | M31: E+H | N31: 黄13326426530 | O31: 18392 | P31: ==F31*O31 -> 165528 | R31: 武宝凤 13826219800 | S31: 21072 | T31: ==F31*S31 -> 189648 | U31: 西门子 | V31: 张勇勤 18736008728 | W31: 55000 | X31: ==F31*W31 -> 495000
A32: 4 | B32: 电磁流量计 | C32: 1) DN1200,PN1.0Mpa,0~2m3/s,精度%%P0.5%,电源AC220V;2) 分体式,法兰连接,传感器IP68,聚四氟乙烯衬里,钽电极,带接地环等;3) 变送器IP67,传感器电缆15m,带立柱式不锈钢保护箱及附件;4) 带非满管及空管检测功能:在空管时,可靠零输出并显示和输出报警信号;5) 瞬时值/累计值/故障状态,工业现场总线通讯接口;6) LCD现场显示,带自清洗系统. | E32: 套 | F32: 1 | G32: 28408.156 | H32: 28408.16 | K32: ==MIN(O32,S32,W32) -> 96000 | L32: ==F32*K32 -> 96000 | M32: E+H | N32: 黄13326426530 | O32: 136800 | P32: ==F32*O32 -> 136800 | R32: 武宝凤 13826219800 | S32: 96000 | T32: ==F32*S32 -> 96000 | U32: 西门子 | V32: 张勇勤 18736008728 | W32: 167000 | X32: ==F32*W32 -> 167000 | Y32: 科隆公司（KROHNE）
A33: 5 | B33: 电磁流量计 | C33: 1) DN1000,PN1.0Mpa,0~2m3/s,精度%%P0.5%,电源AC220V;2) 分体式,法兰连接,传感器IP68,聚四氟乙烯衬里,钽电极,带接地环等;3) 变送器IP67,传感器电缆15m,带立柱式不锈钢保护箱及附件;4) 带非满管及空管检测功能:在空管时,可靠零输出并显示和输出报警信号;5) 瞬时值/累计值/故障状态,工业现场总线通讯接口;6) LCD现场显示,带自清洗系统 | E33: 套 | F33: 2 | G33: 23400 | H33: 46800 | K33: ==MIN(O33,S33,W33) -> 68000 | L33: ==F33*K33 -> 136000 | M33: E+H | N33: 黄13326426530 | O33: 76320 | P33: ==F33*O33 -> 152640 | R33: 武宝凤 13826219800 | S33: 68000 | T33: ==F33*S33 -> 136000 | U33: 西门子 | V33: 张勇勤 18736008728 | W33: 115000 | X33: ==F33*W33 -> 230000 | Y33: 科隆公司（KROHNE）
A34: 6 | B34: 多通道有毒气体检测仪 (氧气、毒气和可燃气体) | C34: 1) 控制器电源输入: DC24V%%P10%, 50Hz;电源输出:DC24V%%P10%;2) 报警方式:声、光报警,数字及光柱显示;控制器及每路探测器均带独立声光报警;3) 工作温度:-20%%DC~+55%%DC; 工作湿度:≤95%RH, 不凝露;4) 背光TFT彩色触摸屏,全中文菜单操作; 带温、湿度监测功能；5) 内置防浪涌功能, 有效防止感应雷及浪涌对设备的伤害;6) 功耗:正常及报警不大于7W/路;自带24V后备电源(5小时电量)；7) 壁挂式控制器,8通道,不锈钢外壳,防护等级IP66, 防爆: 不低于Exd IIBT6;8) 输出信号:Modbus协议 RS485工业现场总线;每路探头带2级报警(自定义);9) 支持8路气体检测,气体检测探头输入信号:带RS485工业现场总线长度≥100米；10) 附气体检测探头(均独立, 不锈钢IP67,防爆: 不低于ExdIIBT6;精度%%P1%FS):1# H2S: 0-25mg/m3; 2# CH4: 0-100%LEL; 3#NH3: 0-100ppm;4# O2: 0-25%VOL; 5# 温度: -40%%DC~120%%DC; 6# 湿度: 0%RH~100%RH; | E34: 套 | F34: 9 | G34: 30000 | H34: 270000 | K34: ==MIN(O34,S34,W34) -> 28458 | L34: ==F34*K34 -> 256122 | M34: 英思科 | O34: 28458 | P34: ==F34*O34 -> 256122 | Q34: 罗斯蒙特 | U34: 霍尼威尔 | Y34: 科尔康
A35: 九 | B35: 生化池
A36: 1 | B36: 生化池PLC测控站（3PLC站） | C36: 可可编程控制器系统(含CPU模块、电源模块、冗余通讯模块)1) 200xDI,64xDO,36xAI,32xAO,I/O隔离,带电源、信号浪涌保护器; 2) 支持工业以太网/Profibus/ControlNet/MB+;带工业以太网、工业现场总线通讯接口(注:污水厂全厂PLC自控设备的工业现场总线通讯接口应统一)及 RS485接口,带相关总线通讯适配器;3) 10.4英寸工业用带背光TFT彩色LCD触摸屏(1024x768像素);4) 配套在线式UPS 220VAC 5kVA 120min不间断电源;5) 含导轨式,24电口(不少于4个PoE口),8光口千兆工业以太网PoE交换机(支持光纤环,网管型),防潮型,IP65。6) 含导轨式,8路,485通信管理机。7) 2套PLC机柜2200Hx800Wx1000D(mm),(含PLC程序及触摸屏组态)。 | E36: 套 | F36: 1 | G36: 347050 | H36: 347050 | K36: ==MIN(O36,S36,W36) -> 190000 | L36: ==F36*K36 -> 190000 | M36: Emerson(GE) | N36: 厂家不配合报价 | R36: 武宝凤 13826219800 | S36: 190000 | T36: ==F36*S36 -> 190000 | U36: 西门子 | V36: 张勇勤 18736008728 | W36: 390000 | X36: ==F36*W36 -> 390000 | Y36: 施耐德 | Z36: 李越13826163590
A37: 2 | B37: I/O服务器 | C37: 1)24xDI,8xDO,I/O隔离,带电源、信号浪涌保护器。2)支持工业以太网/Profibus/ControlNet/MB+;带工业以太网、工业现场总线通讯接口(注:污水厂全厂PLC自控设备的工业现场总线通讯接口应统一)及RS485接口,带相关总线通讯适配器。3)I/O站机箱800Hx600Wx250D(mm)IP54。 | E37: 套 | F37: 9 | G37: 138621.61 | H37: 1247594.5 | K37: ==MIN(O37,S37,W37) -> 27000 | L37: ==F37*K37 -> 243000 | M37: Emerson(GE) | N37: 厂家不配合报价 | R37: 武宝凤 13826219800 | S37: 27000 | T37: ==F37*S37 -> 243000 | U37: 西门子 | V37: 张勇勤 18736008728 | W37: 65000 | X37: ==F37*W37 -> 585000 | Y37: 施耐德 | Z37: 李越13826163590
A38: 4 | B38: MISS在线检测仪 | C38: 1) 0-10g/l,精度%%P1%,电源AC220V; 2) 浸入式传感器IP68,带悬挂支架,传感器电缆15m; 3) 变送器IP66,带立柱式不锈钢保护箱及附件; 4) MLSS值/故障状态,工业现场总线通讯接口; 5) 在线式检测仪表,LCD现场显示 | E38: 套 | F38: 8 | G38: 71998 | H38: 575984 | K38: ==MIN(O38,S38,W38) -> 5000 | L38: ==F38*K38 -> 40000 | M38: HACH | N38: 张锐熙15626146220 | O38: 5000 | P38: ==F38*O38 -> 40000 | Q38: E+H | R38: 黄13326426530 | S38: 33710 | T38: ==F38*S38 -> 269680 | U38: WTW | V38: 廖昌平 18218221882 | W38: 45825 | X38: ==F38*W38 -> 366600
A39: 5 | B39: DO在线检测仪 | C39: 1) DO:0~10mg/L,精度%%P1%,荧光法,电源AC220V;2) 浸入式传感器IP68,带悬挂支架,传感器电缆15;3) 变送器IP66,带立柱式不锈钢保护箱及附件;4) DO值/故障状态,工业现场总线通讯接口;5) 在线式检测仪表,LCD现场显示,自动清洗装置 | E39: 套 | F39: 10 | G39: 44000 | H39: 440000 | K39: ==MIN(O39,S39,W39) -> 26500 | L39: ==F39*K39 -> 265000 | M39: HACH | N39: 张锐熙15626146220 | O39: 53000 | P39: ==F39*O39 -> 530000 | Q39: E+H | R39: 黄13326426530 | S39: 26500 | T39: ==F39*S39 -> 265000 | U39: WTW | V39: 廖昌平 18218221882 | W39: 27243 | X39: ==F39*W39 -> 272430
A40: 6 | B40: OPR在线分析仪 | C40: 1) ORP:-1500~1500mv,精度%%P1mv,电源AC220V;2) 数字差分浸入式传感器IP68,带悬挂支架,传感器电缆8m;3) 变送器IP66,带立柱式不锈钢保护箱及附件;4) ORP/故障状态,Modbus工业现场总线通讯接口;5) LCD现场显示,自动清洗装置 | E40: 套 | F40: 6 | G40: 30000 | H40: 180000 | K40: ==MIN(O40,S40,W40) -> 12585 | L40: ==F40*K40 -> 75510 | M40: HACH | N40: 张锐熙15626146220 | O40: 35000 | P40: ==F40*O40 -> 210000 | Q40: E+H | R40: 黄13326426530 | S40: 12585 | T40: ==F40*S40 -> 75510 | U40: WTW | V40: 廖昌平 18218221882 | W40: 23085 | X40: ==F40*W40 -> 138510
A41: 7 | B41: 氨氮检测仪 | C41: 1) 0-30mg/l, 精度%%P5%,离子选择电极法,电源AC220V;2) 混合水样测量,带采样水泵(20m扬程)及预处理取样系统(250ml/h);3) 预处理取样系统及分析仪表带不锈钢IP54保护柜及附件,含悬挂支架;4) 采样及预处理装置至分析仪表的电缆及采样管道各30m;5) NH3N值/故障状态,工业现场总线通讯接口;6) 在线式检测仪表,LCD现场显示,带自清洗装置;自动标样核查功能模块; | E41: 套 | F41: 2 | G41: 38300 | H41: 76600 | K41: ==MIN(O41,S41,W41) -> 45980 | L41: ==F41*K41 -> 91960 | M41: HACH | N41: 张锐熙15626146220 | O41: 100000 | P41: ==F41*O41 -> 200000 | Q41: E+H | R41: 黄13326426530 | S41: 45980 | T41: ==F41*S41 -> 91960 | U41: WTW | V41: 廖昌平 18218221882 | W41: 63800 | X41: ==F41*W41 -> 127600
A42: 8 | B42: 超声波液位计 | C42: 1) 0-10m,精度%%P0.5%,分体式,电源AC220V;2) 传感器IP68,波束角8%%D,传感器电缆15m;3) 变送器IP65,带立柱式不锈钢保护箱及附件;4) 液位/故障状态,工业现场总线通讯+4~20mA模拟量接口;5) LCD现场显示 | E42: 套 | F42: 4 | G42: 8700 | H42: 34800 | K42: ==MIN(O42,S42,W42) -> 11000 | L42: ==F42*K42 -> 44000 | M42: E+H | N42: 黄13326426530 | O42: 16362 | P42: ==F42*O42 -> 65448 | R42: 武宝凤 13826219800 | S42: 11000 | T42: ==F42*S42 -> 44000 | U42: 西门子 | V42: 张勇勤 18736008728 | W42: 20000 | X42: ==F42*W42 -> 80000
A43: 9 | B43: 多通道有毒气体检测仪 (氧气、毒气和可燃气体) | C43: 1) 控制器电源输入: DC24V%%P10%, 50Hz;电源输出:DC24V%%P10%;2) 报警方式:声、光报警,数字及光柱显示;控制器及每路探测器均带独立声光报警;3) 工作温度:-20%%DC~+55%%DC; 工作湿度:≤95%RH, 不凝露;4) 背光TFT彩色触摸屏,全中文菜单操作; 带温、湿度监测功能；5) 内置防浪涌功能, 有效防止感应雷及浪涌对设备的伤害;6) 功耗:正常及报警不大于7W/路;自带24V后备电源(5小时电量)；7) 壁挂式控制器,8通道,不锈钢外壳,防护等级IP66, 防爆: 不低于Exd IIBT6;8) 输出信号:Modbus协议 RS485工业现场总线;每路探头带2级报警(自定义);9) 支持8路气体检测,气体检测探头输入信号:带RS485工业现场总线长度≥100米；10) 附气体检测探头(均独立, 不锈钢IP67,防爆: 不低于ExdIIBT6;精度%%P1%FS):1# H2S: 0-25mg/m3; 2# CH4: 0-100%LEL; 3#NH3: 0-100ppm;4# O2: 0-25%VOL; 5# 温度: -40%%DC~120%%DC; 6# 湿度: 0%RH~100%RH; | E43: 套 | F43: 4 | G43: 30000 | H43: 120000 | K43: ==MIN(O43,S43,W43) -> 28458 | L43: ==F43*K43 -> 113832 | M43: 英思科 | O43: 28458 | P43: ==F43*O43 -> 113832 | Q43: 罗斯蒙特 | U43: 霍尼威尔 | Y43: 科尔康
A44: 十 | B44: 放空泵房
A45: 1 | B45: 放空泵房PLC测控站（5PLC站） | C45: 可编程控制器系统(含CPU模块、电源模块、冗余通讯模块)1) 72xDI,32xDO,16xAI,12xAO,I/O隔离,带电源、信号浪涌保护器;2) 支持工业以太网/Profibus/ControlNet/MB+;带工业以太网、工业现场总线通讯接口(注:污水厂全厂PLC自控设备的工业现场总线通讯接口应统一)及RS485接口,带相关总线通讯适配器;3) 10.4英寸工业用带背光TFT彩色LCD触摸屏(1024x768像素);4) 配套在线式UPS 220VAC 5kVA 120min不间断电源;5) 含导轨式,24电口(不少于4个PoE口),8光口千兆工业以太网PoE交换机(支持光纤环,网管型),防潮型,IP65。6) 含导轨式,8路,485通信管理机。7) 1套PLC机柜2200Hx800Wx1000D(mm),(含PLC程序及触摸屏组态)。 | E45: 套 | F45: 1 | G45: 347050 | H45: 347050 | K45: ==MIN(O45,S45,W45) -> 170000 | L45: ==F45*K45 -> 170000 | M45: Emerson(GE) | N45: 厂家不配合报价 | R45: 武宝凤 13826219800 | S45: 170000 | T45: ==F45*S45 -> 170000 | U45: 西门子 | V45: 张勇勤 18736008728 | W45: 350000 | X45: ==F45*W45 -> 350000 | Y45: 施耐德 | Z45: 李越13826163590
A46: 2 | B46: I/O服务器 | C46: 1)24xDI,8xDO,I/O隔离,带电源、信号浪涌保护器。2)支持工业以太网/Profibus/ControlNet/MB+;带工业以太网、工业现场总线通讯接口(注:污水厂全厂PLC自控设备的工业现场总线通讯接口应统一)及RS485接口,带相关总线通讯适配器。3)I/O站机箱800Hx600Wx250D(mm)IP54。 | E46: 套 | F46: 2 | G46: 138621.61 | H46: 277243.22 | K46: ==MIN(O46,S46,W46) -> 27000 | L46: ==F46*K46 -> 54000 | M46: Emerson(GE) | N46: 厂家不配合报价 | R46: 武宝凤 13826219800 | S46: 27000 | T46: ==F46*S46 -> 54000 | U46: 西门子 | V46: 张勇勤 18736008728 | W46: 65000 | X46: ==F46*W46 -> 130000 | Y46: 施耐德 | Z46: 李越13826163590
A47: 3 | B47: 超声波液位计 | C47: 1) 0.35-10m,精度%%P0.5%,分体式,电源AC220V;2) 传感器IP68,波束角8%%D,传感器电缆15m;3) 变送器IP65,带立柱式不锈钢保护箱及附件;4) 液位/故障状态,工业现场总线通讯+4~20mA模拟量接口;5) LCD现场显示 | E47: 套 | F47: 2 | G47: 8700 | H47: 17400 | K47: ==MIN(O47,S47,W47) -> 11000 | L47: ==F47*K47 -> 22000 | M47: E+H | N47: 黄13326426530 | O47: 16362 | P47: ==F47*O47 -> 32724 | R47: 武宝凤 13826219800 | S47: 11000 | T47: ==F47*S47 -> 22000 | U47: 西门子 | V47: 张勇勤 18736008728 | W47: 20000 | X47: ==F47*W47 -> 40000
A48: 4 | B48: 投入静压液位计 | C48: 1) 0-5m,精度%%P0.3%,分体式,电源AC220V;2) 适合于废/污水测量的陶瓷测量传感器探头IP68,传感器电缆(氟化乙烯丙烯绝缘)及电缆套管35m;传感器套管:PPS(聚亚苯基) 热缩套管/盖:聚烯烃;3) 密封的电子电路和双过滤器压力补偿抗气候变化,输出信号具有集成过压保护;4) 含配套固定夹及G1 1/2 A螺纹的加长电缆固定螺丝;5) 变送器IP65,带立柱式不锈钢保护箱及附件;探头含定制不锈钢探头保护笼;6) 液位/故障状态,工业现场总线通讯接口;7) LCD现场显示 | E48: 套 | F48: 2 | G48: 17900 | H48: 35800 | K48: ==MIN(O48,S48,W48) -> 5400 | L48: ==F48*K48 -> 10800 | M48: E+H | N48: 黄13326426530 | O48: 6000 | P48: ==F48*O48 -> 12000 | R48: 武宝凤 13826219800 | S48: 5400 | T48: ==F48*S48 -> 10800 | U48: 西门子 | V48: 张勇勤 18736008728 | W48: 6000 | X48: ==F48*W48 -> 12000
A49: 5 | B49: 多通道有毒气体检测仪 (氧气、毒气和可燃气体) | C49: 1) 控制器电源输入: DC24V%%P10%, 50Hz;电源输出:DC24V%%P10%;2) 报警方式:声、光报警,数字及光柱显示;控制器及每路探测器均带独立声光报警;3) 工作温度:-20%%DC~+55%%DC; 工作湿度:≤95%RH, 不凝露;4) 背光TFT彩色触摸屏,全中文菜单操作; 带温、湿度监测功能；5) 内置防浪涌功能, 有效防止感应雷及浪涌对设备的伤害;6) 功耗:正常及报警不大于7W/路;自带24V后备电源(5小时电量)；7) 壁挂式控制器,8通道,不锈钢外壳,防护等级IP66, 防爆: 不低于Exd IIBT6;8) 输出信号:Modbus协议 RS485工业现场总线;每路探头带2级报警(自定义);9) 支持8路气体检测,气体检测探头输入信号:带RS485工业现场总线长度≥100米；10) 附气体检测探头(均独立, 不锈钢IP67,防爆: 不低于ExdIIBT6;精度%%P1%FS):1# H2S: 0-25mg/m3; 2# CH4: 0-100%LEL; 3#NH3: 0-100ppm;4# O2: 0-25%VOL; 5# 温度: -40%%DC~120%%DC; 6# 湿度: 0%RH~100%RH; | E49: 套 | F49: 10 | G49: 30000 | H49: 300000 | K49: ==MIN(O49,S49,W49) -> 28458 | L49: ==F49*K49 -> 284580 | M49: 英思科 | O49: 28458 | P49: ==F49*O49 -> 284580 | Q49: 罗斯蒙特 | U49: 霍尼威尔 | Y49: 科尔康
A50: 十一 | B50: 中水泵房
A51: 1 | B51: 中水泵房PLC测控站（6PLC站） | C51: 可编程控制器系统(含CPU模块、电源模块、冗余通讯模块)1) 144xDI,48xDO,8xAI,8xAO,I/O隔离,带电源、信号浪涌保护器;2) 支持工业以太网/Profibus/ControlNet/MB+;带工业以太网、工业现场总线通讯接口(注:污水厂全厂PLC自控设备的工业现场总线通讯接口应统一)及RS485接口,带相关总线通讯适配器;3) 10.4英寸工业用带背光TFT彩色LCD触摸屏(1024x768像素);4) 在线式UPS 220VAC 5kVA 60min备电;5) 含导轨式,24电口(不少于4个PoE口),8光口千兆工业以太网PoE交换机(支持光纤环,网管型),防潮型,IP65。6) 含导轨式,8路,485通信管理机。7) 2套PLC机柜2200Hx800Wx1000D(mm),(含PLC程序及触摸屏组态)。 | E51: 套 | F51: 1 | G51: 347050 | H51: 347050 | K51: ==MIN(O51,S51,W51) -> 170000 | L51: ==F51*K51 -> 170000 | M51: Emerson(GE) | R51: 武宝凤 13826219800 | S51: 170000 | T51: ==F51*S51 -> 170000 | U51: 西门子 | V51: 张勇勤 18736008728 | W51: 350000 | X51: ==F51*W51 -> 350000 | Y51: 施耐德 | Z51: 李越13826163590
A52: 2 | B52: I/O服务器 | C52: 1)24xDI,8xDO,I/O隔离,带电源、信号浪涌保护器。2)支持工业以太网/Profibus/ControlNet/MB+;带工业以太网、工业现场总线通讯接口(注:污水厂全厂PLC自控设备的工业现场总线通讯接口应统一)及RS485接口,带相关总线通讯适配器。3)I/O站机箱800Hx600Wx250D(mm)IP54。 | E52: 套 | F52: 6 | G52: 138621.61 | H52: 831729.66 | K52: ==MIN(O52,S52,W52) -> 27000 | L52: ==F52*K52 -> 162000 | M52: Emerson(GE) | R52: 武宝凤 13826219800 | S52: 27000 | T52: ==F52*S52 -> 162000 | U52: 西门子 | V52: 张勇勤 18736008728 | W52: 65000 | X52: ==F52*W52 -> 390000 | Y52: 施耐德 | Z52: 李越13826163590
A53: 3 | B53: 电磁流量计 | C53: 1) DN200,PN1.0Mpa,0~20m3/h,精度%%P0.5%,电源AC220V;2) 分体式,法兰连接,传感器IP68,聚四氟乙烯衬里,钽电极,带接地环等;3) 变送器IP67,传感器电缆15m,带立柱式不锈钢保护箱及附件;4) 带非满管及空管检测功能:在空管时,可靠零输出并显示和输出报警信号;5) 瞬时值/累计值/故障状态,工业现场总线通讯接口;6) LCD现场显示,带自清洗系统 | E53: 套 | F53: 1 | G53: 39600 | H53: 39600 | K53: ==MIN(O53,S53,W53) -> 17000 | L53: ==F53*K53 -> 17000 | M53: E+H | N53: 黄13326426530 | O53: 22898 | P53: ==F53*O53 -> 22898 | R53: 武宝凤 13826219800 | S53: 17000 | T53: ==F53*S53 -> 17000 | U53: 西门子 | V53: 张勇勤 18736008728 | W53: 26000 | X53: ==F53*W53 -> 26000 | Y53: 科隆公司（KROHNE）
A54: 4 | B54: 电磁流量计 | C54: 1) DN300,PN1.0Mpa,0~30m3/h,精度%%P0.5%,电源AC220V;2) 分体式,法兰连接,传感器IP68,聚四氟乙烯衬里,钽电极,带接地环等;3) 变送器IP67,传感器电缆15m,带立柱式不锈钢保护箱及附件;4) 带非满管及空管检测功能:在空管时,可靠零输出并显示和输出报警信号;5) 瞬时值/累计值/故障状态,工业现场总线通讯接口;6) LCD现场显示,带自清洗系统 | E54: 套 | F54: 1 | G54: 76000 | H54: 76000 | K54: ==MIN(O54,S54,W54) -> 31960 | L54: ==F54*K54 -> 31960 | M54: E+H | N54: 黄13326426530 | O54: 31960 | P54: ==F54*O54 -> 31960 | R54: 武宝凤 13826219800 | S54: 33000 | T54: ==F54*S54 -> 33000 | U54: 西门子 | V54: 张勇勤 18736008728 | W54: 35400 | X54: ==F54*W54 -> 35400 | Y54: 科隆公司（KROHNE）
A55: 5 | B55: 电磁流量计 | C55: 1) DN50,PN1.0Mpa,0~5m3/h,精度%%P0.5%,电源AC220V;2) 分体式,法兰连接,传感器IP68,聚四氟乙烯衬里,钽电极,带接地环等;3) 变送器IP67,传感器电缆15m,带立柱式不锈钢保护箱及附件;4) 带非满管及空管检测功能:在空管时,可靠零输出并显示和输出报警信号;5) 瞬时值/累计值/故障状态,工业现场总线通讯接口;6) LCD现场显示,带自清洗系统 | E55: 套 | F55: 1 | G55: 18200 | H55: 18200 | K55: ==MIN(O55,S55,W55) -> 14890 | L55: ==F55*K55 -> 14890 | M55: E+H | N55: 黄13326426530 | O55: 14890 | P55: ==F55*O55 -> 14890 | R55: 武宝凤 13826219800 | S55: 24350 | T55: ==F55*S55 -> 24350 | U55: 西门子 | V55: 张勇勤 18736008728 | W55: 30000 | X55: ==F55*W55 -> 30000 | Y55: 科隆公司（KROHNE）
A56: 6 | B56: 多通道有毒气体检测仪 (氧气、毒气和可燃气体) | C56: 1) 控制器电源输入: DC24V%%P10%, 50Hz;电源输出:DC24V%%P10%;2) 报警方式:声、光报警,数字及光柱显示;控制器及每路探测器均带独立声光报警;3) 工作温度:-20%%DC~+55%%DC; 工作湿度:≤95%RH, 不凝露;4) 背光TFT彩色触摸屏,全中文菜单操作; 带温、湿度监测功能；5) 内置防浪涌功能, 有效防止感应雷及浪涌对设备的伤害;6) 功耗:正常及报警不大于7W/路;自带24V后备电源(5小时电量)；7) 壁挂式控制器,8通道,不锈钢外壳,防护等级IP66, 防爆: 不低于Exd IIBT6;8) 输出信号:Modbus协议 RS485工业现场总线;每路探头带2级报警(自定义);9) 支持8路气体检测,气体检测探头输入信号:带RS485工业现场总线长度≥100米；10) 附气体检测探头(均独立, 不锈钢IP67,防爆: 不低于ExdIIBT6;精度%%P1%FS):1# H2S: 0-25mg/m3; 2# CH4: 0-100%LEL; 3#NH3: 0-100ppm;4# O2: 0-25%VOL; 5# 温度: -40%%DC~120%%DC; 6# 湿度: 0%RH~100%RH; | E56: 套 | F56: 6 | G56: 30000 | H56: 180000 | K56: ==MIN(O56,S56,W56) -> 28458 | L56: ==F56*K56 -> 170748 | M56: 英思科 | O56: 28458 | P56: ==F56*O56 -> 170748 | Q56: 罗斯蒙特 | U56: 霍尼威尔 | Y56: 科尔康
A57: 十二 | B57: 进水在线监测系统
A58: 1 | B58: 水质自动采样器 | C58: 1) 全天候型,恒温控制;2) 吸液高度/距离/体积:8米/30米/20~200ml;3) 流量值/故障状态,RS485工业现场总线通讯接口;4) 远控或定时或按污水流量等比例自动采样;5) 满足国家标准HJ 353-2019的要求;带不锈钢保护柜IP54及附件;6) 具有采集瞬时水样及混合水样,混匀及暂存水样、自动润洁及排空混匀桶,以及留样功能;7) 采样方式:瞬时采样、分时混合采样、等比例混合采样;8) 供样方式:双桶轮换( A、B桶);混合方式:空气混合; 9) 人机界面:7寸触摸屏,TFT 液晶显示,真彩(LED 背光),分辨率:800x480正面防护等级IP65;10) 电源: 220VAC 10%@50 Hz; 环境温度: 5~45℃; 环境湿度:10 ~90%;11) 提供实时数据、历史报表、历史曲线、设置系统的相关参数。RS485工业现场总线通讯接口;12) 满足国家标准HJ 353-2019的要求; 带不锈钢保护柜IP54及附件; | E58: 套 | F58: 1 | G58: 95954.046 | H58: 95954.05 | K58: ==MIN(O58,S58,W58) -> 53000 | L58: ==F58*K58 -> 53000 | M58: HACH | N58: 张锐熙15626146220 | O58: 170000 | P58: ==F58*O58 -> 170000 | Q58: E+H （格雷斯普） | R58: 黄13326426530 | S58: 53000 | T58: ==F58*S58 -> 53000 | U58: HOTEC
A59: 2 | B59: 环保数据采集传输仪 | C59: 1) 满足规范HJ353-2019及HJ 212-2017的一切要求;2) 可协调统一运行水污染源在线监测系统,采集、储存、显示监测数据及运行日志,向监控中心平台上传污染源监测数据;3) 可控制水质自动采样单元采样、送样及留样等操作;4) 可触发水污染源在线监测仪器进行测量、标液核查和校准等操作。5) 可读取各个水污染源在线监测仪器的测量数据,并实现实时数据、小时均值和日均值等项目的查询与显示,并通过数据采集传输仪上传至监控中心平台。6) 记录并上传的污染源监测数据,上报数据应带有时间和数据状态标识7) 数据控制单元可生成、显示各水污染源在线监测仪器监测数据的日、月、年统计表;8) 配置备用电源,在断电时数据采集传输仪可继续工作6h以上;9) 数据采集传输仪平均无故障连续运行时问应不小于17000h;10) 输入、输出端口应各有不少于2路冗余作为备用端口;11) 支持GPRS/3G/4G无线及以太网有线网络传输,8路RS485,支持多中心传送;12) 10英寸及以上TFT液晶触摸屏:13) 满足管理部门及当地环保门的一切技术要求; | E59: 套 | F59: 1 | G59: 22389.279 | H59: 22389.28 | K59: ==MIN(O59,S59,W59) -> 8000 | L59: ==F59*K59 -> 8000 | M59: 化一（原博控） | N59: 张锐熙15626146220 | O59: 10000 | P59: ==F59*O59 -> 10000 | Q59: E+H （博控） | R59: 黄13326426530 | S59: 8000 | T59: ==F59*S59 -> 8000
A60: 十三 | B60: 出水在线监测系统
A61: 1 | B61: 预处理、控制单元及自动采样器 | C61: 1) 全天候型,恒温控制;2) 吸液高度/距离/体积:8米/30米/20~200ml;3) 流量值/故障状态,RS485工业现场总线通讯接口;4) 远控或定时或按污水流量等比例自动采样;5) 满足国家标准HJ 353-2019的要求;带不锈钢保护柜IP54及附件;6) 具有采集瞬时水样及混合水样,混匀及暂存水样、自动润洁及排空混匀桶,以及留样功能;7) 采样方式:瞬时采样、分时混合采样、等比例混合采样;8) 供样方式:双桶轮换( A、B桶);混合方式:空气混合; 9) 人机界面:7寸触摸屏,TFT 液晶显示,真彩(LED 背光),分辨率:800x480正面防护等级IP65;10) 电源: 220VAC 10%@50 Hz; 环境温度: 5~45℃; 环境湿度:10 ~90%;11) 提供实时数据、历史报表、历史曲线、设置系统的相关参数。RS485工业现场总线通讯接口;12) 满足国家标准HJ 353-2019的要求; 带不锈钢保护柜IP54及附件; | E61: 套 | F61: 1 | G61: 95954.05 | H61: 95954.05 | K61: ==MIN(O61,S61,W61) -> 75300 | L61: ==F61*K61 -> 75300 | M61: HACH | N61: 张锐熙15626146220 | O61: 170000 | P61: ==F61*O61 -> 170000 | Q61: E+H （伊创ETI，格雷斯普） | R61: 黄13326426530 | S61: 75300 | T61: ==F61*S61 -> 75300 | U61: HOTEC
A62: 2 | B62: 环保数据采集传输仪 | C62: 1) 满足规范HJ353-2019及HJ 212-2017的一切要求;2) 可协调统一运行水污染源在线监测系统,采集、储存、显示监测数据及运行日志,向监控中心平台上传污染源监测数据;3) 可控制水质自动采样单元采样、送样及留样等操作;4) 可触发水污染源在线监测仪器进行测量、标液核查和校准等操作。5) 可读取各个水污染源在线监测仪器的测量数据,并实现实时数据、小时均值和日均值等项目的查询与显示,并通过数据采集传输仪上传至监控中心平台。6) 记录并上传的污染源监测数据,上报数据应带有时间和数据状态标识7) 数据控制单元可生成、显示各水污染源在线监测仪器监测数据的日、月、年统计表;8) 配置备用电源,在断电时数据采集传输仪可继续工作6h以上;9) 数据采集传输仪平均无故障连续运行时问应不小于17000h;10) 输入、输出端口应各有不少于2路冗余作为备用端口;11) 支持GPRS/3G/4G无线及以太网有线网络传输,8路RS485,支持多中心传送;12) 10英寸及以上TFT液晶触摸屏:13) 满足管理部门及当地环保门的一切技术要求; | E62: 套 | F62: 1 | G62: 22389.279 | H62: 22389.28 | K62: ==MIN(O62,S62,W62) -> 8000 | L62: ==F62*K62 -> 8000 | M62: 化一（原博控） | N62: 张锐熙15626146220 | O62: 10000 | P62: ==F62*O62 -> 10000 | Q62: E+H （博控） | R62: 黄13326426530 | S62: 8000 | T62: ==F62*S62 -> 8000
A63: 十四 | B63: 网络安全防护系统
A64: 1 | B64: 工业防火墙 | C64: (1) 工业防火墙,DIN35导轨式,DC24V直流工业冗余电源; IP40;(2) 产品硬件应采用工业级芯片、无风扇、电源冗余、重负荷铝合金全封闭设计。(3) 标配4个10/100/1000Mbps自适应业务端口(支持2路ByPass)及4个1000LX单模 SC/LC口光纤接口,1个带外RJ45管理端口;(4) 运行模式及部署方式:支持透明模式/路由模式/混合模式/路由部署模式;(5) 系统功能:支持工控协议的深度解析不少于20种(包括但不限于OPC, Modbus TCP,ModbusUDP,Ethernet/IP(CIP),Profinet等;(6) 支持白名单自学习,内置工控威胁漏洞库,工控基础防火墙功能,VPN,NAT等;(7) 在线保护时延<100us; 整机吞吐量≥900Mbps;最大并发连接数(TCP)≥100000;每秒新建连接数(TCP)≥5000;(8) 支持策略安全事件(包括黑名单、白名单、IPMAC、会话连接事件)、规约告警事件、系统事件告警或记录。(9) 具有公安部计算机信息系统安全专用产品销售许可证及公安部认证;(10) 满足《信息安全技术网络安全等级保护基本要求》GB/T 22239不低于二级要求 | E64: 套 | F64: 3 | G64: 40479.809 | H64: 121439.43 | K64: ==MIN(O64,S64,W64) -> 15600 | L64: ==F64*K64 -> 46800 | M64: 威努特 | O64: 111480 | P64: ==F64*O64 -> 334440 | Q64: 北京安盟华御 | R64: 王辰涛 13331007849 | S64: 15600 | T64: ==F64*S64 -> 46800 | U64: 北京神州慧安科技有限公司 | Y64: 深信服科技
A65: 2 | B65: 工控入侵检测系统 | C65: (1) DIN35导轨式,DC24V直流工业冗余电源,4个10/100/1000Mbps自适应电口及4个1000LX单模SC/LC口光纤接口,1个带外RJ45管理端口; IP40;(2) 对网络数据、事件进行实时监测、实时告警、快速识别出系统中存在的非法操作、异常事件及外部攻击。工控网络异常数据或行为识别与检测,工控通讯协议指令级检测与审计,流量日志、攻击日志,白名单自学习,数据留存等功能。(3) 支持无流量监测功能,对指定IP,指定工控协议(比如opcda,iec104等)进行持续监控,一旦出现异常,进行持续报警,直到异常恢复(4) 支持工控协议的深度解析不少于20种(包括但不限于OPC, Modbus TCP,ModbusUDP,Ethernet/IP(CIP),Profinet等;(5) 内置超过1200种公开漏洞库中的漏洞,包含工控设备漏洞、工控系统组态软件漏洞、监控软件、操作系统、应用软件漏洞等,并支持模板方式导入对规则库进行扩展。(6) 具有公安部计算机信息系统安全专用产品销售许可证及公安部认证;(7) 满足《信息安全技术网络安全等级保护基本要求》GB/T22239不低于二级要求 | E65: 套 | F65: 1 | G65: 36142.688 | H65: 36142.69 | K65: ==MIN(O65,S65,W65) -> 13850 | L65: ==F65*K65 -> 13850 | M65: 威努特 | O65: 29500 | P65: ==F65*O65 -> 29500 | Q65: 北京安盟华御 | R65: 王辰涛 13331007849 | S65: 13850 | T65: ==F65*S65 -> 13850 | U65: 北京神州慧安科技有限公司 | Y65: 深信服科技
A66: 3 | B66: 集中安全管理系统 | C66: (1) 标准1U机箱,包括1个10/100/1000M速率RJ45MGMT管理端口,4个10/100/1000M速率RJ45业务端口,2个USB 2.0端口,1个EXT扩展口,1个RJ45Console管理端口。(2) 最多管理100台安全设备,可以管理工业卫士。网络安全设备统一管理、配置、安全策略统一部署,设备状态监控,监测网络的通信流量与安全事件。监控工业卫士状态,对内网设备接入进行管控,统一收集与下发工业卫士白名单。(3) 系统功能:设备状态监视、设备发现、报警分析、安全设备管理、安全策略管理、安全审计日志、用户管理等功能。(4) 支持通过开放的网络协议,接收或吐给第三方设备日志;支持批量安全策略收集和配置;支持基于网络资产的风险关联性分析,从风险阶段、访问关系、服务端口、资产记录等多个角度识别风险。(5) 支持对系统中所有原始数据进行按需备份,并可对备份文件内容进行统计及查看;(6) 满足《信息安全技术网络安全等级保护基本要求》GB/T22239不低于二级要求; | E66: 套 | F66: 1 | G66: 57828.301 | H66: 57828.3 | K66: ==MIN(O66,S66,W66) -> 57400 | L66: ==F66*K66 -> 57400 | M66: 威努特 | O66: 67040 | P66: ==F66*O66 -> 67040 | Q66: 北京安盟华御 | R66: 王辰涛 13331007849 | S66: 57400 | T66: ==F66*S66 -> 57400 | U66: 北京神州慧安科技有限公司 | Y66: 深信服科技
A67: 4 | B67: 堡垒机 | C67: (1)6个千兆电口,1T硬盘,1U机箱,冗余电源。包含100个被管理对象许可;(2)功能包括:用户认证、密码代填、密码代维、访问授权、操作审计、账号管理、认证管理、授权管理、操作管理、单点登陆等功能;(3)密钥登录模式:通过堡垒机生成密钥,下载后放置服务器内,实现单点直接输入账号即可登录操作;(4)支持联动手机Google身份验证动态码,实现双因素认证;可联动自带证书和身份验证动态码结合实现多因素认证;(5)系统支持短信授权申请、审批操作;(6)自动学习模式:可自动学习资产;对学习到的资产可以导入到资产列表中,并可根据导入的资产列表进行详情的编辑;(7)windows的改密至少可以通过ssh、agent、telnet、AD域数字证书这四种方式实现。支持以邮件、FTP上传的方式通知管理员;(8)支持以html、Excel、txt、word、csv、pdf方式输出;(9)具有公安部计算机信息系统安全专用产品销售许可证;(10) 满足《信息安全技术网络安全等级保护基本要求》GB/T22239不低于二级要求。 | E67: 套 | F67: 1 | G67: 46262.64 | H67: 46262.64 | K67: ==MIN(O67,S67,W67) -> 39600 | L67: ==F67*K67 -> 39600 | M67: 威努特 | O67: 39600 | P67: ==F67*O67 -> 39600 | Q67: 北京安盟华御 | R67: 王辰涛 13331007849 | S67: 49600 | T67: ==F67*S67 -> 49600 | U67: 北京神州慧安科技有限公司 | Y67: 深信服科技
A68: 5 | B68: 漏洞扫描系统 | C68: (1)不低于《信息安全技术网络安全等级保护基本要求》GB/T22239二级要求;(2)2U机架设备,1T硬盘,8G内存,6个100/1000M电口,1个RJ45串口,2个USB口,单电源;(3)支持系统漏洞扫描,系统漏洞知识库大于28万条,能够检测各种主流操作系统、应用服务、数据库、网络设备、工控设备等漏洞,支持恶意代码检测、补丁联动。(4)支持WEB网站漏洞扫描,支持敏感关键字检测、网马和暗链检测、网站钓鱼检测,支持Cookie认证、会话录制、漏洞验证等。(5)支持工控漏洞扫描(加强版),支持无损的工控漏洞扫描技术,漏洞知识库数量大于120000条,其中工控专有的漏洞知识库数量大于3000条。(6)支持弱口令扫描,支持SSH、TELNET、SMB、RDP、FTP、POP3、SMTP、SNMP、REDIS、ORACLE、MSSQL、MYSQL、RTSP、SIP、S7-300、VNC等20多种协议。(7)支持恶意代码检测,支持木马后门的离线检查,支持网站恶意代码的离线检查。支持空间资产探测管理,能够全面发现网络中的存活主机、网络设备、数据库,能够自动生成网络拓扑,也可以后期人工修改。(8)支持脆弱性大屏展示,支持通过大屏展示各类漏洞地理分布情况,资产统计,漏洞统计,最新漏洞,风险趋势等。(9)支持在线升级、本地升级、定时升级,每周至少升级一次。报表格式包括:HTML、DOC、PDF、XML等。(10)支持多用户多任务并发扫描。单任务可扫描IP数不少于8192个IP地址,允许最大并发扫描≥100个IP地址,允许最大并发任务≥10个任务。总可扫描IP数量无限制。总可扫描网站数量无限制。 | E68: 套 | F68: 1 | G68: 86742.85 | H68: 86742.85 | K68: ==MIN(O68,S68,W68) -> 39800 | L68: ==F68*K68 -> 39800 | M68: 威努特 | O68: 39800 | P68: ==F68*O68 -> 39800 | Q68: 北京安盟华御 | R68: 王辰涛 13331007849 | S68: 48800 | T68: ==F68*S68 -> 48800 | U68: 北京神州慧安科技有限公司 | Y68: 深信服科技
A69: 6 | B69: 日志审计 | C69: (1)6个千兆电口,2个扩展插槽,1T硬盘,2U机箱,冗余电源;(2)标配综合日志采集模块、数据统计分析模块、异常告警模块、资产管理模块、知识库管理模块等;(3)支持控制采集时间、采集级别、采集范围、采集路径、采集名称、采集文件、多文件采集、采集编码格式、采集正则表达式、自定义采集等;(4)提供可视化关联分析规则编辑视图,可根据实际业务编辑关联分析规则,关联内容支持不少于资产、源地址、源端口、目的地址、目的端口、事件级别、原始日志、关键词等信息;(5)支持实时日志查看,可选择任意时间节点进行查看全部日志或符合时间节点重要事件,无需进行二次查询;(6)支持在告警信息页面,点击统计图,以环形图形式对告警类型进行统计;(7)支持采集网络流量,解析协议不少于ICMP、AMQP、Cassandra、DNS、HTTP、Memcache、MySQL、PgSQL、TNS、Redis、Thrift、MongoDB、NFS、TDS、Sybase、Drda、Dameng、POP、SMTP、达梦等;(8)具有公安部计算机信息系统安全专用产品销售许可证;(9) 满足《信息安全技术网络安全等级保护基本要求》GB/T22239不低于二级要求。 | E69: 套 | F69: 1 | G69: 46262.64 | H69: 46262.64 | K69: ==MIN(O69,S69,W69) -> 49500 | L69: ==F69*K69 -> 49500 | M69: 威努特 | O69: 49500 | P69: ==F69*O69 -> 49500 | Q69: 北京安盟华御 | R69: 王辰涛 13331007849 | S69: 53800 | T69: ==F69*S69 -> 53800 | U69: 北京神州慧安科技有限公司 | Y69: 深信服科技
A70: 7 | B70: 工控安全审计系统 | C70: (1) DIN35导轨式,DC24V直流工业冗余电源; IP40;(2) 产品硬件应采用工业级芯片、无风扇、电源冗余、重负荷铝合金全封闭设计;(3) 4个10/100/1000M速率RJ45业务端口,4个100/1000M速率的SFP业务端口及4个1000LX单模SC/LC口光纤接口,支持电口/光口网络接口扩展。(3) 工控网络异常数据或行为识别与检测,工控通讯协议指令级检测与审计,流量日志、攻击日志,白名单自学习,数据留存等功能;网络安全日志留存时长不少于六个月;(4) 支持对网络数据报文基于IP地址,协议,端口号等元素的会话安全审计;(5) 支持工控协议的深度解析不少于20种(包括但不限于OPC, Modbus TCP,ModbusUDP,Ethernet/IP(CIP),Profinet等;(6) 支持基于机器学习方式自动记录并梳理工控协议中的操作行为规律,并通过这些行为和规则逐步形成白名单防护规则,支持规则的处理动作批量配置。(7) 具有公安部计算机信息系统安全专用产品销售许可证及公安部认证;(8) 满足《信息安全技术网络安全等级保护基本要求》GB/T 22239不低于二级要求 | E70: 套 | F70: 1 | G70: 43371.24 | H70: 43371.24 | K70: ==MIN(O70,S70,W70) -> 29920 | L70: ==F70*K70 -> 29920 | M70: 威努特 | O70: 29920 | P70: ==F70*O70 -> 29920 | Q70: 北京安盟华御 | R70: 王辰涛 13331007849 | S70: 38600 | T70: ==F70*S70 -> 38600 | U70: 北京神州慧安科技有限公司 | Y70: 深信服科技
A71: 8 | B71: 安全卫士软件 | C71: (1) 支持Windows操作系统,含Windows Server2008/2012/2016/2019;Windows XP/7/8/8.1/10操作系统(32位及64位)以及window7嵌入式;(2) 支持对系统进行一键固化操作,自动生成白名单库;支持安装即固化功能(3) 支持在启用白名单防护前提下对Windows中软件更新平台的自动更新软件;支持在启用白名单防护前提下对Windows下信任软件库中软件的安装和更新;(4) 支持安全专用U盘的注册、认证、授权,支持读写权限管理(5) 支持单机部署和网络部署;支持对特定注册表进行防篡改保护、支持对关键业务进程进行防杀保护、支持对操作系统的审核策略、安全选项等进行统一的设置;(6) 具有公安部计算机信息系统安全专用产品销售许可证及公安部认证;(7) 满足《信息安全技术网络安全等级保护基本要求》GB/T 22239不低于二级要求 | E71: 套 | F71: 8 | G71: 3614.27 | H71: 28914.16 | K71: ==MIN(O71,S71,W71) -> 1880 | L71: ==F71*K71 -> 15040 | M71: 威努特 | O71: 16000 | P71: ==F71*O71 -> 128000 | Q71: 北京安盟华御 | R71: 王辰涛 13331007849 | S71: 1880 | T71: ==F71*S71 -> 15040 | U71: 北京神州慧安科技有限公司 | Y71: 深信服科技
A72: 9 | B72: 数据库审计 | C72: (1)满足《信息安全技术网络安全等级保护基本要求》GB/T 22239不低于二级要求;(2)通过SQL语句合并归类实现对数据库语句共性的抽取,提升查询效率,节省存储空间,提供权威机构认可的原理说明;(3)支持与物理设备面板一一对应的网卡模拟展示,可根据实际连线情况实时展示网卡当前状态,包含光/电口识别、网卡连通、数据收发、网卡信息等状态,并以水量方式展示网卡当前负载,且支持面板与表格模式切换。(4)支持在IPV6环境下部署和管理,且支持在纯IPV4环境、纯IPV6环境及IPV4与IPV6混杂环境下对数据库操作行为进行审计,同时产品自身支持以IPV6方式进行管理(5)支持语句大小为30MB内的超长语句的审计与展示,页面不仅展示超长语句全文,还可统计出语句大小。(6)系统支持自定义查询条件和查询结果展示列,并自动记录最近5次的查询条件及内容,方便后续查询。同时,系统根据用户帐号记忆自定义设置,不同用户打开页面时自动加载用户自定义设置.(7)支持对高危报表元素进行二次编辑,使之产生更精确的报表,以图表方式展示各个字段,包括源IP、目标IP、SQL模板、操作方式、操作对象、规则编号、应用程序名的统计情况.(8)具有公安部计算机信息系统安全专用产品销售许可证; | E72: 套 | F72: 1 | K72: ==MIN(O72,S72,W72) -> 47400 | L72: ==F72*K72 -> 47400 | M72: 威努特 | O72: 52300 | P72: ==F72*O72 -> 52300 | Q72: 北京安盟华御 | R72: 王辰涛 13331007849 | S72: 47400 | T72: ==F72*S72 -> 47400 | U72: 北京神州慧安科技有限公司 | Y72: 深信服科技
A73: 十五 | B73: 车辆识别系统设备
B74: 车辆识别系统设备
A75: 1 | B75: 车牌识别摄像机 | C75: 带语音显示屏(内置网络接口模块及总线电源) | E75: 套 | F75: 12 | K75: ==MIN(O75,S75,W75) -> 3800 | L75: ==F75*K75 -> 45600 | M75: 安快 | N75: 叶启灿13827442891 | O75: 5500 | P75: ==F75*O75 -> 66000 | Q75: 捷顺 | R75: 周先生 15279083620 | S75: 3800 | T75: ==F75*S75 -> 45600 | U75: 红门 | Y75: 富士
A76: 2 | B76: 高速自动闸机 | C76: 内置出入口控制器、网络接口模块及总线电源 | E76: 套 | F76: 6 | K76: ==MIN(O76,S76,W76) -> 2500 | L76: ==F76*K76 -> 15000 | M76: 安快 | N76: 叶启灿13827442891 | O76: 2500 | P76: ==F76*O76 -> 15000 | Q76: 捷顺 | R76: 周先生 15279083620 | S76: 29700 | T76: ==F76*S76 -> 178200 | U76: 红门 | Y76: 富士
A77: 3 | B77: 地感线圈 | E77: 套 | F77: 12 | K77: ==MIN(O77,S77,W77) -> 264 | L77: ==F77*K77 -> 3168 | M77: 安快 | N77: 叶启灿13827442891 | O77: 300 | P77: ==F77*O77 -> 3600 | Q77: 捷顺 | R77: 周先生 15279083620 | S77: 264 | T77: ==F77*S77 -> 3168 | U77: 红门 | Y77: 富士
A78: 4 | B78: 无线遥控器 | C78: 用于遥控高速自动闸门机 | E78: 套 | F78: 12 | K78: ==MIN(O78,S78,W78) -> 30 | L78: ==F78*K78 -> 360 | M78: 安快 | N78: 叶启灿13827442891 | O78: 30 | P78: ==F78*O78 -> 360 | Q78: 捷顺 | R78: 周先生 15279083620 | S78: 30 | T78: ==F78*S78 -> 360 | U78: 红门 | Y78: 富士
A79: 5 | B79: 手动控制按钮 | E79: 套 | F79: 12 | K79: ==MIN(O79,S79,W79) -> 80 | L79: ==F79*K79 -> 960 | M79: 安快 | N79: 叶启灿13827442891 | O79: 80 | P79: ==F79*O79 -> 960 | Q79: 捷顺 | R79: 周先生 15279083620 | S79: 100 | T79: ==F79*S79 -> 1200 | U79: 红门 | Y79: 富士
A80: 6 | B80: 车辆管理控制器 | E80: 套 | F80: 12 | K80: ==MIN(O80,S80,W80) -> 400 | L80: ==F80*K80 -> 4800 | M80: 安快 | N80: 叶启灿13827442891 | O80: 400 | P80: ==F80*O80 -> 4800 | Q80: 捷顺 | R80: 周先生 15279083620 | S80: 550 | T80: ==F80*S80 -> 6600 | U80: 红门 | Y80: 富士
A81: 7 | B81: 门卫室管理工作站 | C81: 配套车辆识别系统软件及开发包 | E81: 套 | F81: 4 | K81: ==MIN(O81,S81,W81) -> 8000 | L81: ==F81*K81 -> 32000 | M81: 安快 | N81: 叶启灿13827442891 | O81: 10000 | P81: ==F81*O81 -> 40000 | Q81: 捷顺 | R81: 周先生 15279083620 | S81: 8000 | T81: ==F81*S81 -> 32000 | U81: 红门 | Y81: 富士
A82: 8 | B82: 交换机 | C82: 8口交换机(2单模光口),IP65不锈钢立柱式保护箱 | E82: 套 | F82: 4 | K82: ==MIN(O82,S82,W82) -> 100 | L82: ==F82*K82 -> 400 | M82: 安快 | N82: 叶启灿13827442891 | O82: 100 | P82: ==F82*O82 -> 400 | Q82: 捷顺 | R82: 周先生 15279083620 | S82: 320 | T82: ==F82*S82 -> 1280 | U82: 红门 | Y82: 富士
A83: 9 | B83: 减速带 | E83: 套 | F83: 12 | K83: ==MIN(O83,S83,W83) -> 400 | L83: ==F83*K83 -> 4800 | M83: 安快 | N83: 叶启灿13827442891 | O83: 500 | P83: ==F83*O83 -> 6000 | Q83: 捷顺 | R83: 周先生 15279083620 | S83: 400 | T83: ==F83*S83 -> 4800 | U83: 红门 | Y83: 富士
A84: 10 | B84: 安全岛 | C84: 6000*600*200mm | E84: 套 | F84: 1 | K84: ==MIN(O84,S84,W84) -> 1000 | L84: ==F84*K84 -> 1000 | M84: 安快 | N84: 叶启灿13827442891 | O84: 1000 | P84: ==F84*O84 -> 1000 | Q84: 捷顺 | R84: 周先生 15279083620 | S84: 1300 | T84: ==F84*S84 -> 1300 | U84: 红门 | Y84: 富士
A85: 11 | B85: 防撞立柱 | E85: 套 | F85: 12 | K85: ==MIN(O85,S85,W85) -> 900 | L85: ==F85*K85 -> 10800 | M85: 安快 | N85: 叶启灿13827442891 | O85: 1100 | P85: ==F85*O85 -> 13200 | Q85: 捷顺 | R85: 周先生 15279083620 | S85: 900 | T85: ==F85*S85 -> 10800 | U85: 红门 | Y85: 富士
B86: 车辆识别系统软件
A87: 12 | B87: 车辆识别管理系统 | C87: 出入口控制及车辆管理平台集成设计 | E87: 综 | F87: 1 | K87: ==MIN(O87,S87,W87) -> 0 | L87: ==F87*K87 -> 0 | M87: 安快 | N87: 含于整体设备 | Q87: 捷顺 | R87: 含于整体设备 | U87: 红门 | Y87: 富士
A88: 十七 | B88: 视频监控系统
A89: 1 | B89: 一体化彩色球形摄像机 | C89: 1) 一体化网络变速IP球机,1/1.8"CMOS,0.002Lux;支持PTZ控制;日夜全彩; 2) 白光功能:照射距离80m,具有逆光补偿和白平衡功能,轨迹巡航;配套视频监控软件 3) 4.7-110mm电动变焦镜头,23倍光学变焦,执行机构可360°水平无级旋转,垂直扫描角度15°~90°,视场角57.6°(远)~2.7°(近),音频监听、智能巡航、联动跟踪; 4) 内置数字运动图像检测器; 人脸识别; 动态追踪;动态录像;声光报警;深度学习硬件算法;人车精准分类侦测;异常报警及报警信息推送;符合GB/T17626.2/3/4/6四级标准 5) 含解码器、视频驱动光圈及视频、电源、控制信号浪涌保护器; 6) RJ45接口,支持H.265/H.264/MJPEG,分辨率2560x1440(60Hz:30fps) 7) 含安装支架及IP66保护壳,安装高度不低于3.5米; 8) 含灯光、报警、门磁联动辅助输入/输出节点模块数量:2/2;位置联动预设 | E89: 套 | F89: 152 | K89: ==MIN(O89,S89,W89) -> 3015 | L89: ==F89*K89 -> 458280 | M89: 海康威视 | O89: 3015 | P89: ==F89*O89 -> 458280 | Q89: 浙江大华 | U89: 美电贝尔 | W89: 4961 | X89: ==F89*W89 -> 754072
A90: 2 | B90: 一体化彩色球形摄像机(防爆) | C90: 1) 一体化网络变速IP球机,1/1.8"CMOS,0.002Lux;支持PTZ控制;日夜全彩; 2) 白光功能:照射距离80m,具有逆光补偿和白平衡功能,轨迹巡航;配套视频监控软件 3) 4.7-110mm电动变焦镜头,23倍光学变焦,执行机构可360°水平无级旋转,垂直扫描角度15°~90°,视场角57.6°(远)~2.7°(近),音频监听、智能巡航、联动跟踪; 4) 内置数字运动图像检测器; 人脸识别; 动态追踪;动态录像;声光报警;深度学习硬件算法;人车精准分类侦测;异常报警及报警信息推送;符合GB/T17626.2/3/4/6四级标准 5) 含解码器、视频驱动光圈及视频、电源、控制信号浪涌保护器; 6) RJ45接口,支持H.265/H.264/MJPEG,分辨率2560x1440(60Hz:30fps) 7) 防爆等级不低于Exd IICT6及ExtD A21 T80°C ,含安装支架及IP66保护壳; 8) 含灯光、报警、门磁联动辅助输入/输出节点模块数量:2/2;位置联动预设 | E90: 套 | F90: 4 | K90: ==MIN(O90,S90,W90) -> 4961 | L90: ==F90*K90 -> 19844 | M90: 海康威视 | O90: 6149 | P90: ==F90*O90 -> 24596 | Q90: 浙江大华 | U90: 美电贝尔 | W90: 4961 | X90: ==F90*W90 -> 19844
A91: 3 | B91: 一体化彩色球形摄像机 | C91: 1)一体化网络变速IP球机,1/1.8"CMOS, 0.002Lux;支持PTZ控制;日夜全彩; 2) 白光功能:照射距离80m,具有逆光补偿和白平衡功能,轨迹巡航;配套视频监控软件 3) 3-90mm 电动变焦镜头,30倍光学变焦,执行机构可360°水平无级旋转,垂直扫描角度-15°~90°,视场角57.6°(远)~2.7°(近),音频监听、智能巡航、联动跟踪; 4) 内置数字运动图像检测器; 人脸识别; 动态追踪;声光报警;深度学习硬件算法;人车精准分类侦测;异常报警及报警信息推送;符合GB/T17626.2/3/4/6四级标准; 5) 含解码器、视频驱动光圈及视频、电源、控制信号浪涌保护器; 音频输入输出; 6) RJ45接口,支持H.265/H.264/MJPEG,分辨率2560x1440(60Hz:30fps) 7) 遮阳罩,3.5米立柱/挂墙支架,雨刮,避雷针,含安装支架及IP66保护壳; 8) 含灯光、报警、门磁联动辅助输入/输出节点模块数量:2/2;位置联动预设 | E91: 套 | F91: 31 | K91: ==MIN(O91,S91,W91) -> 2818 | L91: ==F91*K91 -> 87358 | M91: 海康威视 | O91: 2818 | P91: ==F91*O91 -> 87358 | Q91: 浙江大华 | U91: 美电贝尔 | W91: 4399 | X91: ==F91*W91 -> 136369
A92: 4 | B92: 一体化彩色摄像枪机 | C92: 1) 一体化网络枪机,1/1.8"CMOS, 0.002Lux;支持PTZ控制;日夜全彩; 2) 白光功能:照射距离80m,具有逆光补偿和白平衡功能,轨迹巡航;配套视频监控软件 3) 4.7-110mm电动变焦镜头,23倍光学变焦,视场角57.6°(远)~2.7°(近),音频监听; 4) 内置数字运动图像检测器; 人脸识别; 声光报警;深度学习硬件算法;人车精准分类侦测;异常报警及报警信息推送;符合GB/T17626.2/3/4/6四级标准 5) 含解码器、视频驱动光圈及视频、电源、控制信号浪涌保护器; 6) RJ45接口,支持H.265/H.264/MJPEG,分辨率2560x1440(60Hz:30fps) 7) 含安装支架及IP66保护壳,安装高度不低于3.5米; 8) 含灯光、报警输入/输出节点模块数量:2/2; | E92: 套 | F92: 3 | K92: ==MIN(O92,S92,W92) -> 809 | L92: ==F92*K92 -> 2427 | M92: 海康威视 | O92: 809 | P92: ==F92*O92 -> 2427 | Q92: 浙江大华 | U92: 美电贝尔 | W92: 2246 | X92: ==F92*W92 -> 6738
A93: 5 | B93: 一体化彩色摄像枪机 | C93: 1) 一体化网络枪机,1/1.8"CMOS, 0.002Lux;支持PTZ控制;日夜全彩; 2) 白光功能:照射距离80m,具有逆光补偿和白平衡功能,轨迹巡航;配套视频监控软件 3) 4.7-110mm电动变焦镜头,23倍光学变焦,视场角57.6°(远)~2.7°(近),音频监听; 4) 内置数字运动图像检测器; 人脸识别; 声光报警;深度学习硬件算法;人车精准分类侦测;异常报警及报警信息推送;符合GB/T17626.2/3/4/6四级标准 5) 含解码器、视频驱动光圈及视频、电源、控制信号浪涌保护器; 6) RJ45接口,支持H.265/H.264/MJPEG,分辨率2560x1440(60Hz:30fps) 7) 遮阳罩,3.5米立柱/挂墙支架,雨刮,避雷针,含安装支架及IP66保护壳; 8) 含灯光、报警输入/输出节点模块数量:2/2; | E93: 套 | F93: 1 | K93: ==MIN(O93,S93,W93) -> 809 | L93: ==F93*K93 -> 809 | M93: 海康威视 | O93: 809 | P93: ==F93*O93 -> 809 | Q93: 浙江大华 | U93: 美电贝尔 | W93: 2246 | X93: ==F93*W93 -> 2246
A94: 6 | B94: 网络数字型硬盘录像机 | C94: 1) 支持32路网络视频接入,网络视频接入带宽768Mbps,2路HDMI输出(4K分辨率),7英寸液晶触控显示屏; 2) 录像分辨率12MP/8MP/7MP/6MP/5MP/4MP/3MP/1080p/UXGA/720p/VGA/4CIF/2CIF/CIF/QCIF,支持16路同步回放; 3) 12盘位硬盘驱动器,12个SATA接口10TB硬盘(SATA6Gb/s 128M缓存); 4) 4个RJ45 10M/100M/1000M自适应以太网口;1个标准RS-485串行接口; 5) 报警输入:16路;报警输出:8路; 6) 解码格式:H.265、H.264、MPEG4 7) 网络协议:UPnP、SNMP、NTP、SADP、SMTP、NFS、PPPoE、DHCP等; 8) 电源:AC100V~240V,支持单电、冗余电源两种配置;4U标准机架,不死机,断电来电后自动恢复; 9) 工作温度:0°C~+50°C; 工作湿度:10%~90%; | E94: 套 | F94: 2 | K94: ==MIN(O94,S94,W94) -> 24355 | L94: ==F94*K94 -> 48710 | M94: 海康威视 | O94: ==6355+12*1500 -> 24355 | P94: ==F94*O94 -> 48710 | Q94: 浙江大华 | U94: 美电贝尔 | W94: 24365 | X94: ==F94*W94 -> 48730
A95: 7 | B95: 网络数字型硬盘录像机 | C95: 1) 支持64路网络视频入,网络视频接入带宽768Mbps,2路HDMI输出(4K分辨率),7英寸液晶触控显示屏; 2) 录像分辨率12MP/8MP/7MP/6MP/5MP/4MP/3MP/1080p/UXGA/720p/VGA/4CIF/2CIF/CIF/QCIF,支持16路同步回放; 3) 24盘位硬盘驱动器,24个SATA接口10TB硬盘(SATA6Gb/s 128M缓存); 4) 4个RJ45 10M/100M/1000M自适应以太网口;1个标准RS-485串行接口; 5) 报警输入:16路;报警输出:8路; 6) 解码格式:H.265、H.264、MPEG4 7) 网络协议:UPnP、SNMP、NTP、SADP、SMTP、NFS、PPPoE、DHCP等; 8) 电源:AC100V~240V,支持单电、冗余电源两种配置;4U标准机架,不死机,断电来电后自动恢复; 9) 工作温度:0°C~+50°C; 工作湿度:10%~90%; | E95: 套 | F95: 3 | K95: ==MIN(O95,S95,W95) -> 45885 | L95: ==F95*K95 -> 137655 | M95: 海康威视 | O95: ==9885+24*1500 -> 45885 | P95: ==F95*O95 -> 137655 | Q95: 浙江大华 | U95: 美电贝尔 | W95: 50939 | X95: ==F95*W95 -> 152817
A96: 8 | B96: 网络视频机架式解码器 | C96: 1) 提供不少于128路视频输出(BNC接口),128路VGA(DVI/HDMI)视频输出实时MPEG4编码,将以太网上多媒体数据流转换为模拟/数字视频信号; 2) 冗余电源设计,具有掉电保护,上电自动恢复功能;3U标准机箱,19"标准机架 3) 提供10/100 /1000Base-T自适应 RJ45接口及RS232/485接口; 4) 支持TCP/IP,RTP/RCP,HTTP,SNMP,UDP等协议; 5) 提供配套的授权不少于128点的网络视频监控/录像软件供客户机使用。 | E96: 套 | F96: 1 | K96: ==MIN(O96,S96,W96) -> 62016 | L96: ==F96*K96 -> 62016 | M96: 海康威视 | Q96: 浙江大华 | U96: 美电贝尔 | W96: 62016 | X96: ==F96*W96 -> 62016
A97: 9 | B97: 视频光纤收发器 | C97: 1) 光纤接口:1个FC接口;发送器、接收器各一套 2) 光纤类型:单模单纤,9/125um,传输距离:0~20kM; 3) 输出Tx/输入Rx 波长:1310nm/1550nm; 4) 网络接口:2个RJ45,10/100BaseT(x); 5) 标准: IEEE802.3,802.3u,802.3x;交换容量:1.2Gbps; 6) LED指示灯:OPT光纤链路指示灯,PWR电源指示灯; 7) 操作温度:-30~70°C; 存储温度:-40~85° C; 8) IP40外壳金属材质,无风扇; | E97: 对 | F97: 50 | K97: ==MIN(O97,S97,W97) -> 459 | L97: ==F97*K97 -> 22950 | M97: 海康威视 | O97: 459 | P97: ==F97*O97 -> 22950 | Q97: 浙江大华 | U97: 美电贝尔 | W97: 550 | X97: ==F97*W97 -> 27500
A98: 10 | B98: 工业以太网交换机 | C98: 导轨式,RJ45接口:10/100/1000Base-TX自适应口x32; 光纤接口:1000LX单模SC/LC口x4,100LX单模SC/LC口x8; 规格:IP40,防潮型,支持基于国际标准IEC62439-6的环网协议,支持VLAN功能,支持流量控制,存储转发,带网管功能; | E98: 套 | F98: 6 | K98: 15000 | L98: ==F98*K98 -> 90000 | M98: Emerson(GE) | N98: 厂家不配合报价 | Q98: ABB | U98: 西门子 | V98: 武宝凤 13826219800 | W98: 73892 | X98: ==F98*W98 -> 443352 | Y98: 施耐德 | Z98: 李越13826163590
A99: 11 | B99: 工业以太网交换机 | C99: 导轨式,RJ45接口:10/100/1000Base-TX自适应口x16; 光纤接口:1000LX单模SC/LC口x4,100LX单模SC/LC口x8; 规格:IP40,防潮型,支持基于国际标准IEC62439-6的环网协议,支持VLAN功能,支持流量控制,存储转发,带网管功能; | E99: 套 | F99: 5 | K99: 10000 | L99: ==F99*K99 -> 50000 | M99: Emerson(GE) | N99: 厂家不配合报价 | Q99: ABB | U99: 西门子 | V99: 武宝凤 13826219800 | W99: 33210 | X99: ==F99*W99 -> 166050 | Y99: 施耐德 | Z99: 李越13826163590
A100: 12 | B100: 工业以太网交换机 | C100: 导轨式,RJ45接口:10/100/1000Base-TX自适应口x8; 光纤接口:1000LX单模SC/LC口x4; 规格:IP40,防潮型,支持基于国际标准IEC62439-6的环网协议,支持VLAN功能,支持流量控制,存储转发,带网管功能; | E100: 套 | F100: 10 | K100: 8000 | L100: ==F100*K100 -> 80000 | M100: Emerson(GE) | N100: 厂家不配合报价 | Q100: ABB | U100: 西门子 | V100: 武宝凤 13826219800 | W100: 15180 | X100: ==F100*W100 -> 151800 | Y100: 施耐德 | Z100: 李越13826163590
...

Sheet 暖通空调专业
A1: 设备价格表（含税）
A2: 单位工程：暖通空调专业设备
A3: 序号 | B3: 设备名称 | C3: 概算规格、型号 | D3: 施工图预算规格、型号 | E3: 单位 | F3: 数量 | G3: 概算 | I3: 预算数量 | J3: 预算选用价格 | M3: 品牌1 | Q3: 品牌2 | U3: 品牌3 | Y3: 品牌4
G4: 单价(元) | H4: 合价(元) | J4: 建议下浮率 | K4: 单价（元） | L4: 总价（元） | M4: 公司名称 | N4: 联系人、联系电话 | O4: 单价（元） | P4: 总价（元） | Q4: 公司名称 | R4: 联系人、联系电话 | S4: 单价（元） | T4: 总价（元） | U4: 公司名称 | V4: 联系人、联系电话 | W4: 单价（元） | X4: 总价（元） | Y4: 公司名称 | Z4: 联系人、联系电话 | AA4: 单价（元） | AB4: 总价（元）
B5: 地下除臭系统设备(不含污泥干化车间)
B6: 生物滤池 | D6: Q=20000m3/h，尺寸：11.5*7.0*3.0m | E6: 组 | F6: 1 | G6: 1306800 | H6: 1306800 | K6: ==P6*0.6*0.85 -> 642039 | M6: 南方环保 | N6: 程13922450496 | O6: 1258900 | P6: ==F6*O6 -> 1258900 | Q6: 西原环保（上海）股份有限公司 | R6: 徐经理13524653119 | S6: 1395000 | T6: ==S6*F6 -> 1395000
B7: 预洗池 | D7: Q=20000m3/h，尺寸：1.5*7.0*3.0m | E7: 组 | F7: 1 | K7: ==O6*0.4*0.85 -> 428026 | M7: 南方环保 | N7: 程13922450496 | Q7: 西原环保（上海）股份有限公司 | R7: 徐经理13524653119 | S7: 1012500 | T7: ==S7*F7 -> 1012500
B8: 离心风机 | D8: Q=20000m3/h，P=3500Pa，IP55，含隔音罩 | E8: 台 | F8: 2 | K8: ==O8*0.85 -> 40800 | M8: 南方环保 | N8: 程13922450496 | O8: 48000 | P8: ==F8*O8 -> 96000 | Q8: 西原环保（上海）股份有限公司 | R8: 徐经理13524653119 | S8: 65000 | T8: ==S8*F8 -> 130000
B9: 循环水泵 | D9: Q=8m3/h，H=15m，IP55 | E9: 台 | F9: 2 | K9: ==O9*0.85 -> 2465 | M9: 南方环保 | N9: 程13922450496 | O9: 2900 | P9: ==F9*O9 -> 5800 | Q9: 西原环保（上海）股份有限公司 | R9: 徐经理13524653119 | S9: 7500 | T9: ==S9*F9 -> 15000
B10: 喷淋水泵 | D10: Q=8m3/h，H=15m，IP55 | E10: 台 | F10: 2 | K10: ==O10*0.85 -> 2465 | M10: 南方环保 | N10: 程13922450496 | O10: 2900 | P10: ==F10*O10 -> 5800 | Q10: 西原环保（上海）股份有限公司 | R10: 徐经理13524653119 | S10: 4500 | T10: ==S10*F10 -> 9000
B11: 控制柜 | D11: 含PLC，7寸触摸屏和以太网通讯协议，柜体IP55 | E11: 套 | F11: 1 | K11: ==O11*0.85 -> 59670 | M11: 南方环保 | N11: 程13922450496 | O11: 70200 | P11: ==F11*O11 -> 70200 | Q11: 西原环保（上海）股份有限公司 | R11: 徐经理13524653119 | S11: 230000 | T11: ==S11*F11 -> 230000
B12: 水箱 | D12: 1200mm*1000mm*800mm | E12: 套 | F12: 2 | K12: ==O12*0.85 -> 5780 | M12: 南方环保 | N12: 程13922450496 | O12: 6800 | P12: ==F12*O12 -> 13600 | Q12: 西原环保（上海）股份有限公司 | R12: 徐经理13524653119 | S12: 5000 | T12: ==S12*F12 -> 10000
B13: 干簧管高、低液位计 | D13: 带开关量信号输出 | E13: 套 | F13: 2 | K13: ==O13*0.85 -> 255 | M13: 南方环保 | N13: 程13922450496 | O13: 300 | P13: ==F13*O13 -> 600 | Q13: 西原环保（上海）股份有限公司 | R13: 徐经理13524653119 | S13: 2000 | T13: ==S13*F13 -> 4000
B14: 水压压力表 | D14: 电子式，0~0.6MPa，带数字显示及4-20mA信号输出 | E14: 套 | F14: 2 | K14: ==O14*0.85 -> 510 | M14: 南方环保 | N14: 程13922450496 | O14: 600 | P14: ==F14*O14 -> 1200 | Q14: 西原环保（上海）股份有限公司 | R14: 徐经理13524653119 | S14: 300 | T14: ==S14*F14 -> 600
B15: 内部连接风管 | D15: 1250mm*630mm，含直管、管件及支架 | E15: 套 | F15: 1 | K15: ==O15*0.85 -> 9775 | M15: 南方环保 | N15: 程13922450496 | O15: 11500 | P15: ==F15*O15 -> 11500
B16: 电动风阀 | D16: 1250mm*630mm | E16: 个 | F16: 4 | K16: ==O16*0.85 -> 6885 | M16: 南方环保 | N16: 程13922450496 | O16: 8100 | P16: ==F16*O16 -> 32400
B17: 手动采样口 | D17: 法兰式采用口，DN100，带盲板 | E17: 个 | F17: 2 | K17: ==O17*0.85 -> 170 | M17: 南方环保 | N17: 程13922450496 | O17: 200 | P17: ==F17*O17 -> 400
B18: 污染物检测仪 | D18: 硫化氢、氨气检测仪，量程：0-50ppm，精度±p3%（FS），带LED显示，声、光报警及4-20mA信号输出 | E18: 个 | F18: 1 | K18: ==O18*0.85 -> 7905 | M18: 南方环保 | N18: 程13922450496 | O18: 9300 | P18: ==F18*O18 -> 9300
B20: 近期生化池及膜池用生物除臭装置
B21: 生物滤池 | D21: Q=25000m3/h，尺寸：15.5*5.0*3.0m | E21: 组 | F21: 2 | G21: 1447200 | H21: ==G21*2 -> 2894400 | K21: ==O21*0.6*0.85 -> 678300 | M21: 南方环保 | N21: 程13922450496 | O21: 1330000 | P21: ==F21*O21 -> 2660000 | Q21: 西原环保（上海）股份有限公司 | R21: 徐经理13524653119 | S21: 1395000 | T21: ==S21*F21 -> 2790000
B22: 预洗池 | D22: Q=25000m3/h，尺寸：1.5*5.0*3.0m | E22: 组 | F22: 2 | K22: ==O21*0.4*0.85 -> 452200 | M22: 南方环保 | N22: 程13922450496 | Q22: 西原环保（上海）股份有限公司 | R22: 徐经理13524653119 | S22: 1012500 | T22: ==S22*F22 -> 2025000
B23: 离心风机 | D23: Q=25000m3/h，P=3500Pa，IP55，含隔音罩 | E23: 台 | F23: 4 | K23: ==O23*0.85 -> 47430 | M23: 南方环保 | N23: 程13922450496 | O23: 55800 | P23: ==F23*O23 -> 223200 | Q23: 西原环保（上海）股份有限公司 | R23: 徐经理13524653119 | S23: 78000 | T23: ==S23*F23 -> 312000
B24: 循环水泵 | D24: Q=10m3/h，H=15m，IP55 | E24: 台 | F24: 4 | K24: ==O24*0.85 -> 2635 | M24: 南方环保 | N24: 程13922450496 | O24: 3100 | P24: ==F24*O24 -> 12400 | Q24: 西原环保（上海）股份有限公司 | R24: 徐经理13524653119 | S24: 9500 | T24: ==S24*F24 -> 38000
B25: 喷淋水泵 | D25: Q=10m3/h，H=15m，IP55 | E25: 台 | F25: 4 | K25: ==O25*0.85 -> 2635 | M25: 南方环保 | N25: 程13922450496 | O25: 3100 | P25: ==F25*O25 -> 12400 | Q25: 西原环保（上海）股份有限公司 | R25: 徐经理13524653119 | S25: 5500 | T25: ==S25*F25 -> 22000
B26: 控制柜 | D26: 含PLC，7寸触摸屏和以太网通讯协议，柜体IP55 | E26: 套 | F26: 2 | K26: ==O26*0.85 -> 66045 | M26: 南方环保 | N26: 程13922450496 | O26: 77700 | P26: ==F26*O26 -> 155400 | Q26: 西原环保（上海）股份有限公司 | R26: 徐经理13524653119 | S26: 230000 | T26: ==S26*F26 -> 460000
B27: 水箱 | D27: 1200mm*1000mm*800mm | E27: 套 | F27: 4 | K27: ==O27*0.85 -> 5780 | M27: 南方环保 | N27: 程13922450496 | O27: 6800 | P27: ==F27*O27 -> 27200 | Q27: 西原环保（上海）股份有限公司 | R27: 徐经理13524653119 | S27: 5000 | T27: ==S27*F27 -> 20000
B28: 干簧管高、低液位计 | D28: 带开关量信号输出 | E28: 套 | F28: 4 | K28: ==O28*0.85 -> 255 | M28: 南方环保 | N28: 程13922450496 | O28: 300 | P28: ==F28*O28 -> 1200 | Q28: 西原环保（上海）股份有限公司 | R28: 徐经理13524653119 | S28: 2000 | T28: ==S28*F28 -> 8000
B29: 水压压力表 | D29: 电子式，0~0.6MPa，带数字显示及4-20mA信号输出 | E29: 套 | F29: 4 | K29: ==O29*0.85 -> 510 | M29: 南方环保 | N29: 程13922450496 | O29: 600 | P29: ==F29*O29 -> 2400 | Q29: 西原环保（上海）股份有限公司 | R29: 徐经理13524653119 | S29: 300 | T29: ==S29*F29 -> 1200
B30: 内部连接风管 | D30: 1250mm*630mm，含直管、管件及支架 | E30: 套 | F30: 2 | K30: ==O30*0.85 -> 9775 | M30: 南方环保 | N30: 程13922450496 | O30: 11500 | P30: ==F30*O30 -> 23000
B31: 电动风阀 | D31: 1250mm*630mm | E31: 个 | F31: 8 | K31: ==O31*0.85 -> 6885 | M31: 南方环保 | N31: 程13922450496 | O31: 8100 | P31: ==F31*O31 -> 64800
B32: 手动采样口 | D32: 法兰式采用口，DN100，带盲板 | E32: 个 | F32: 4 | K32: ==O32*0.85 -> 170 | M32: 南方环保 | N32: 程13922450496 | O32: 200 | P32: ==F32*O32 -> 800
B33: 污染物检测仪 | D33: 硫化氢、氨气检测仪，量程：0-50ppm，精度±p3%（FS），带LED显示，声、光报警及4-20mA信号输出 | E33: 个 | F33: 2 | K33: ==O33*0.85 -> 7905 | M33: 南方环保 | N33: 程13922450496 | O33: 9300 | P33: ==F33*O33 -> 18600
B34: 污泥干化区生物除臭装置
B35: 组合式生物除臭箱体 | D35: 含填料,支架,各检修口、检修爬梯、系统内风管等附件。Q=37000m3/h,尺寸:22.0m*5.0m*4.2m,预洗+生物过滤+碱洗,生物段停留时间t≥25s,材质:FRP+Q235 | E35: 套 | F35: 1 | K35: ==O35*0.9 -> 2778840 | M35: 南方环保 | N35: 程13922450496 | O35: 3087600 | P35: ==F35*O35 -> 3087600 | Q35: 西原环保（上海）股份有限公司 | R35: 徐经理13524653119 | S35: 3200000 | T35: ==S35*F35 -> 3200000
B36: 应急用活性炭吸附设备 | D36: 含填料,支架,各检修口、检修爬梯、系统内风管等附件。风量37000m3/h,尺寸:3x4x3m,停留时间≥2s,材质:FRP+Q235 | E36: 套 | F36: 1 | K36: ==O36*0.9 -> 855360 | M36: 南方环保 | N36: 程13922450496 | O36: 950400 | P36: ==F36*O36 -> 950400 | Q36: 西原环保（上海）股份有限公司 | R36: 徐经理13524653119 | S36: 900000 | T36: ==S36*F36 -> 900000
B37: 离心风机 | C37: 座地式离心风机，Q=42000m3h，H=350Pa，N=7.5kW | D37: Q=40000m3/h,全压=4000pa,75kw,IP55,含隔音罩,叶轮及壳体用玻璃钢。1用1备,变频控制。 | E37: 台 | F37: 2 | G37: 17220 | K37: ==O37*0.9 -> 62640 | M37: 南方环保 | N37: 程13922450496 | O37: 69600 | P37: ==F37*O37 -> 139200 | Q37: 西原环保（上海）股份有限公司 | R37: 徐经理13524653119 | S37: 123500 | T37: ==S37*F37 -> 247000
B38: 洗涤循环水泵 | D38: Q=40m3/h,H=20m,7.5kw,IP55,FRPP，1用1备 | E38: 台 | F38: 2 | K38: ==O38*0.9 -> 5220 | M38: 南方环保 | N38: 程13922450496 | O38: 5800 | P38: ==F38*O38 -> 11600 | Q38: 西原环保（上海）股份有限公司 | R38: 徐经理13524653119 | S38: 9500 | T38: ==S38*F38 -> 19000
B39: 化洗循环水泵 | D39: Q=80m3/h,H=20m,11kw,IP55,FRPP，1用1备 | E39: 台 | F39: 2 | K39: ==O39*0.9 -> 7740 | M39: 南方环保 | N39: 程13922450496 | O39: 8600 | P39: ==F39*O39 -> 17200 | Q39: 西原环保（上海）股份有限公司 | R39: 徐经理13524653119 | S39: 7500 | T39: ==S39*F39 -> 15000
B40: 喷淋水泵 | D40: Q=40m3/h,H=20m,7.5kw,IP55,FRPP，1用1备 | E40: 台 | F40: 2 | K40: ==O40*0.9 -> 5220 | M40: 南方环保 | N40: 程13922450496 | O40: 5800 | P40: ==F40*O40 -> 11600 | Q40: 西原环保（上海）股份有限公司 | R40: 徐经理13524653119 | S40: 5500 | T40: ==S40*F40 -> 11000
B41: 水箱 | D41: V=5m3,尺寸:φ1.85*2.3m,PE | E41: 台 | F41: 1 | K41: ==O41*0.9 -> 10800 | M41: 南方环保 | N41: 程13922450496 | O41: 12000 | P41: ==F41*O41 -> 12000 | Q41: 西原环保（上海）股份有限公司 | R41: 徐经理13524653119 | S41: 6500 | T41: ==S41*F41 -> 6500
B42: 储药罐 | D42: V=8m3,尺寸:φ2.13*2.6m,PE | E42: 台 | F42: 1 | K42: ==O42*0.9 -> 16200 | M42: 南方环保 | N42: 程13922450496 | O42: 18000 | P42: ==F42*O42 -> 18000 | Q42: 西原环保（上海）股份有限公司 | R42: 徐经理13524653119 | S42: 12000 | T42: ==S42*F42 -> 12000
B43: 加药计量泵 | D43: Q=250L/h,H=5bar,0.37kw | E43: 台 | F43: 1 | K43: ==O43*0.9 -> 9720 | M43: 南方环保 | N43: 程13922450496 | O43: 10800 | P43: ==F43*O43 -> 10800 | Q43: 西原环保（上海）股份有限公司 | R43: 徐经理13524653119 | S43: 3000 | T43: ==S43*F43 -> 3000
B44: 电控系统 | D44: 含PLC 、触摸屏、变频器,柜体IP54,SS304 | E44: 套 | F44: 1 | K44: ==O44*0.9 -> 92070 | M44: 南方环保 | N44: 程13922450496 | O44: 102300 | P44: ==F44*O44 -> 102300 | Q44: 西原环保（上海）股份有限公司 | R44: 徐经理13524653119 | S44: 300000 | T44: ==S44*F44 -> 300000
B45: 管道式离子发生器
B46: 管道式离子发生器 （含控制柜） | D46: 风量49000m³/h，主风管设计风速约8m/s,对于H2S的净化效率不小于95%,自带F5级中效过滤器.需配置防触电装置，电源:220V,50Hz | E46: 套 | F46: 1 | K46: ==O46*0.8 -> 392000 | M46: 南方环保 | N46: 程13922450496 | O46: 490000 | P46: ==O46*F46 -> 490000
B47: 管道式离子发生器 （含控制柜） | D47: 风量63000m³/h，主风管设计风速约8m/s,对于H2S的净化效率不小于95%,自带F5级中效过滤器.需配置防触电装置，电源:220V,50Hz | E47: 套 | F47: 1 | K47: ==O47*0.8 -> 464000 | M47: 南方环保 | N47: 程13922450496 | O47: 580000 | P47: ==O47*F47 -> 580000
B48: 风机
B49: MARK0001 | D49: 风量（m3/h）：4000，11kw | E49: 台 | F49: 1 | K49: ==O49*0.9 -> 12839.4 | M49: 英飞 | N49: 彭15918711991 | O49: 14266 | P49: ==O49*F49 -> 14266 | Q49: 洛森拒绝报价，理由品牌价差悬殊，无优势 | U49: 科禄格拒绝报价，理由品牌价差悬殊，无优势
B50: MARK0002 | D50: 风量（m3/h）：2500，5.5kw | E50: 台 | F50: 1 | K50: ==O50*0.9 -> 9234.9 | M50: 英飞 | N50: 彭15918711991 | O50: 10261 | P50: ==O50*F50 -> 10261
B51: MARK0003 | D51: 风量（m3/h）：2000，5.5kw | E51: 台 | F51: 1 | K51: ==O51*0.9 -> 9234.9 | M51: 英飞 | N51: 彭15918711991 | O51: 10261 | P51: ==O51*F51 -> 10261
B52: P-B1-1 | D52: 风量（m3/h）：12000，2.2kw | E52: 台 | F52: 1 | K52: ==O52*0.9 -> 10471.5 | M52: 英飞 | N52: 彭15918711991 | O52: 11635 | P52: ==O52*F52 -> 11635
B53: P-B1-2 | D53: 风量（m3/h）：12000，2.2kw | E53: 台 | F53: 1 | K53: ==O53*0.9 -> 10471.5 | M53: 英飞 | N53: 彭15918711991 | O53: 11635 | P53: ==O53*F53 -> 11635
B54: P-B1-3 | C54: 座地式离心风机，Q=5000m3h，H=380Pa，N=1.1kW | D54: 风量（m3/h）：5000，1.1kw | E54: 台 | F54: 1 | G54: 3000 | K54: ==O54*0.9 -> 7420.5 | M54: 英飞 | N54: 彭15918711991 | O54: 8245 | P54: ==O54*F54 -> 8245
B55: P-B1-4 | D55: 风量（m3/h）：12000，2.2kw | E55: 台 | F55: 1 | K55: ==O55*0.9 -> 10471.5 | M55: 英飞 | N55: 彭15918711991 | O55: 11635 | P55: ==O55*F55 -> 11635
B56: P-B1-5 | D56: 风量（m3/h）：12000，2.2kw | E56: 台 | F56: 1 | K56: ==O56*0.9 -> 10471.5 | M56: 英飞 | N56: 彭15918711991 | O56: 11635 | P56: ==O56*F56 -> 11635
B57: P-B1-6 | C57: 座地式离心风机，Q=5500m3h，H=350Pa，N=1.1kW | D57: 风量（m3/h）：5500，1.1kw | E57: 台 | F57: 1 | G57: 3500 | K57: ==O57*0.9 -> 7420.5 | M57: 英飞 | N57: 彭15918711991 | O57: 8245 | P57: ==O57*F57 -> 8245
B58: P-B1-7 | D58: 风量（m3/h）：20000，4kw | E58: 台 | F58: 1 | K58: ==O58*0.9 -> 14583.6 | M58: 英飞 | N58: 彭15918711991 | O58: 16204 | P58: ==O58*F58 -> 16204
B59: P-B1-8 | D59: 风量（m3/h）：5500，1.1kw | E59: 台 | F59: 1 | K59: ==O59*0.9 -> 7420.5 | M59: 英飞 | N59: 彭15918711991 | O59: 8245 | P59: ==O59*F59 -> 8245
B60: P-B1-9 | D60: 风量（m3/h）：24000，4kw | E60: 台 | F60: 1 | K60: ==O60*0.9 -> 19067.4 | M60: 英飞 | N60: 彭15918711991 | O60: 21186 | P60: ==O60*F60 -> 21186
B61: P-B1-10 | D61: 风量（m3/h）：10000，2.2kw | E61: 台 | F61: 1 | K61: ==O61*0.9 -> 9948.6 | M61: 英飞 | N61: 彭15918711991 | O61: 11054 | P61: ==O61*F61 -> 11054
B62: P-B1-11 | D62: 风量（m3/h）：25000，4kw | E62: 台 | F62: 1 | K62: ==O62*0.9 -> 24447.6 | M62: 英飞 | N62: 彭15918711991 | O62: 27164 | P62: ==O62*F62 -> 27164
B63: P-B1-12 | D63: 风量（m3/h）：18000，4kw | E63: 台 | F63: 1 | K63: ==O63*0.9 -> 14583.6 | M63: 英飞 | N63: 彭15918711991 | O63: 16204 | P63: ==O63*F63 -> 16204
B64: P-B1-13 | D64: 风量（m3/h）：25000，4kw | E64: 台 | F64: 1 | K64: ==O64*0.9 -> 24447.6 | M64: 英飞 | N64: 彭15918711991 | O64: 27164 | P64: ==O64*F64 -> 27164
B65: P-B1-14 | D65: 风量（m3/h）：18000，4kw | E65: 台 | F65: 1 | K65: ==O65*0.9 -> 14583.6 | M65: 英飞 | N65: 彭15918711991 | O65: 16204 | P65: ==O65*F65 -> 16204
B66: P-B1-15 | D66: 风量（m3/h）：26000，4kw | E66: 台 | F66: 1 | K66: ==O66*0.9 -> 30415.5 | M66: 英飞 | N66: 彭15918711991 | O66: 33795 | P66: ==O66*F66 -> 33795
B67: P-B1-16 | D67: 风量（m3/h）：5500，1.1kw | E67: 台 | F67: 1 | K67: ==O67*0.9 -> 7420.5 | M67: 英飞 | N67: 彭15918711991 | O67: 8245 | P67: ==O67*F67 -> 8245
B68: P-B1-17 | D68: 风量（m3/h）：15000，4kw | E68: 台 | F68: 1 | G68: 10500 | K68: ==O68*0.9 -> 11960.1 | M68: 英飞 | N68: 彭15918711991 | O68: 13289 | P68: ==O68*F68 -> 13289
B69: P-B1-20 | D69: 风量（m3/h）：35000，5.5kw | E69: 台 | F69: 1 | K69: ==O69*0.9 -> 31296.6 | M69: 英飞 | N69: 彭15918711991 | O69: 34774 | P69: ==O69*F69 -> 34774
B70: P-B1-21 | D70: 风量（m3/h）：35000，5.5kw | E70: 台 | F70: 1 | K70: ==O70*0.9 -> 31296.6 | M70: 英飞 | N70: 彭15918711991 | O70: 34774 | P70: ==O70*F70 -> 34774
B71: P-B1-22 | C71: 座地式离心风机，Q=6000m3h，H=300Pa，N=1.1kW | D71: 风量（m3/h）：6000，1.1kw | E71: 台 | F71: 1 | G71: 3700 | K71: ==O71*0.9 -> 7872.3 | M71: 英飞 | N71: 彭15918711991 | O71: 8747 | P71: ==O71*F71 -> 8747
B72: P-B1-23 | D72: 风量（m3/h）：6000，1.1kw | E72: 台 | F72: 1 | K72: ==O72*0.9 -> 7872.3 | M72: 英飞 | N72: 彭15918711991 | O72: 8747 | P72: ==O72*F72 -> 8747
B73: S-B1-1 | C73: 座地式离心风机，Q=12000m3h，H=250Pa，N=2.2kW | D73: 风量（m3/h）：12000，2.2kw | E73: 台 | F73: 1 | G73: 7200 | K73: ==O73*0.9 -> 11895.3 | M73: 英飞 | N73: 彭15918711991 | O73: 13217 | P73: ==O73*F73 -> 13217
B74: S-B1-2 | D74: 风量（m3/h）：12000，2.2kw | E74: 台 | F74: 1 | K74: ==O74*0.9 -> 11895.3 | M74: 英飞 | N74: 彭15918711991 | O74: 13217 | P74: ==O74*F74 -> 13217
B75: S-B1-3 | C75: 座地式离心风机，Q=24000m3h，H=250Pa，N=2.2kW | D75: 风量（m3/h）：24000，4kw | E75: 台 | F75: 1 | G75: 10560 | K75: ==O75*0.9 -> 19067.4 | M75: 英飞 | N75: 彭15918711991 | O75: 21186 | P75: ==O75*F75 -> 21186
B76: S-B1-4 | D76: 风量（m3/h）：24000，4kw | E76: 台 | F76: 1 | K76: ==O76*0.9 -> 19067.4 | M76: 英飞 | N76: 彭15918711991 | O76: 21186 | P76: ==O76*F76 -> 21186
B77: S-B1-5 | D77: 风量（m3/h）：36000，7.5kw | E77: 台 | F77: 1 | K77: ==O77*0.9 -> 23364 | M77: 英飞 | N77: 彭15918711991 | O77: 25960 | P77: ==O77*F77 -> 25960
B78: S-B1-6 | D78: 风量（m3/h）：6000，1.1kw | E78: 台 | F78: 1 | K78: ==O78*0.9 -> 7420.5 | M78: 英飞 | N78: 彭15918711991 | O78: 8245 | P78: ==O78*F78 -> 8245
B79: S-B1-7 | D79: 风量（m3/h）：36000，7.5kw | E79: 台 | F79: 1 | K79: ==O79*0.9 -> 23364 | M79: 英飞 | N79: 彭15918711991 | O79: 25960 | P79: ==O79*F79 -> 25960
B80: S-B1-8 | D80: 风量（m3/h）：6000，1.1kw | E80: 台 | F80: 1 | K80: ==O80*0.9 -> 7872.3 | M80: 英飞 | N80: 彭15918711991 | O80: 8747 | P80: ==O80*F80 -> 8747
B81: S-B1-9 | C81: 座地式离心风机，Q=18000m3h，H=300Pa，N=1.1kW | D81: 风量（m3/h）：18000，3kw | E81: 台 | F81: 1 | G81: 10520 | K81: ==O81*0.9 -> 17073 | M81: 英飞 | N81: 彭15918711991 | O81: 18970 | P81: ==O81*F81 -> 18970
B82: S-B1-10 | D82: 风量（m3/h）：28000，5.5kw | E82: 台 | F82: 1 | K82: ==O82*0.9 -> 19380.6 | M82: 英飞 | N82: 彭15918711991 | O82: 21534 | P82: ==O82*F82 -> 21534
B83: S-B1-11 | C83: 座地式离心风机，Q=15000m3h，H=200Pa，N=2.2kW | D83: 风量（m3/h）：15000，2.2kw | E83: 台 | F83: 1 | G83: 9000 | K83: ==O83*0.9 -> 13352.4 | M83: 英飞 | N83: 彭15918711991 | O83: 14836 | P83: ==O83*F83 -> 14836
B84: S-B1-12 | D84: 风量（m3/h）：28000，5.5kw | E84: 台 | F84: 1 | K84: ==O84*0.9 -> 19380.6 | M84: 英飞 | N84: 彭15918711991 | O84: 21534 | P84: ==O84*F84 -> 21534
B85: S-B1-13 | C85: 座地式离心风机，Q=25000m3h，H=300Pa，N=2.2kW | D85: 风量（m3/h）：25000，4kw | E85: 台 | F85: 1 | G85: 11000 | K85: ==O85*0.9 -> 19067.4 | M85: 英飞 | N85: 彭15918711991 | O85: 21186 | P85: ==O85*F85 -> 21186
B86: S-B1-14 | C86: 座地式离心风机，Q=26000m3h，H=350Pa，N=4kW | D86: 风量（m3/h）：26000，5.5kw | E86: 台 | F86: 1 | G86: 11500 | K86: ==O86*0.9 -> 19380.6 | M86: 英飞 | N86: 彭15918711991 | O86: 21534 | P86: ==O86*F86 -> 21534
B87: S-B1-15 | D87: 风量（m3/h）：6000，1.1kw | E87: 台 | F87: 1 | K87: ==O87*0.9 -> 7872.3 | M87: 英飞 | N87: 彭15918711991 | O87: 8747 | P87: ==O87*F87 -> 8747
B88: S-B1-18 | C88: 座地式离心风机，Q=28000m3h，H=350Pa，N=4kW | D88: 风量（m3/h）：28000，5.5kw | E88: 台 | F88: 1 | G88: 12040 | K88: ==O88*0.9 -> 21649.5 | M88: 英飞 | N88: 彭15918711991 | O88: 24055 | P88: ==O88*F88 -> 24055
B89: S-B1-19 | D89: 风量（m3/h）：28000，5.5kw | E89: 台 | F89: 1 | K89: ==O89*0.9 -> 21649.5 | M89: 英飞 | N89: 彭15918711991 | O89: 24055 | P89: ==O89*F89 -> 24055
B90: S-B1-20 | C90: 座地式离心风机，Q=3000m3h，H=200Pa，N=1.1kW | D90: 风量（m3/h）：3000，0.37kw | E90: 台 | F90: 1 | G90: 2500 | K90: ==O90*0.9 -> 6857.1 | M90: 英飞 | N90: 彭15918711991 | O90: 7619 | P90: ==O90*F90 -> 7619
B91: S-B1-21 | C91: 座地式离心风机，Q=10000m3h，H=250Pa，N=4kW | D91: 风量（m3/h）：10000，1.5kw | E91: 台 | F91: 1 | G91: 6000 | K91: ==O91*0.9 -> 11441.7 | M91: 英飞 | N91: 彭15918711991 | O91: 12713 | P91: ==O91*F91 -> 12713
B92: P-B2-1 | D92: 风量（m3/h）：45000，11kw | E92: 台 | F92: 1 | K92: ==O92*0.9 -> 29521.8 | M92: 英飞 | N92: 彭15918711991 | O92: 32802 | P92: ==O92*F92 -> 32802
B93: P-B2-2 | D93: 风量（m3/h）：45000，7.5kw | E93: 台 | F93: 1 | K93: ==O93*0.9 -> 31725 | M93: 英飞 | N93: 彭15918711991 | O93: 35250 | P93: ==O93*F93 -> 35250
B94: P-B2-3 | D94: 风量（m3/h）：26000，5.5kw | E94: 台 | F94: 1 | K94: ==O94*0.9 -> 19380.6 | M94: 英飞 | N94: 彭15918711991 | O94: 21534 | P94: ==O94*F94 -> 21534
B95: P-B2-6 | C95: 座地式离心风机，Q=35000m3h，H=300Pa，N=7.5kW | D95: 风量（m3/h）：35000，7.5kw | E95: 台 | F95: 2 | G95: 14350 | K95: ==O95*0.9 -> 23364 | M95: 英飞 | N95: 彭15918711991 | O95: 25960 | P95: ==O95*F95 -> 51920
B96: P-B2-7 | D96: 风量（m3/h）：35000，7.5kw | E96: 台 | F96: 4 | K96: ==O96*0.9 -> 23364 | M96: 英飞 | N96: 彭15918711991 | O96: 25960 | P96: ==O96*F96 -> 103840
B97: S-B2-1 | D97: 风量（m3/h）：45000，7.5kw | E97: 台 | F97: 2 | K97: ==O97*0.9 -> 45333.9 | M97: 英飞 | N97: 彭15918711991 | O97: 50371 | P97: ==O97*F97 -> 100742
B98: S-B2-2 | C98: 座地式离心风机，Q=45000m3h，H=450Pa，N=15kW | D98: 风量（m3/h）：45000，11kw | E98: 台 | F98: 3 | G98: 18450 | K98: ==O98*0.9 -> 29521.8 | M98: 英飞 | N98: 彭15918711991 | O98: 32802 | P98: ==O98*F98 -> 98406
B99: S-B2-3 | D99: 风量（m3/h）：26000，5.5kw | E99: 台 | F99: 8 | K99: ==O99*0.9 -> 19380.6 | M99: 英飞 | N99: 彭15918711991 | O99: 21534 | P99: ==O99*F99 -> 172272
B100: S-B2-6 | C100: 座地式离心风机，Q=36000m3h，H=350Pa，N=2.2kW | D100: 风量（m3/h）：36000，7.5kw | E100: 台 | F100: 2 | G100: 14760 | K100: ==O100*0.9 -> 23364 | M100: 英飞 | N100: 彭15918711991 | O100: 25960 | P100: ==O100*F100 -> 51920
B101: S-B2-7 | D101: 风量（m3/h）：36000，7.5kw | E101: 台 | F101: 1 | K101: ==O101*0.9 -> 23364 | M101: 英飞 | N101: 彭15918711991 | O101: 25960 | P101: ==O101*F101 -> 25960
...

Sheet 建水、消防水工程
A1: 设备价格表（含税）
A2: 单位工程：消防工程设备
A3: 序号 | B3: 设备名称 | C3: 概算规格、型号 | D3: 施工图预算规格、型号 | E3: 单位 | F3: 数量 | G3: 概算 | I3: 预算数量 | J3: 预算选用价格 | M3: 品牌1 | Q3: 品牌2 | U3: 品牌3 | Y3: 品牌4
G4: 单价(元) | H4: 合价(元) | J4: 建议下浮率 | K4: 单价（元） | L4: 总价（元） | M4: 公司名称 | N4: 联系人、联系电话 | O4: 单价（元） | P4: 总价（元） | Q4: 公司名称 | R4: 联系人、联系电话 | S4: 单价（元） | T4: 总价（元） | U4: 公司名称 | V4: 联系人、联系电话 | W4: 单价（元） | X4: 总价（元） | Y4: 公司名称 | Z4: 联系人、联系电话 | AA4: 单价（元） | AB4: 总价（元）
B5: 泵类
B6: 室内消火栓加压泵(S1) | C6: 室内消火栓泵(深井长轴消防泵)Q=40L/s H=80m N=55kW | D6: Q=40L/s H=0.65MPa N=37kW | E6: 台 | F6: 2 | G6: 41589 | H6: ==F6*G6 -> 83178 | M6: 上海凯泉泵业（集团）有限公司广州 分公司 | N6: 胥志龙15821717141 | O6: ==13167+10394/2 -> 18364 | P6: ==O6*F6 -> 36728
B7: 室内自动喷淋加压泵(P1) | C7: 自动喷淋泵(深井长轴消防泵) Q=40L/s H=80m N=55kW | D7: Q=40L/s H=0.52MPa N=30kW | E7: 台 | F7: 2 | G7: 41589 | H7: ==G7*F7 -> 83178 | M7: 上海凯泉泵业（集团）有限公司广州 分公司 | N7: 胥志龙15821717141 | O7: ==10400+9821/2 -> 15310.5 | P7: ==O7*F7 -> 30621
B8: 室内消火栓稳压泵(S2) | C8: 室内消火栓稳压装置（一用一备）Q=1.5L/s H=20m N=1.5kW 带气压罐SQL800*0.6 气压罐调节水容积 150L（成套产品，包含管道附件） | D8: Q=1.0L/S H=0.38MPa N=0.75KW 配套隔膜式气压罐:SQL800x0.6 | E8: 套 | F8: 1 | G8: ==20512.25*1.13 -> 23178.842 | H8: ==F8*G8 -> 23178.842 | M8: 上海凯泉泵业（集团）有限公司广州 分公司 | N8: 胥志龙15821717141 | O8: ==4116+2547+6805 -> 13468 | P8: ==O8*F8 -> 13468
B9: 室内自动喷淋稳压泵(P2) | D9: Q=1.0L/S H=0.38MPa N=0.75KW 配套隔膜式气压罐:SQL800x0.6 | E9: 套 | F9: 1 | M9: 上海凯泉泵业（集团）有限公司广州 分公司 | N9: 胥志龙15821717141 | O9: ==4116+2547+6805 -> 13468 | P9: ==O9*F9 -> 13468
B10: 管道类
B11: 内外壁热镀锌钢管 | C11: 热浸锌镀锌钢管DN25 | D11: DN25*3.2mm，1.0MPa | E11: m | G11: 14.693 | H11: ==G11*F11 -> 0 | M11: 金洲 | N11: 陈经理13802642573 | O11: 15.1 | P11: ==O11*F11 -> 0
B12: 内外壁热镀锌钢管 | D12: DN32*3.5mm，1.0MPa | E12: m | M12: 金洲 | N12: 陈经理13802642573 | O12: 20.76 | P12: ==O12*F12 -> 0
B13: 内外壁热镀锌钢管 | C13: 热浸锌镀锌钢管DN40 | D13: DN40*3.5mm，1.0MPa | E13: m | G13: 21.358 | H13: ==G13*F13 -> 0 | M13: 金洲 | N13: 陈经理13802642573 | O13: 23.9 | P13: ==O13*F13 -> 0
B14: 内外壁热镀锌钢管 | C14: 热浸锌镀锌钢管DN50 | D14: DN50*3.8mm，1.0MPa | E14: m | G14: 35.142 | H14: ==G14*F14 -> 0 | M14: 金洲 | N14: 陈经理13802642573 | O14: 32.23 | P14: ==O14*F14 -> 0
B15: 内外壁热镀锌钢管 | C15: 热浸锌镀锌钢管DN65 | D15: DN65*4.0mm，1.0MPa | E15: m | G15: 45.839 | H15: ==G15*F15 -> 0 | M15: 金洲 | N15: 陈经理13802642573 | O15: 42.27 | P15: ==O15*F15 -> 0
B16: 内外壁热镀锌钢管 | C16: 热浸锌镀锌钢管DN80 | D16: DN80*4.0mm，1.0MPa | E16: m | G16: 59.029 | H16: ==G16*F16 -> 0 | M16: 金洲 | N16: 陈经理13802642573 | O16: 49.77 | P16: ==O16*F16 -> 0
B17: 内外壁热镀锌钢管 | C17: 热浸锌镀锌钢管DN100 | D17: DN100*4.0mm，1.0MPa | E17: m | G17: 82.683 | H17: ==G17*F17 -> 0 | M17: 金洲 | N17: 陈经理13802642573 | O17: 64.1 | P17: ==O17*F17 -> 0
B18: 内外壁热镀锌钢管 | C18: 热浸锌镀锌钢管DN150 | D18: DN150*4.5mm，1.0MPa | E18: m | G18: 45.839 | H18: ==G18*F18 -> 0 | M18: 金洲 | N18: 陈经理13802642573 | O18: 110.07 | P18: ==O18*F18 -> 0
B19: 内外壁热镀锌钢管 | D19: DN200*6.0mm，1.0MPa | E19: m | M19: 金洲 | N19: 陈经理13802642573 | O19: 198.99 | P19: ==O19*F19 -> 0
B20: 内外壁热镀锌钢管 | D20: DN250*6.0mm，1.0MPa | E20: m | M20: 金洲 | N20: 陈经理13802642573 | O20: 264.49 | P20: ==O20*F20 -> 0
B21: 钢塑复合管 | D21: DN25 | E21: m | M21: 金洲 | N21: 陈经理13802642573 | O21: 21.21 | P21: ==O21*F21 -> 0
B22: 钢塑复合管 | D22: DN40 | E22: m | M22: 金洲 | N22: 陈经理13802642573 | O22: 33.43 | P22: ==O22*F22 -> 0
B23: 钢塑复合管 | D23: DN50 | E23: m | M23: 金洲 | N23: 陈经理13802642573 | O23: 45.6 | P23: ==O23*F23 -> 0
B24: 钢塑复合管 | D24: DN65 | E24: m | M24: 金洲 | N24: 陈经理13802642573 | O24: 60.55 | P24: ==O24*F24 -> 0

Sheet 室外景观绿化给排水设备
A1: 设备价格表（含税）
A2: 单位工程：室外景观绿化给排水设备
A3: 序号 | B3: 设备名称 | C3: 概算规格、型号 | D3: 施工图预算规格、型号 | E3: 单位 | F3: 数量 | G3: 概算 | I3: 预算数量 | J3: 预算选用价格 | M3: 品牌1 | Q3: 品牌2 | U3: 品牌3 | Y3: 品牌4
G4: 单价(元) | H4: 合价(元) | J4: 建议下浮率 | K4: 单价（元） | L4: 总价（元） | M4: 公司名称 | N4: 联系人、联系电话 | O4: 单价（元） | P4: 总价（元） | Q4: 公司名称 | R4: 联系人、联系电话 | S4: 单价（元） | T4: 总价（元） | U4: 公司名称 | V4: 联系人、联系电话 | W4: 单价（元） | X4: 总价（元） | Y4: 公司名称 | Z4: 联系人、联系电话 | AA4: 单价（元） | AB4: 总价（元）

Sheet 估算1118修改
A1: 投资估算表
A2: 序号 | B2: 工程或费用名称 | C2: 估 算 价 值（万元） | H2: 技术经济指标 | K2: 备注
C3: 建筑工程 | D3: 设备及工器具购置 | E3: 安装工程 | F3: 其他费用 | G3: 合 计 | H3: 单位 | I3: 数量 | J3: 单位价值 （元） | L3: 工程费限价 | M3: 差额 | N3: 设计费限价 | O3: 差额 | P3: 总投限价 | Q3: ==G74+G73+G75+G77+G84++G86+G88+G90+G91+G89+G92+G93+G94+#REF!+#REF!-G74-I74*(90+85)/10000 -> #REF! | S3: ==I74+I73+I75+I77+I84++I86+I88+I90+I91+I89+I92+I93+I94-I74 -> 94263.53 | T3: ==Q3/S3*10000 -> #REF!
A4: 一 | B4: 第一部分 工程费用 | C4: ==C5+C68 -> 41031.045 | D4: ==D5+D68 -> #VALUE! | E4: ==E5+E68 -> #VALUE! | F4: ==F5+F68 -> 0 | G4: ==SUM(C4:F4) -> #VALUE! | H4: m3/d | I4: 100000 | J4: ==G4/I4*10000 -> #VALUE! | L4: 72700 | M4: ==L4-G4 -> #VALUE! | P4: 85500 | Q4: ==P4-G137 -> 6.7492183
A5: （一） | B5: 净水厂工程 | C5: ==C6+C44 -> 38722.958 | D5: ==D6+D44 -> #VALUE! | E5: ==E6+E44 -> #VALUE! | F5: ==F6+F44 -> 0 | G5: ==SUM(C5:F5) -> #VALUE! | H5: m3/d | I5: ==I4 -> 100000 | J5: ==G5/I5*10000 -> #VALUE!
A6: A | B6: 建筑工程 | C6: ==SUM(C7:C42) -> 38722.958 | D6: ==SUM(D7:D41) -> 0 | E6: ==SUM(E7:E41) -> 0 | F6: ==SUM(F7:F41) -> 0 | G6: ==SUM(C6:F6) -> 38722.958 | H6: m3/d | I6: ==I5 -> 100000 | J6: ==G6/I6*10000 -> 3872.2958 | N6: 126.7 | O6: 232.8 | P6: 11 | R6: ==(N6-7.5)*(O6-7.5)*5.6+(N6-22)*(O6-22)*12.3 -> 421862.6 | S6: ==N6-P6*2 -> 104.7 | T6: ==O6-P6*2 -> 210.8
A7: 1 | B7: 基坑支护 | C7: ==5122.18*1.3 -> 6658.834 | G7: ==SUM(C7:F7) -> 6658.834 | H7: m | I7: 662 | J7: ==C7/I7*10000 -> 100586.62 | M7: 61940 | N7: 45.133 | O7: 18.492 | P7: ==(N7*N7+O7*O7)^(1/2) -> 48.774396 | Q7: ==N7+O7-P7 -> 14.850604
A8: 2 | B8: 土石方工程 | C8: ==(61940*35+291200*1.05*95+94800*1.05*45)/10000 -> 3569.44 | G8: ==SUM(C8:F8) -> 3569.44 | H8: m3 | I8: 467240 | J8: ==C8/I8*10000 -> 76.394144 | M8: 386000 | N8: ==M8-M9 -> 291200
A9: 3 | B9: 地基处理 | C9: ==2167*16*904/10000*1.1*1.03 -> 3551.2172 | G9: ==SUM(C9:F9) -> 3551.2172 | H9: m2 | I9: 22632 | J9: ==C9/I9*10000 -> 1569.1133 | M9: ==69800+25000 -> 94800
A10: 4 | B10: 地下处理厂框架 | C10: ==I10*J10/10000 -> 13709.516 | G10: ==SUM(C10:F10) -> 13709.516 | H10: m2 | I10: 42869.03 | J10: 3198 | L10: ==SUM(C10:C33) -> 20626.524 | M10: 序号 | N10: 名 称 | O10: 单组尺寸或总规模（m/m2） | P10: 结构形式 | Q10: 单位 | R10: 数量 | S10: 备注
A11: 5 | B11: 进水闸门井 | C11: ==I11*J11/10000 -> 306.02342 | G11: ==SUM(C11:F11) -> 306.02342 | H11: m3 | I11: ==9.8*6.4*19 -> 1191.68 | J11: 2568 | K11: 厂区 | M11: 1 | N11: 进水闸门井 | O11: B×L×H=9.8×6.4×19.00 | P11: R.C | Q11: 座 | R11: 1 | S11: 厂区
A12: 6 | B12: 进水泵房及粗格栅 | C12: ==I12*J12/10000 -> 296.36059 | G12: ==SUM(C12:F12) -> 296.36059 | H12: m3 | I12: ==17.6*24.1*12*0.85 -> 4326.432 | J12: 685 | K12: 地下处理区 | L12: ==L10/I10*10000 -> 4811.5212 | M12: 2 | N12: 进水泵房及粗格栅 | O12: B×L×H=17.6×24.10×12.00 | P12: R.C | Q12: 座 | R12: 1 | S12: 地下处理区
A13: 7 | B13: 细格栅 | C13: ==I13*J13/10000 -> 46.300827 | G13: ==SUM(C13:F13) -> 46.300827 | H13: m3 | I13: ==17.6*13.7*3.15*0.8 -> 607.6224 | J13: 762 | K13: 地下处理区 | M13: 3 | N13: 细格栅 | O13: B×L×H=17.6×13.7×3.15 | P13: R.C | Q13: 座 | R13: 1 | S13: 地下处理区
A14: 8 | B14: 曝气沉砂池 | C14: ==I14*J14/10000 -> 291.96717 | G14: ==SUM(C14:F14) -> 291.96717 | H14: m3 | I14: ==20.5*27.4*9.1*0.85 -> 4344.7495 | J14: 672 | K14: 地下处理区 | L14: ==G133 -> #VALUE! | M14: 4 | N14: 曝气沉砂池 | O14: B×L×H=20.5×27.4×9.10 | P14: R.C | Q14: 座 | R14: 1 | S14: 地下处理区
A15: 9 | B15: 精细格栅 | C15: ==I15*J15/10000 -> 49.717395 | G15: ==SUM(C15:F15) -> 49.717395 | H15: m3 | I15: ==210*3.55*0.9 -> 670.95 | J15: 741 | K15: 地下处理区 | M15: 5 | N15: 精细格栅 | O15: S×H=210×3.55 | P15: R.C | Q15: 座 | R15: 1 | S15: 地下处理区
A16: 10 | B16: 生化池 | C16: ==I16*J16/10000 -> 2918.535 | G16: ==SUM(C16:F16) -> 2918.535 | H16: m3 | I16: ==47.6*97.2*10*2*0.95 -> 87907.68 | J16: 332 | K16: 地下处理区 | M16: 6 | N16: 生化池 | O16: B×L×H=47.6×97.2×10 | P16: R.C | Q16: 组 | R16: 2 | S16: 地下处理区
A17: 11 | B17: 二沉池 | C17: ==I17*J17/10000 -> 1584.6943 | G17: ==SUM(C17:F17) -> 1584.6943 | H17: m3 | I17: ==9.05*56.7*(7.2+10)/2*10*0.95 -> 41923.13 | J17: 378 | K17: 地下处理区 | M17: 7 | N17: 二沉池 | O17: B×L×H=9.05×56.7×7.2~10 | P17: R.C | Q17: 组 | R17: 10 | S17: 地下处理区
A18: 12 | B18: 高效沉淀池 | C18: ==I18*J18/10000 -> 242.84251 | G18: ==SUM(C18:F18) -> 242.84251 | H18: m3 | I18: ==17.95*26.1*8.7*0.9 -> 3668.3158 | J18: 662 | K18: 地下处理区 | M18: 8 | N18: 高效沉淀池 | O18: B×L×H=17.95×26.1×8.7 | P18: R.C | Q18: 座 | R18: 1 | S18: 地下处理区
A19: 13 | B19: 出水池及出水泵房 | C19: ==I19*J19/10000 -> 333.62066 | G19: ==SUM(C19:F19) -> 333.62066 | H19: m3 | I19: ==23*29.2*9*0.95 -> 5742.18 | J19: 581 | K19: 地下处理区 | M19: 9 | N19: 出水池及出水泵房 | O19: B×L×H=23.00×29.20×9 | P19: R.C | Q19: 座 | R19: 1 | S19: 地下处理区
A20: 14 | B20: 污泥脱水及干化车间 | C20: ==I20*J20/10000 -> 295.56 | G20: ==SUM(C20:F20) -> 295.56 | H20: m2 | I20: 1642 | J20: 1800 | K20: 地下负一、二层 | M20: 10 | N20: 污泥脱水及干化车间 | O20: 1642 m2 | P20: 框架 | Q20: 处 | R20: 1 | S20: 地下负一、二层
A21: 15 | B21: 加药间 | C21: ==I21*J21/10000 -> 51.75 | G21: ==SUM(C21:F21) -> 51.75 | H21: m2 | I21: 345 | J21: 1500 | K21: 地下处理区 | M21: 11 | N21: 加药间 | O21: 345m2 | P21: 框架 | Q21: 处 | R21: 1 | S21: 地下负一层
A22: 16 | B22: 碳源储池 | C22: ==I22*J22/10000 -> 20.929709 | G22: ==SUM(C22:F22) -> 20.929709 | H22: m3 | I22: ==3.3*7.7*5.2*2 -> 264.264 | J22: 792 | K22: 地下处理区 | M22: 12 | N22: 碳源储池 | O22: B×L×H=3.3×7.7×5.2 | P22: R.C | Q22: 座 | R22: 2 | S22: 地下负一层
A23: 17 | B23: PAC储池 | C23: ==I23*J23/10000 -> 11.583 | G23: ==SUM(C23:F23) -> 11.583 | H23: m3 | I23: ==3*4.5*5.2*2 -> 140.4 | J23: 825 | K23: 地下处理区 | M23: 13 | N23: PAC储池 | O23: B×L×H=3.0×4.5×5.2 | P23: R.C | Q23: 座 | R23: 2 | S23: 地下负一层
A24: 18 | B24: 溶液池 | C24: ==I24*J24/10000 -> 9.4084224 | G24: ==SUM(C24:F24) -> 9.4084224 | H24: m3 | I24: ==4.7*4.8*5.2 -> 117.312 | J24: 802 | K24: 地下处理区 | M24: 14 | N24: 溶液池 | O24: B×L×H=4.7×4.8×5.2 | P24: R.C | Q24: 座 | R24: 1 | S24: 地下负一层
A25: 19 | B25: 鼓风机房 | C25: ==I25*J25/10000 -> 52.02 | G25: ==SUM(C25:F25) -> 52.02 | H25: m2 | I25: 306 | J25: 1700 | K25: 地下处理区 | M25: 15 | N25: 鼓风机房 | O25: 306m2 | P25: 框架 | Q25: 座 | R25: 1 | S25: 地下处理区
A26: 20 | B26: 废液池（高效合建） | C26: ==I26*J26/10000 -> 29.089368 | G26: ==SUM(C26:F26) -> 29.089368 | H26: m3 | I26: ==5.3*8.4*10*0.9 -> 400.68 | J26: 726 | K26: 地下处理区 | M26: 16 | N26: 废液池（高效） | O26: B×L×H=5.3×8.4×10 | P26: R.C | Q26: 座 | R26: 1 | S26: 地下处理区；高效合建
A27: 21 | B27: 废液池 | C27: ==I27*J27/10000 -> 60.888712 | G27: ==SUM(C27:F27) -> 60.888712 | H27: m3 | I27: ==7.7*13.75*10*0.9 -> 952.875 | J27: 639 | K27: 地下处理区 | M27: 17 | N27: 废液池 | O27: B×L×H=7.7×13.75×10 | P27: R.C | Q27: 座 | R27: 1 | S27: 地下处理区
A28: 22 | B28: 调质池 | C28: ==I28*J28/10000 -> 39.742872 | G28: ==SUM(C28:F28) -> 39.742872 | H28: m3 | I28: ==5.9*13*6.8 -> 521.56 | J28: 762 | K28: 地下处理区 | M28: 18 | N28: 调质池 | O28: B×L×H=5.9×13×6.8 | P28: R.C | Q28: 座 | R28: 1 | S28: 地下处理区
A29: 23 | B29: 污泥浓缩池 | C29: ==I29*J29/10000 -> 113.14852 | G29: ==SUM(C29:F29) -> 113.14852 | H29: m3 | I29: ==6*6*3.14*6.8*2 -> 1537.344 | J29: 736 | K29: 地下处理区 | M29: 19 | N29: 污泥浓缩池 | O29: D×H=Ø12×6.8 | P29: R.C | Q29: 座 | R29: 2 | S29: 地下处理区
A30: 24 | B30: 消防水池 | C30: ==I30*J30/10000 -> 36.6366 | G30: ==SUM(C30:F30) -> 36.6366 | H30: m3 | I30: ==7.7*13*5 -> 500.5 | J30: 732 | K30: 地下处理区 | M30: 20 | N30: 消防水池 | O30: B×L×H=13X7.7X5 | P30: R.C | Q30: 座 | R30: 1 | S30: 地下负一层
A31: 25 | B31: 消防泵房 | C31: ==I31*J31/10000 -> 10.5 | G31: ==SUM(C31:F31) -> 10.5 | H31: m2 | I31: 70 | J31: 1500 | K31: 地下处理区 | M31: 21 | N31: 消防泵房 | O31: 70m2 | P31: 框架 | Q31: 座 | R31: 1 | S31: 地下负一层
A32: 26 | B32: 精密过滤池 | C32: ==I32*J32/10000 -> 74.074 | G32: ==SUM(C32:F32) -> 74.074 | H32: m3 | I32: ==13*18.5*5 -> 1202.5 | J32: 616 | K32: 地下处理区 | M32: 22 | N32: 精密过滤池 | O32: B×L×H=13X18.5X5 | P32: R.C | Q32: 座 | R32: 1 | S32: 地下负一层
A33: 27 | B33: 紫外消毒池 | C33: ==I33*J33/10000 -> 41.61564 | G33: ==SUM(C33:F33) -> 41.61564 | H33: m3 | I33: ==8.8*15.5*5*0.9 -> 613.8 | J33: 678 | K33: 地下处理区 | M33: 23 | N33: 紫外消毒池 | O33: B×L×H=8.8X15.5X5 | P33: R.C | Q33: 处 | R33: 1 | S33: 地下负一层
A34: 28 | B34: 厂区管线土建工程 | C34: 602.18 | G34: ==SUM(C34:F34) -> 602.18 | M34: 24 | N34: 综合楼 | O34: 3185.38m2 | P34: 框架 | Q34: 座 | R34: 1 | S34: 地面
A35: 29 | B35: 综合业务用房 | C35: ==I35*J35/10000 -> 1600 | G35: ==SUM(C35:F35) -> 1600 | H35: m2 | I35: 3200 | J35: 5000 | K35: 地面 | M35: 24 | N35: 综合楼 | O35: 3185.38m2 | P35: 框架 | Q35: 座 | R35: 1 | S35: 地面
A36: 30 | B36: 地下通道出入口 | C36: ==I36*J36/10000 -> 288 | G36: ==SUM(C36:F36) -> 288 | H36: m2 | I36: 400 | J36: 7200
A37: 31 | B37: 出水管道 | C37: ==I37*J37/10000 -> 1475.7624 | G37: ==SUM(C37:F37) -> 1475.7624 | H37: m | I37: 1960 | J37: ==4183*1.8 -> 7529.4 | K37: DN1200
A38: 32 | B38: 仓库、机修、危废间 | C38: ==I38*J38/10000 -> 120 | G38: ==SUM(C38:F38) -> 120 | H38: m2 | I38: 400 | J38: 3000 | K38: 地面
A39: 33 | B39: 开关房 | C39: ==I39*J39/10000 -> 45 | G39: ==SUM(C39:F39) -> 45 | H39: m2 | I39: 150 | J39: 3000 | K39: 地面
A40: 34 | B40: 公园管理用房 | C40: ==I40*J40/10000 -> 90 | G40: ==SUM(C40:F40) -> 90 | H40: m2 | I40: 300 | J40: 3000 | K40: 地面
A41: 35 | B41: 疏散楼梯间、风井 | C41: ==I41*J41/10000 -> 71 | G41: ==SUM(C41:F41) -> 71 | H41: m2 | I41: ==300-16 -> 284 | J41: 2500 | K41: 地面
A42: 36 | B42: 风塔 H=16m | C42: ==I42*J42/10000 -> 25 | G42: ==SUM(C42:F42) -> 25 | H42: 座 | I42: 1 | J42: 250000 | K42: 地面
A44: B | B44: 设备及安装工程 | C44: ==SUM(C45:C66) -> 0 | D44: ==SUM(D45:D66) -> #VALUE! | E44: ==SUM(E45:E66) -> #VALUE! | G44: ==SUM(C44:F44) -> #VALUE! | H44: m3/d | I44: 100000 | J44: ==G44/I44*10000 -> #VALUE!
A45: 1 | B45: 进水系统 | D45: ==#REF!H3 -> #VALUE! | E45: ==D45*0.15+50 -> #VALUE! | G45: ==SUM(C45:F45) -> #VALUE! | H45: m3/d | I45: 100000 | J45: ==G45/I45*10000 -> #VALUE!
A46: 2 | B46: 预处理区 | D46: ==设备!H9 -> 2409.75 | E46: ==D46*0.15+55 -> 416.4625 | G46: ==SUM(C46:F46) -> 2826.2125 | H46: m3/d | I46: 100000 | J46: ==G46/I46*10000 -> 282.62125
A47: 3 | B47: 生化池 | D47: ==#REF!H70 -> #VALUE! | E47: ==D47*0.15+80 -> #VALUE! | G47: ==SUM(C47:F47) -> #VALUE! | H47: m3/d | I47: 100000 | J47: ==G47/I47*10000 -> #VALUE!
A48: 4 | B48: 二沉池 | D48: ==#REF!H100 -> #VALUE! | E48: ==D48*0.15+20 -> #VALUE! | G48: ==SUM(C48:F48) -> #VALUE! | H48: m3/d | I48: 100000 | J48: ==G48/I48*10000 -> #VALUE!
A49: 5 | B49: 高效沉淀池 | D49: 2663 | E49: ==D49*0.08+30 -> 243.04 | G49: ==SUM(C49:F49) -> 2906.04 | H49: m3/d | I49: 100000 | J49: ==G49/I49*10000 -> 290.604
A50: 6 | B50: 精密过滤池 | D50: ==#REF!H138 -> #VALUE! | E50: ==D50*0.08+5 -> #VALUE! | G50: ==SUM(C50:F50) -> #VALUE! | H50: m3/d | I50: 100000 | J50: ==G50/I50*10000 -> #VALUE!
A51: 7 | B51: 污泥干化系统 | D51: ==#REF!H142 -> #VALUE! | E51: ==D51*0.1+15 -> #VALUE! | G51: ==SUM(C51:F51) -> #VALUE! | H51: m3/d | I51: 100000 | J51: ==G51/I51*10000 -> #VALUE!
A52: 8 | B52: 消毒及出水泵房 | D52: ==#REF!H179 -> #VALUE! | E52: ==D52*0.15+25 -> #VALUE! | G52: ==SUM(C52:F52) -> #VALUE! | H52: m3/d | I52: 100000 | J52: ==G52/I52*10000 -> #VALUE!
A53: 9 | B53: 鼓风机房 | D53: ==#REF!H192 -> #VALUE! | E53: ==D53*0.1+5 -> #VALUE! | G53: ==SUM(C53:F53) -> #VALUE! | H53: m3/d | I53: 100000 | J53: ==G53/I53*10000 -> #VALUE!
A54: 10 | B54: 加药系统 | D54: ==#REF!H203 -> #VALUE! | E54: ==D54*0.15+3 -> #VALUE! | G54: ==SUM(C54:F54) -> #VALUE! | H54: m3/d | I54: 100000 | J54: ==G54/I54*10000 -> #VALUE!
A55: 11 | B55: 通风及除臭工程 | D55: 2779.03 | E55: 2011.25 | G55: ==SUM(C55:F55) -> 4790.28 | H55: m3/d | I55: 100000 | J55: ==G55/I55*10000 -> 479.028
A56: 12 | B56: 消防工程 | D56: ==#REF!H225 -> #VALUE! | E56: ==D56*0.15+120 -> #VALUE! | G56: ==SUM(C56:F56) -> #VALUE! | H56: m3/d | I56: 100000 | J56: ==G56/I56*10000 -> #VALUE!
A57: 13 | B57: 机修设备 | D57: 10.25 | G57: ==SUM(C57:F57) -> 10.25 | H57: m3/d | I57: 100000 | J57: ==G57/I57*10000 -> 1.025
A58: 14 | B58: 化验设备 | D58: 69.12 | G58: ==SUM(C58:F58) -> 69.12 | H58: m3/d | I58: 100000 | J58: ==G58/I58*10000 -> 6.912
A59: 15 | B59: 运输设备 | D59: 150 | G59: ==SUM(C59:F59) -> 150 | H59: m3/d | I59: 100000 | J59: ==G59/I59*10000 -> 15
A60: 16 | B60: 厂区管线安装工程 | E60: 620.77 | G60: ==SUM(C60:F60) -> 620.77 | H60: m3/d | I60: 100000 | J60: ==G60/I60*10000 -> 62.077
A61: 17 | B61: 电气工程 | D61: 1338.79 | E61: ==D61*0.15+1200 -> 1400.8185 | G61: ==SUM(C61:F61) -> 2739.6085 | H61: m3/d | I61: 100000 | J61: ==G61/I61*10000 -> 273.96085
A62: 18 | B62: 电源外线 | E62: ==I62*J62/10000 -> 540 | G62: ==SUM(C62:F62) -> 540 | H62: m | I62: 3000 | J62: 1800
A63: 19 | B63: 永久外水接驳费用 | E63: 50 | G63: ==SUM(C63:F63) -> 50
A64: 20 | B64: 自动化控制及仪表 | D64: 2310.77 | E64: ==D64*0.15+500 -> 846.6155 | G64: ==SUM(C64:F64) -> 3157.3855 | H64: m3/d | I64: 100000 | J64: ==G64/I64*10000 -> 315.73855
A65: 21 | B65: 火灾报警控制系统 | D65: ==216.75*0.8 -> 173.4 | E65: ==201.12*0.8 -> 160.896 | G65: ==SUM(C65:F65) -> 334.296 | H65: m3/d | I65: 100000 | J65: ==G65/I65*10000 -> 33.4296
A66: 22 | B66: 工器具及生产工具购置费 | D66: 213.97 | G66: ==SUM(C66:F66) -> 213.97 | H66: m3/d | I66: 100000 | J66: ==G66/I66*10000 -> 21.397
C67: ==I67*J67/10000 -> 0 | G67: ==SUM(C67:F67) -> 0
A68: （二） | B68: 厂区平面景观布置 | C68: ==SUM(C69:C94) -> 2308.0869 | D68: 0 | F68: 0 | G68: ==C68 -> 2308.0869 | H68: m3/d | I68: 100000 | J68: ==G68/I68*10000 -> 230.80869 | N68: 项目 | O68: 单位 | P68: 数量 | Q68: 备注 | R68: ==P84+P85 -> 928.64 | T68: 项目 | U68: 单位 | V68: 数量 | W68: 备注
A69: 1 | B69: 铺装（砂基砖） | C69: ==I69*J69/10000 -> 134.57093 | G69: ==C69 -> 134.57093 | H69: ㎡ | I69: 5850.91 | J69: 230 | N69: 铺装（砂基砖） | O69: ㎡ | P69: 2552.96 | T69: 铺装（砂基砖） | U69: ㎡ | V69: 4407.05
A70: 2 | B70: 台阶 | C70: ==I70*J70/10000 -> 15.0467 | G70: ==C70 -> 15.0467 | H70: ㎡ | I70: 354.04 | J70: 425 | K70: 饰面：砂基砖 | N70: 台阶 | O70: ㎡ | P70: 126.7 | Q70: 饰面：砂基砖 | T70: 台阶 | U70: ㎡ | V70: 354.04 | W70: 饰面：砂基砖
A71: 3 | B71: 架空楼梯 | C71: ==I71*J71/10000 -> 33.246 | G71: ==C71 -> 33.246 | H71: ㎡ | I71: 184.7 | J71: 1800 | T71: 架空楼梯 | U71: ㎡ | V71: 191.09
A72: 4 | B72: 汀步 | C72: ==I72*J72/10000 -> 1.26 | G72: ==C72 -> 1.26 | H72: ㎡ | I72: 28 | J72: 450 | N72: 汀步 | O72: ㎡ | P72: 13 | T72: 汀步 | U72: ㎡ | V72: 28
A73: 5 | B73: 草阶 | C73: ==I73*J73/10000 -> 4.16 | G73: ==C73 -> 4.16 | H73: ㎡ | I73: 80 | J73: 520 | N73: 草阶 | O73: ㎡ | P73: 187.07 | T73: 草阶 | U73: m | V73: 80 | W73: 石笼，宽0.4m，高0.2m
A74: 6 | B74: 绿化 | C74: ==I74*J74/10000 -> 581.73952 | G74: ==C74 -> 581.73952 | H74: ㎡ | I74: 36358.72 | J74: 160 | N74: 绿化（雨水花园） | O74: ㎡ | P74: 41197.66 | T74: 绿化（雨水花园） | U74: ㎡ | V74: 38627.35
A75: 7 | B75: 景观水体 | C75: ==I75*J75/10000 -> 47.822488 | G75: ==C75 -> 47.822488 | H75: ㎡ | I75: 1160.74 | J75: 412 | K75: 底部黑色片石 | N75: 景观水体 | O75: ㎡ | P75: 1789.14 | Q75: 底部是黑色片石 | T75: 景观水体 | U75: ㎡ | V75: 907.07 | W75: 底部是黑色片石
A76: 8 | B76: 足球场 | C76: ==I76*J76/10000 -> 222.25 | G76: ==C76 -> 222.25 | H76: ㎡ | I76: 8890 | J76: 250 | K76: 普通草坪 | N76: 湿地景观 | O76: ㎡ | P76: 6792.04 | T76: 足球场 | U76: ㎡ | V76: 8890 | W76: 1个11人球场和1个7人球场
A77: 9 | B77: 层级花池 | C77: ==I77*J77/10000 -> 107.232 | G77: ==C77 -> 107.232 | H77: ㎡ | I77: 1072.32 | J77: 1000 | K77: 共4层，每层1.3米，混凝土挡墙，拉丝石材饰面 | N77: 层级花池 | O77: ㎡ | P77: 7393.87 | Q77: 共4层，每层1.3米，混凝土挡墙，拉丝石材饰面 | R77: ==339.99+336.05+179.81+611.73 -> 1467.58 | T77: 层级花池 | U77: ㎡ | V77: 869.05 | W77: 共4层，每层1.3米，混凝土挡墙，拉丝石材饰面
A78: 10 | B78: 停车场 | C78: ==I78*J78/10000 -> 25.52 | G78: ==C78 -> 25.52 | H78: ㎡ | I78: 797.5 | J78: 320 | N78: 停车场 | O78: ㎡ | P78: 797.5 | T78: 停车场 | U78: ㎡ | V78: 797.5
A79: 11 | B79: 透水沥青路面 | C79: ==I79*J79/10000 -> 322.468 | G79: ==C79 -> 322.468 | H79: ㎡ | I79: 6449.36 | J79: 500 | N79: 透水沥青路面 | O79: ㎡ | P79: 4488.35 | T79: 透水沥青路面 | U79: ㎡ | V79: 6449.36
A80: 12 | B80: 下沉空间侧墙装饰 | C80: ==I80*J80/10000 -> 52.6875 | G80: ==C80 -> 52.6875 | H80: ㎡ | I80: 1053.75 | J80: 500 | K80: 镶嵌塑料草 | N80: 中式景墙 | O80: ㎡ | P80: 108.05 | T80: 中式景墙 | U80: ㎡ | V80: 30
A81: 13 | B81: 体育场地 | C81: ==I81*J81/10000 -> 83.788 | G81: ==C81 -> 83.788 | H81: ㎡ | I81: 2094.7 | J81: 400 | K81: 包含器械 | N81: 下沉空间侧墙装饰 | O81: ㎡ | P81: 1053.75 | T81: 下沉空间侧墙装饰 | U81: ㎡ | V81: 1053.75
A82: 14 | B82: 全龄化活动场地 | C82: ==I82*J82/10000 -> 23.0601 | G82: ==C82 -> 23.0601 | H82: ㎡ | I82: 329.43 | J82: 700 | K82: 包含器械 | N82: 体育场地 | O82: ㎡ | P82: 2975.4 | Q82: 包含器械 | T82: 体育场地 | U82: ㎡ | V82: 2270.44 | W82: 包含器械
A83: 15 | B83: 景观连廊 | C83: ==I83*J83/10000 -> 132.6276 | G83: ==C83 -> 132.6276 | H83: ㎡ | I83: 473.67 | J83: 2800 | K83: 钢结构，外包铝板 | N83: 全龄化活动场地 | O83: ㎡ | P83: 518.49 | Q83: 包含器械 | T83: 全龄化活动场地 | U83: ㎡ | V83: 329.43 | W83: 包含器械
A84: 16 | B84: 景观亭 | C84: ==I84*J84/10000 -> 10 | G84: ==C84 -> 10 | H84: ㎡ | I84: 25 | J84: 4000 | N84: 景观连廊 | O84: ㎡ | P84: 784.64 | Q84: 钢结构，外包铝板 | T84: 景观连廊 | U84: ㎡ | V84: 638.17 | W84: 钢结构，外包铝板
A85: 17 | B85: 树池坐凳 | C85: ==I85*J85/10000 -> 8.7444 | G85: ==C85 -> 8.7444 | H85: ㎡ | I85: 72.87 | J85: 1200 | N85: 景观亭 | O85: ㎡ | P85: 144 | T85: 景观亭 | U85: ㎡ | V85: 25
A86: 18 | B86: 洗手间 | C86: ==I86*J86/10000 -> 28.8 | G86: ==C86 -> 28.8 | H86: ㎡ | I86: 90 | J86: 3200 | N86: 树池坐凳 | O86: ㎡ | P86: 109.39 | T86: 树池坐凳 | U86: ㎡ | V86: 72.87
A87: 19 | B87: 岗亭 | C87: ==I87*J87/10000 -> 4.9 | G87: ==C87 -> 4.9 | H87: ㎡ | I87: 12.25 | J87: 4000 | K87: 成品 | N87: 洗手间 | O87: ㎡ | P87: 40 | T87: 洗手间 | U87: ㎡ | V87: 40
A88: 20 | B88: 海绵城市立体展示空间 | C88: ==I88*J88/10000 -> 16.6344 | G88: ==C88 -> 16.6344 | H88: ㎡ | I88: 277.24 | J88: 600 | N88: 岗亭 | O88: ㎡ | P88: 12.25 | Q88: 成品 | T88: 岗亭 | U88: ㎡ | V88: 12.25 | W88: 成品
A89: 21 | B89: 木平台 | C89: ==I89*J89/10000 -> 51.7395 | G89: ==C89 -> 51.7395 | H89: ㎡ | I89: 1034.79 | J89: 500 | K89: 水泥塑木铺装 | N89: 景观看台 | O89: ㎡ | P89: 460.93 | Q89: 混凝土结构、水泥塑木铺装 | T89: 海绵城市立体展示空间 | U89: ㎡ | V89: 289.28 | W89: 钢化玻璃展示墙、海绵城市生态做法展示
A90: 22 | B90: 升旗台 | C90: ==I90*J90/10000 -> 4.8 | G90: ==C90 -> 4.8 | H90: ㎡ | I90: 24 | J90: 2000 | N90: 木平台 | O90: ㎡ | P90: 1529.24 | Q90: 水泥塑木铺装 | T90: 木平台 | U90: ㎡ | V90: 1034.79 | W90: 水泥塑木铺装
A91: 23 | B91: 景观入口标识（字体） | C91: ==I91*J91/10000 -> 3 | G91: ==C91 -> 3 | H91: 个 | I91: 1 | J91: 30000 | K91: 材质：钢 | N91: 景观栈道 | O91: ㎡ | P91: 4652.3 | Q91: 混凝土结构、水泥塑木铺装，不锈钢栏杆 | T91: 景观栈道 | U91: ㎡ | V91: 2625.34 | W91: 混凝土结构、水泥塑木铺装，不锈钢栏杆
A92: 24 | B92: 配套设施 | C92: ==I92*J92/10000 -> 30 | G92: ==C92 -> 30 | H92: 项 | I92: 1 | J92: 300000 | K92: 坐凳、指示牌、垃圾桶等 | N92: 景观桥 | O92: ㎡ | P92: 165.77 | Q92: 混凝土结构、水泥塑木铺装，不锈钢栏杆 | T92: 升旗台 | U92: ㎡ | V92: 24
A93: 25 | B93: 景观电气 | C93: ==I93*J93/10000 -> 158.37052 | G93: ==C93 -> 158.37052 | H93: ㎡ | I93: 45248.72 | J93: 35 | K93: 包含灯具 | N93: 景观入口标识（字体） | O93: 个 | P93: 1 | Q93: 材质：钢 | T93: 景观入口标识（字体） | U93: 个 | V93: 1 | W93: 材质：钢
A94: 26 | B94: 景观给排水 | C94: ==I94*J94/10000 -> 203.61924 | G94: ==C94 -> 203.61924 | H94: ㎡ | I94: 45248.72 | J94: 45 | K94: 包含海绵措施 | N94: 配套设施 | O94: 项 | P94: 1 | Q94: 坐凳、指示牌、垃圾桶等 | T94: 配套设施 | U94: 项 | V94: 1 | W94: 坐凳、指示牌、垃圾桶等
A96: 二 | B96: 第二部分 工程建设其他费用 | F96: ==SUM(F97:F121)-F99-F104 -> #VALUE! | G96: ==F96 -> #VALUE! | H96: m3/d | I96: 100000 | J96: ==G96/I96*10000 -> #VALUE!
A97: 1 | B97: 建设单位管理费 | F97: ==#REF!F20 -> #VALUE! | G97: ==F97 -> #VALUE! | L97: 284.60116
A98: 2 | B98: 工程建设监理费 | F98: ==#REF!I19*0.8 -> #VALUE! | G98: ==F98 -> #VALUE!
A99: 3 | B99: 项目前期咨询费 | F99: ==SUM(F100) -> #VALUE! | G99: ==F99 -> #VALUE!
A100: 3.1 | B100: 编制可行性研究报告 | F100: ==#REF!D21 -> #VALUE! | G100: ==F100 -> #VALUE!
A101: 4 | B101: 工程勘察费 | F101: ==G4*0.008 -> #VALUE! | G101: ==F101 -> #VALUE! | L101: 581.6 | N101: 304.8
A102: 5 | B102: 工程设计费 | F102: ==#REF!I19*1.18 -> #VALUE! | G102: ==F102 -> #VALUE! | L102: 2439.5 | M102: ==L102*1.1 -> 2683.45 | N102: 566.8
...

Sheet 水务局专家意见回复
A1: 水务局专家意见回复（中部净水厂投资估算） | Z1: 备注 | AA1: 路面结构厚
A2: 微信聊天记录中的专家意见如下：
A3: 单位指标都还比较合理，建议从设计上优化，基坑支护大概压缩130万左右，土石方工程压缩500万左右，地下处理厂框架压缩1000万左右，综合用房300万左右，出水管道、仓库用房、开头房、管理用房250万左右，土建2200万左右，设备及安装工程调2000万左右
A6: 回复意见如下：
D7: 原估算 | G7: 调整估算 | L7: 备注
A8: 序号 | B8: 项目名称 | C8: 单位 | D8: 工程量 | E8: 单价(元） | F8: 金额 （万元） | G8: 要求工程量 | H8: 调减量 | I8: 单价(元） | J8: 建议调减金额（万元） | K8: 金额 （万元）
A9: 1 | B9: 基坑支护 | C9: m | D9: 662 | E9: 100586.62 | F9: ==D9*E9/10000 -> 6658.834 | G9: ==K9/I9*10000 -> 649.07582 | H9: ==G9-D9 -> -12.924185 | I9: ==E9 -> 100586.62 | J9: 130 | K9: ==F9-J9 -> 6528.834 | L9: 长度可调多少？ | Z9: 新建道路 | AA9: 0.48
A10: 2 | B10: 土石方工程 | C10: m3 | D10: 467240 | E10: 76.394144 | F10: ==D10*E10/10000 -> 3569.44 | G10: ==K10/I10*10000 -> 401789.96 | H10: ==G10-D10 -> -65450.043 | I10: ==E10 -> 76.394144 | J10: 500 | K10: ==F10-J10 -> 3069.44 | L10: 土方量可调多少？ | Z10: 新建道路 | AA10: 0
A11: 3 | B11: 地下处理厂框架 | C11: m2 | D11: 42869.03 | E11: 3198 | F11: ==D11*E11/10000 -> 13709.516 | G11: ==K11/I11*10000 -> 39742.076 | H11: ==G11-D11 -> -3126.9543 | I11: ==E11 -> 3198 | J11: 1000 | K11: ==F11-J11 -> 12709.516 | L11: 面积可调多少？ | Z11: 新建道路
A12: 4 | B12: 综合用房 | C12: m2 | D12: 3200 | E12: 5000 | F12: ==D12*E12/10000 -> 1600 | G12: ==K12/I12*10000 -> 2600 | H12: ==G12-D12 -> -600 | I12: ==E12 -> 5000 | J12: 300 | K12: ==F12-J12 -> 1300 | L12: 面积可调多少？ | Z12: 新建道路
A13: 5 | B13: 其他土建 | F13: ==SUM(F14:F17) -> 1730.7624 | J13: 250 | K13: ==F13-J13 -> 1480.7624 | Z13: 新建道路
A14: 5.1 | B14: 出水管道 | C14: m | D14: 1960 | E14: 7529.4 | F14: ==D14*E14/10000 -> 1475.7624 | L14: 出水管道线路长度、管径可调吗？ | Z14: 新建道路
A15: 5.2 | B15: 仓库用房 | C15: m2 | D15: 400 | E15: 3000 | F15: ==D15*E15/10000 -> 120 | L15: 面积可调多少？ | Z15: 新建道路
A16: 5.3 | B16: 开关房 | C16: m2 | D16: 150 | E16: 3000 | F16: ==D16*E16/10000 -> 45 | L16: 面积可调多少？ | Z16: 新建道路
A17: 5.4 | B17: 管理用房 | C17: m2 | D17: 300 | E17: 3000 | F17: ==D17*E17/10000 -> 90 | L17: 面积可调多少？ | Z17: 新建道路
A18: 6 | B18: 设备安装工程 | C18: m3/d | D18: 100000 | E18: 2905.7153 | F18: ==D18*E18/10000 -> 29057.153 | J18: 2000 | K18: ==F18-J18 -> 27057.153 | L18: 能否降低设备档次？能否调减安装工程量？ | Z18: 新建道路
B19: 合计调减金额 | J19: ==J9+J10+J11+J12+J13+J18 -> 4180
B20: 可研工程费 | C20: m3/d | D20: 100000 | E20: ==F20/D20*10000 -> 7008.8197 | F20: 70088.197 | G20: ==D20 -> 100000 | I20: ==K20/G20*10000 -> 6590.8197 | K20: ==F20-J19 -> 65908.197 | Z20: 新建道路
Z21: 新建道路
Z22: 新建道路
Z23: 新建道路
Z24: 新建道路
Z25: 新建道路
Z26: 新建道路
Z27: 新建道路
Z28: 新建道路
Z29: 新建道路
Z33: 新建道路
Z34: 新建道路
Z35: 新建道路
... Z49: 新建道路
P65: ==0.7+0.24*2 -> 1.18 | Q65: ==(3.14*P65*P65*0.25-3.14*0.7*0.7*0.25)*0.15 -> 0.1062576
T67: ==167.1+19.8+28.8+30+130.43 -> 376.13

Sheet 估算1115修改园建
A1: 投资估算表
A2: 序号 | B2: 工程或费用名称 | C2: 估 算 价 值（万元） | H2: 技术经济指标 | K2: 备注
C3: 建筑工程 | D3: 设备及工器具购置 | E3: 安装工程 | F3: 其他费用 | G3: 合 计 | H3: 单位 | I3: 数量 | J3: 单位价值 （元） | L3: 工程费限价 | M3: 差额 | N3: 设计费限价 | O3: 差额 | P3: 总投限价 | Q3: ==G73+G72+G74+G76+G83++G85+G87+G89+G90+G88+G91+G92+G93+G94+G95-G73-I73*(90+85)/10000 -> 485.78254 | S3: ==I73+I72+I74+I76+I83++I85+I87+I89+I90+I88+I91+I92+I93-I73 -> 3929.48 | T3: ==Q3/S3*10000 -> 1236.2515
A4: 一 | B4: 第一部分 工程费用 | C4: ==C5+C67 -> 41983.856 | D4: ==D5+D67 -> #VALUE! | E4: ==E5+E67 -> #VALUE! | F4: ==F5+F67 -> 0 | G4: ==SUM(C4:F4) -> #VALUE! | H4: m3/d | I4: 100000 | J4: ==G4/I4*10000 -> #VALUE! | L4: 72700 | M4: ==L4-G4 -> #VALUE! | P4: 85500 | Q4: ==P4-G133 -> -1332.7242
A5: （一） | B5: 净水厂工程 | C5: ==C6+C44 -> 38949.487 | D5: ==D6+D44 -> #VALUE! | E5: ==E6+E44 -> #VALUE! | F5: ==F6+F44 -> 0 | G5: ==SUM(C5:F5) -> #VALUE! | H5: m3/d | I5: ==I4 -> 100000 | J5: ==G5/I5*10000 -> #VALUE!
A6: A | B6: 建筑工程 | C6: ==SUM(C7:C42) -> 38949.487 | D6: ==SUM(D7:D41) -> 0 | E6: ==SUM(E7:E41) -> 0 | F6: ==SUM(F7:F41) -> 0 | G6: ==SUM(C6:F6) -> 38949.487 | H6: m3/d | I6: ==I5 -> 100000 | J6: ==G6/I6*10000 -> 3894.9487 | N6: 126.7 | O6: 232.8 | P6: 11 | R6: ==(N6-7.5)*(O6-7.5)*5.6+(N6-22)*(O6-22)*12.3 -> 421862.6 | S6: ==N6-P6*2 -> 104.7 | T6: ==O6-P6*2 -> 210.8
A7: 1 | B7: 基坑支护 | C7: ==5122.18*1.3 -> 6658.834 | G7: ==SUM(C7:F7) -> 6658.834 | H7: m | I7: 662 | J7: ==C7/I7*10000 -> 100586.62 | M7: 61940 | N7: 45.133 | O7: 18.492 | P7: ==(N7*N7+O7*O7)^(1/2) -> 48.774396 | Q7: ==N7+O7-P7 -> 14.850604
A8: 2 | B8: 土石方工程 | C8: ==(61940*35+291200*1.05*95+94800*1.05*45)/10000 -> 3569.44 | G8: ==SUM(C8:F8) -> 3569.44 | H8: m3 | I8: 467240 | J8: ==C8/I8*10000 -> 76.394144 | M8: 386000 | N8: ==M8-M9 -> 291200
A9: 3 | B9: 地基处理 | C9: ==2167*16*904/10000*1.1*1.03 -> 3551.2172 | G9: ==SUM(C9:F9) -> 3551.2172 | H9: m2 | I9: 22632 | J9: ==C9/I9*10000 -> 1569.1133 | M9: ==69800+25000 -> 94800
A10: 4 | B10: 地下处理厂框架 | C10: ==I10*J10/10000 -> 13709.516 | G10: ==SUM(C10:F10) -> 13709.516 | H10: m2 | I10: 42869.03 | J10: 3198 | L10: ==SUM(C10:C33) -> 20853.054 | M10: 序号 | N10: 名 称 | O10: 单组尺寸或总规模（m/m2） | P10: 结构形式 | Q10: 单位 | R10: 数量 | S10: 备注
A11: 5 | B11: 进水闸门井 | C11: ==I11*J11/10000 -> 306.02342 | G11: ==SUM(C11:F11) -> 306.02342 | H11: m3 | I11: ==9.8*6.4*19 -> 1191.68 | J11: 2568 | K11: 厂区 | M11: 1 | N11: 进水闸门井 | O11: B×L×H=9.8×6.4×19.00 | P11: R.C | Q11: 座 | R11: 1 | S11: 厂区
A12: 6 | B12: 进水泵房及粗格栅 | C12: ==I12*J12/10000 -> 296.36059 | G12: ==SUM(C12:F12) -> 296.36059 | H12: m3 | I12: ==17.6*24.1*12*0.85 -> 4326.432 | J12: 685 | K12: 地下处理区 | L12: ==L10/I10*10000 -> 4864.3633 | M12: 2 | N12: 进水泵房及粗格栅 | O12: B×L×H=17.6×24.10×12.00 | P12: R.C | Q12: 座 | R12: 1 | S12: 地下处理区
A13: 7 | B13: 细格栅 | C13: ==I13*J13/10000 -> 46.300827 | G13: ==SUM(C13:F13) -> 46.300827 | H13: m3 | I13: ==17.6*13.7*3.15*0.8 -> 607.6224 | J13: 762 | K13: 地下处理区 | M13: 3 | N13: 细格栅 | O13: B×L×H=17.6×13.7×3.15 | P13: R.C | Q13: 座 | R13: 1 | S13: 地下处理区
A14: 8 | B14: 曝气沉砂池 | C14: ==I14*J14/10000 -> 291.96717 | G14: ==SUM(C14:F14) -> 291.96717 | H14: m3 | I14: ==20.5*27.4*9.1*0.85 -> 4344.7495 | J14: 672 | K14: 地下处理区 | M14: 4 | N14: 曝气沉砂池 | O14: B×L×H=20.5×27.4×9.10 | P14: R.C | Q14: 座 | R14: 1 | S14: 地下处理区
A15: 9 | B15: 精细格栅 | C15: ==I15*J15/10000 -> 49.717395 | G15: ==SUM(C15:F15) -> 49.717395 | H15: m3 | I15: ==210*3.55*0.9 -> 670.95 | J15: 741 | K15: 地下处理区 | M15: 5 | N15: 精细格栅 | O15: S×H=210×3.55 | P15: R.C | Q15: 座 | R15: 1 | S15: 地下处理区
A16: 10 | B16: 生化池 | C16: ==I16*J16/10000 -> 3103.1411 | G16: ==SUM(C16:F16) -> 3103.1411 | H16: m3 | I16: ==47.6*97.2*10*2*0.95 -> 87907.68 | J16: 353 | K16: 地下处理区 | M16: 6 | N16: 生化池 | O16: B×L×H=47.6×97.2×10 | P16: R.C | Q16: 组 | R16: 2 | S16: 地下处理区
A17: 11 | B17: 二沉池 | C17: ==I17*J17/10000 -> 1626.6174 | G17: ==SUM(C17:F17) -> 1626.6174 | H17: m3 | I17: ==9.05*56.7*(7.2+10)/2*10*0.95 -> 41923.13 | J17: 388 | K17: 地下处理区 | M17: 7 | N17: 二沉池 | O17: B×L×H=9.05×56.7×7.2~10 | P17: R.C | Q17: 组 | R17: 10 | S17: 地下处理区
A18: 12 | B18: 高效沉淀池 | C18: ==I18*J18/10000 -> 242.84251 | G18: ==SUM(C18:F18) -> 242.84251 | H18: m3 | I18: ==17.95*26.1*8.7*0.9 -> 3668.3158 | J18: 662 | K18: 地下处理区 | M18: 8 | N18: 高效沉淀池 | O18: B×L×H=17.95×26.1×8.7 | P18: R.C | Q18: 座 | R18: 1 | S18: 地下处理区
A19: 13 | B19: 出水池及出水泵房 | C19: ==I19*J19/10000 -> 333.62066 | G19: ==SUM(C19:F19) -> 333.62066 | H19: m3 | I19: ==23*29.2*9*0.95 -> 5742.18 | J19: 581 | K19: 地下处理区 | M19: 9 | N19: 出水池及出水泵房 | O19: B×L×H=23.00×29.20×9 | P19: R.C | Q19: 座 | R19: 1 | S19: 地下处理区
A20: 14 | B20: 污泥脱水及干化车间 | C20: ==I20*J20/10000 -> 295.56 | G20: ==SUM(C20:F20) -> 295.56 | H20: m2 | I20: 1642 | J20: 1800 | K20: 地下负一、二层 | M20: 10 | N20: 污泥脱水及干化车间 | O20: 1642 m2 | P20: 框架 | Q20: 处 | R20: 1 | S20: 地下负一、二层
A21: 15 | B21: 加药间 | C21: ==I21*J21/10000 -> 51.75 | G21: ==SUM(C21:F21) -> 51.75 | H21: m2 | I21: 345 | J21: 1500 | K21: 地下处理区 | M21: 11 | N21: 加药间 | O21: 345m2 | P21: 框架 | Q21: 处 | R21: 1 | S21: 地下负一层
A22: 16 | B22: 碳源储池 | C22: ==I22*J22/10000 -> 20.929709 | G22: ==SUM(C22:F22) -> 20.929709 | H22: m3 | I22: ==3.3*7.7*5.2*2 -> 264.264 | J22: 792 | K22: 地下处理区 | M22: 12 | N22: 碳源储池 | O22: B×L×H=3.3×7.7×5.2 | P22: R.C | Q22: 座 | R22: 2 | S22: 地下负一层
A23: 17 | B23: PAC储池 | C23: ==I23*J23/10000 -> 11.583 | G23: ==SUM(C23:F23) -> 11.583 | H23: m3 | I23: ==3*4.5*5.2*2 -> 140.4 | J23: 825 | K23: 地下处理区 | M23: 13 | N23: PAC储池 | O23: B×L×H=3.0×4.5×5.2 | P23: R.C | Q23: 座 | R23: 2 | S23: 地下负一层
A24: 18 | B24: 溶液池 | C24: ==I24*J24/10000 -> 9.4084224 | G24: ==SUM(C24:F24) -> 9.4084224 | H24: m3 | I24: ==4.7*4.8*5.2 -> 117.312 | J24: 802 | K24: 地下处理区 | M24: 14 | N24: 溶液池 | O24: B×L×H=4.7×4.8×5.2 | P24: R.C | Q24: 座 | R24: 1 | S24: 地下负一层
A25: 19 | B25: 鼓风机房 | C25: ==I25*J25/10000 -> 52.02 | G25: ==SUM(C25:F25) -> 52.02 | H25: m2 | I25: 306 | J25: 1700 | K25: 地下处理区 | M25: 15 | N25: 鼓风机房 | O25: 306m2 | P25: 框架 | Q25: 座 | R25: 1 | S25: 地下处理区
A26: 20 | B26: 废液池（高效合建） | C26: ==I26*J26/10000 -> 29.089368 | G26: ==SUM(C26:F26) -> 29.089368 | H26: m3 | I26: ==5.3*8.4*10*0.9 -> 400.68 | J26: 726 | K26: 地下处理区 | M26: 16 | N26: 废液池（高效） | O26: B×L×H=5.3×8.4×10 | P26: R.C | Q26: 座 | R26: 1 | S26: 地下处理区；高效合建
A27: 21 | B27: 废液池 | C27: ==I27*J27/10000 -> 60.888712 | G27: ==SUM(C27:F27) -> 60.888712 | H27: m3 | I27: ==7.7*13.75*10*0.9 -> 952.875 | J27: 639 | K27: 地下处理区 | M27: 17 | N27: 废液池 | O27: B×L×H=7.7×13.75×10 | P27: R.C | Q27: 座 | R27: 1 | S27: 地下处理区
A28: 22 | B28: 调质池 | C28: ==I28*J28/10000 -> 39.742872 | G28: ==SUM(C28:F28) -> 39.742872 | H28: m3 | I28: ==5.9*13*6.8 -> 521.56 | J28: 762 | K28: 地下处理区 | M28: 18 | N28: 调质池 | O28: B×L×H=5.9×13×6.8 | P28: R.C | Q28: 座 | R28: 1 | S28: 地下处理区
A29: 23 | B29: 污泥浓缩池 | C29: ==I29*J29/10000 -> 113.14852 | G29: ==SUM(C29:F29) -> 113.14852 | H29: m3 | I29: ==6*6*3.14*6.8*2 -> 1537.344 | J29: 736 | K29: 地下处理区 | M29: 19 | N29: 污泥浓缩池 | O29: D×H=Ø12×6.8 | P29: R.C | Q29: 座 | R29: 2 | S29: 地下处理区
A30: 24 | B30: 消防水池 | C30: ==I30*J30/10000 -> 36.6366 | G30: ==SUM(C30:F30) -> 36.6366 | H30: m3 | I30: ==7.7*13*5 -> 500.5 | J30: 732 | K30: 地下处理区 | M30: 20 | N30: 消防水池 | O30: B×L×H=13X7.7X5 | P30: R.C | Q30: 座 | R30: 1 | S30: 地下负一层
A31: 25 | B31: 消防泵房 | C31: ==I31*J31/10000 -> 10.5 | G31: ==SUM(C31:F31) -> 10.5 | H31: m2 | I31: 70 | J31: 1500 | K31: 地下处理区 | M31: 21 | N31: 消防泵房 | O31: 70m2 | P31: 框架 | Q31: 座 | R31: 1 | S31: 地下负一层
A32: 26 | B32: 精密过滤池 | C32: ==I32*J32/10000 -> 74.074 | G32: ==SUM(C32:F32) -> 74.074 | H32: m3 | I32: ==13*18.5*5 -> 1202.5 | J32: 616 | K32: 地下处理区 | M32: 22 | N32: 精密过滤池 | O32: B×L×H=13X18.5X5 | P32: R.C | Q32: 座 | R32: 1 | S32: 地下负一层
A33: 27 | B33: 紫外消毒池 | C33: ==I33*J33/10000 -> 41.61564 | G33: ==SUM(C33:F33) -> 41.61564 | H33: m3 | I33: ==8.8*15.5*5*0.9 -> 613.8 | J33: 678 | K33: 地下处理区 | M33: 23 | N33: 紫外消毒池 | O33: B×L×H=8.8X15.5X5 | P33: R.C | Q33: 处 | R33: 1 | S33: 地下负一层
A34: 28 | B34: 厂区管线土建工程 | C34: 602.18 | G34: ==SUM(C34:F34) -> 602.18 | M34: 24 | N34: 综合楼 | O34: 3185.38m2 | P34: 框架 | Q34: 座 | R34: 1 | S34: 地面
A35: 29 | B35: 综合业务用房 | C35: ==I35*J35/10000 -> 1600 | G35: ==SUM(C35:F35) -> 1600 | H35: m2 | I35: 3200 | J35: 5000 | K35: 地面 | M35: 24 | N35: 综合楼 | O35: 3185.38m2 | P35: 框架 | Q35: 座 | R35: 1 | S35: 地面
A36: 30 | B36: 地下通道出入口 | C36: ==I36*J36/10000 -> 288 | G36: ==SUM(C36:F36) -> 288 | H36: m2 | I36: 400 | J36: 7200
A37: 31 | B37: 出水管道 | C37: ==I37*J37/10000 -> 1475.7624 | G37: ==SUM(C37:F37) -> 1475.7624 | H37: m | I37: 1960 | J37: ==4183*1.8 -> 7529.4 | K37: DN1200
A38: 32 | B38: 仓库、机修、危废间 | C38: ==I38*J38/10000 -> 120 | G38: ==SUM(C38:F38) -> 120 | H38: m2 | I38: 400 | J38: 3000 | K38: 地面
A39: 33 | B39: 开关房 | C39: ==I39*J39/10000 -> 45 | G39: ==SUM(C39:F39) -> 45 | H39: m2 | I39: 150 | J39: 3000 | K39: 地面
A40: 34 | B40: 公园管理用房 | C40: ==I40*J40/10000 -> 90 | G40: ==SUM(C40:F40) -> 90 | H40: m2 | I40: 300 | J40: 3000 | K40: 地面
A41: 35 | B41: 疏散楼梯间、风井 | C41: ==I41*J41/10000 -> 71 | G41: ==SUM(C41:F41) -> 71 | H41: m2 | I41: ==300-16 -> 284 | J41: 2500 | K41: 地面
A42: 36 | B42: 风塔 H=16m | C42: ==I42*J42/10000 -> 25 | G42: ==SUM(C42:F42) -> 25 | H42: 座 | I42: 1 | J42: 250000 | K42: 地面
A44: B | B44: 设备及安装工程 | C44: ==SUM(C45:C65) -> 0 | D44: ==SUM(D45:D65) -> #VALUE! | E44: ==SUM(E45:E65) -> #VALUE! | G44: ==SUM(C44:F44) -> #VALUE! | H44: m3/d | I44: 100000 | J44: ==G44/I44*10000 -> #VALUE!
A45: 1 | B45: 进水系统 | D45: ==#REF!H3 -> #VALUE! | E45: ==D45*0.15+50 -> #VALUE! | G45: ==SUM(C45:F45) -> #VALUE! | H45: m3/d | I45: 100000 | J45: ==G45/I45*10000 -> #VALUE!
A46: 2 | B46: 预处理区 | D46: ==设备!H9 -> 2409.75 | E46: ==D46*0.15+55 -> 416.4625 | G46: ==SUM(C46:F46) -> 2826.2125 | H46: m3/d | I46: 100000 | J46: ==G46/I46*10000 -> 282.62125
A47: 3 | B47: 生化池 | D47: ==#REF!H70 -> #VALUE! | E47: ==D47*0.15+80 -> #VALUE! | G47: ==SUM(C47:F47) -> #VALUE! | H47: m3/d | I47: 100000 | J47: ==G47/I47*10000 -> #VALUE!
A48: 4 | B48: 二沉池 | D48: ==#REF!H100 -> #VALUE! | E48: ==D48*0.15+20 -> #VALUE! | G48: ==SUM(C48:F48) -> #VALUE! | H48: m3/d | I48: 100000 | J48: ==G48/I48*10000 -> #VALUE!
A49: 5 | B49: 高效沉淀池 | D49: 2663 | E49: ==D49*0.08+30 -> 243.04 | G49: ==SUM(C49:F49) -> 2906.04 | H49: m3/d | I49: 100000 | J49: ==G49/I49*10000 -> 290.604
A50: 6 | B50: 精密过滤池 | D50: ==#REF!H138 -> #VALUE! | E50: ==D50*0.08+5 -> #VALUE! | G50: ==SUM(C50:F50) -> #VALUE! | H50: m3/d | I50: 100000 | J50: ==G50/I50*10000 -> #VALUE!
A51: 7 | B51: 污泥干化系统 | D51: ==#REF!H142 -> #VALUE! | E51: ==D51*0.1+15 -> #VALUE! | G51: ==SUM(C51:F51) -> #VALUE! | H51: m3/d | I51: 100000 | J51: ==G51/I51*10000 -> #VALUE!
A52: 8 | B52: 消毒及出水泵房 | D52: ==#REF!H179 -> #VALUE! | E52: ==D52*0.15+25 -> #VALUE! | G52: ==SUM(C52:F52) -> #VALUE! | H52: m3/d | I52: 100000 | J52: ==G52/I52*10000 -> #VALUE!
A53: 9 | B53: 鼓风机房 | D53: ==#REF!H192 -> #VALUE! | E53: ==D53*0.1+5 -> #VALUE! | G53: ==SUM(C53:F53) -> #VALUE! | H53: m3/d | I53: 100000 | J53: ==G53/I53*10000 -> #VALUE!
A54: 10 | B54: 加药系统 | D54: ==#REF!H203 -> #VALUE! | E54: ==D54*0.15+3 -> #VALUE! | G54: ==SUM(C54:F54) -> #VALUE! | H54: m3/d | I54: 100000 | J54: ==G54/I54*10000 -> #VALUE!
A55: 11 | B55: 通风及除臭工程 | D55: 2779.03 | E55: 2011.25 | G55: ==SUM(C55:F55) -> 4790.28 | H55: m3/d | I55: 100000 | J55: ==G55/I55*10000 -> 479.028
A56: 12 | B56: 消防工程 | D56: ==#REF!H225 -> #VALUE! | E56: ==D56*0.15+120 -> #VALUE! | G56: ==SUM(C56:F56) -> #VALUE! | H56: m3/d | I56: 100000 | J56: ==G56/I56*10000 -> #VALUE!
A57: 13 | B57: 机修设备 | D57: 11.25 | G57: ==SUM(C57:F57) -> 11.25 | H57: m3/d | I57: 100000 | J57: ==G57/I57*10000 -> 1.125
A58: 14 | B58: 化验设备 | D58: 69.12 | G58: ==SUM(C58:F58) -> 69.12 | H58: m3/d | I58: 100000 | J58: ==G58/I58*10000 -> 6.912
A59: 15 | B59: 运输设备 | D59: 180 | G59: ==SUM(C59:F59) -> 180 | H59: m3/d | I59: 100000 | J59: ==G59/I59*10000 -> 18
A60: 16 | B60: 厂区管线安装工程 | E60: 620.77 | G60: ==SUM(C60:F60) -> 620.77 | H60: m3/d | I60: 100000 | J60: ==G60/I60*10000 -> 62.077
A61: 17 | B61: 电气工程 | D61: 1338.79 | E61: ==D61*0.15+1200 -> 1400.8185 | G61: ==SUM(C61:F61) -> 2739.6085 | H61: m3/d | I61: 100000 | J61: ==G61/I61*10000 -> 273.96085
A62: 18 | B62: 电源外线 | E62: ==I62*J62/10000 -> 540 | G62: ==SUM(C62:F62) -> 540 | H62: m | I62: 3000 | J62: 1800
A63: 19 | B63: 自动化控制及仪表 | D63: 2310.77 | E63: ==D63*0.15+600 -> 946.6155 | G63: ==SUM(C63:F63) -> 3257.3855 | H63: m3/d | I63: 100000 | J63: ==G63/I63*10000 -> 325.73855
A64: 20 | B64: 火灾报警控制系统 | D64: 216.75 | E64: 201.12 | G64: ==SUM(C64:F64) -> 417.87 | H64: m3/d | I64: 100000 | J64: ==G64/I64*10000 -> 41.787
A65: 21 | B65: 工器具及生产工具购置费 | D65: 220.83 | G65: ==SUM(C65:F65) -> 220.83 | H65: m3/d | I65: 100000 | J65: ==G65/I65*10000 -> 22.083
C66: ==I66*J66/10000 -> 0 | G66: ==SUM(C66:F66) -> 0
A67: （二） | B67: 厂区平面景观布置 | C67: ==SUM(C68:C95) -> 3034.3686 | D67: ==SUM(D68:D95) -> 0 | E67: 0 | F67: ==SUM(F68:F95) -> 0 | G67: ==SUM(C67:F67) -> 3034.3686 | H67: m3/d | I67: 100000 | J67: ==G67/I67*10000 -> 303.43686 | N67: 项目 | O67: 单位 | P67: 数量 | Q67: 备注 | R67: ==P83+P84 -> 928.64 | T67: 项目 | U67: 单位 | V67: 数量 | W67: 备注
A68: 1 | B68: 铺装（砂基砖） | C68: ==I68*J68/10000 -> 161.74497 | G68: ==C68 -> 161.74497 | H68: ㎡ | I68: 7032.39 | J68: 230 | N68: 铺装（砂基砖） | O68: ㎡ | P68: 2552.96 | T68: 铺装（砂基砖） | U68: ㎡ | V68: 4407.05
A69: 2 | B69: 台阶 | C69: ==I69*J69/10000 -> 15.0467 | G69: ==C69 -> 15.0467 | H69: ㎡ | I69: 354.04 | J69: 425 | K69: 饰面：砂基砖 | N69: 台阶 | O69: ㎡ | P69: 126.7 | Q69: 饰面：砂基砖 | T69: 台阶 | U69: ㎡ | V69: 354.04 | W69: 饰面：砂基砖
A70: 3 | B70: 架空楼梯 | C70: ==I70*J70/10000 -> 34.3962 | G70: ==C70 -> 34.3962 | H70: ㎡ | I70: 191.09 | J70: 1800 | T70: 架空楼梯 | U70: ㎡ | V70: 191.09
A71: 4 | B71: 汀步 | C71: ==I71*J71/10000 -> 1.26 | G71: ==C71 -> 1.26 | H71: ㎡ | I71: 28 | J71: 450 | N71: 汀步 | O71: ㎡ | P71: 13 | T71: 汀步 | U71: ㎡ | V71: 28
A72: 5 | B72: 草阶 | C72: ==I72*J72/10000 -> 4.16 | G72: ==C72 -> 4.16 | H72: ㎡ | I72: 80 | J72: 520 | N72: 草阶 | O72: ㎡ | P72: 187.07 | T72: 草阶 | U72: m | V72: 80 | W72: 石笼，宽0.4m，高0.2m
